Workbook
Name Elements: 'Lookup-General'!$AA$1
Name lstAoI: 'Lookup-Influence'!$A$2:$A$17
Name lstBanes: Lists!$I$1:$I$20
Name lstBenefactor: Lists!$O$2:$O$15
Name lstBloodlines: Lists!$E$1:$E$106
Name lstCarthianLaw: Lists!$L$1:$L$14
Name lstClan: Lists!$D$1:$D$6
Name lstCovenant: Lists!$F$1:$F$6
Name lstDevotions: Lists!$K$2:$K$58
Name lstDisciplines: Lists!$G$1:$G$11
Name lstInvictusOaths: Lists!$M$1:$M$16
Name lstManoeuvres: tblManoeuvre[Manoeuvre]
Name lstManoeuvres: tblManoeuvre[Manoeuvre]
Name lstManoeuvres: tblManoeuvre[Manoeuvre]
Name lstManoeuvres: tblManoeuvre[Manoeuvre]
Name lstManoeuvres: tblManoeuvre[Manoeuvre]
Name lstManoeuvres: tblManoeuvre[Manoeuvre]
Name lstManoeuvres: tblManoeuvre[Manoeuvre]
Name lstManoeuvres: tblManoeuvre[Manoeuvre]
Name lstManoeuvres: tblManoeuvre[Manoeuvre]
Name lstManoeuvres: tblManoeuvre[Manoeuvre]
Name lstManoeuvres: tblManoeuvre[Manoeuvre]
Name lstManoeuvres: tblManoeuvre[Manoeuvre]
Name lstManoeuvres: tblManoeuvre[Manoeuvre]
Name lstManoeuvres: tblManoeuvre[Manoeuvre]
Name lstManoeuvres: tblManoeuvre[Manoeuvre]
Name lstManoeuvres: tblManoeuvre[Manoeuvre]
Name lstManoeuvres: tblManoeuvre[Manoeuvre]
Name lstManoeuvres: tblManoeuvre[Manoeuvre]
Name lstManoeuvres: tblManoeuvre[Manoeuvre]
Name lstManoeuvres: tblManoeuvre[Manoeuvre]
Name lstManoeuvres: tblManoeuvre[Manoeuvre]
Name lstManoeuvres: tblManoeuvre[Manoeuvre]
Name lstManoeuvres: tblManoeuvre[Manoeuvre]
Name lstManoeuvres: tblManoeuvre[Manoeuvre]
Name lstManoeuvres: tblManoeuvre[Manoeuvre]
Name lstManoeuvres: tblManoeuvre[Manoeuvre]
Name lstManoeuvres: tblManoeuvre[Manoeuvre]
Name lstManoeuvres: tblManoeuvre[Manoeuvre]
Name lstManoeuvres: tblManoeuvre[Manoeuvre]
Name lstManoeuvres: tblManoeuvre[Manoeuvre]
Name lstManoeuvres: tblManoeuvre[Manoeuvre]
Name lstManoeuvres: tblManoeuvre[Manoeuvre]
Name lstMerits: tblMerits[Merit]
Name lstMerits: tblMerits[Merit]
Name lstMerits: tblMerits[Merit]
Name lstMerits: tblMerits[Merit]
Name lstMerits: tblMerits[Merit]
Name lstMerits: tblMerits[Merit]
Name lstMerits: tblMerits[Merit]
Name lstMerits: tblMerits[Merit]
Name lstMerits: tblMerits[Merit]
Name lstMerits: tblMerits[Merit]
Name lstMerits: tblMerits[Merit]
Name lstMerits: tblMerits[Merit]
Name lstMerits: tblMerits[Merit]
Name lstMerits: tblMerits[Merit]
Name lstMerits: tblMerits[Merit]
Name lstMerits: tblMerits[Merit]
Name lstMerits: tblMerits[Merit]

Sheet Character Data
A1: Sheet | B1: Date | C1: XP Left | D1: XP Total | E1: Player Name | F1: Character Name | G1: Concept | H1: Pronouns | I1: Clan | J1: Clan Icon | K1: Bloodline | L1: Covenant | M1: Covenant Icon | N1: Mask | O1: Dirge | P1: Court Title | Q1: Intelligence | R1: Wits | S1: Resolve | T1: Strength | U1: Dexterity | V1: Stamina | W1: Presence | X1: Manipulation | Y1: Composure | Z1: Academics | AA1: Computer | AB1: Crafts | AC1: Investigation | AD1: Medicine | AE1: Occult | AF1: Politics | AG1: Science | AH1: Athletics | AI1: Brawl | AJ1: Drive | AK1: Firearms | AL1: Larceny | AM1: Stealth | AN1: Survival | AO1: Weaponry | AP1: Animal Ken | AQ1: Empathy | AR1: Expression | AS1: Intimidation | AT1: Persuasion | AU1: Socialise | AV1: Streetwise | AW1: Subterfuge | AX1: Blood Potency | AY1: BP | AZ1: BP Icon | BA1: Health | BB1: Willpower | BC1: Willpower Squares | BD1: Vitae | BE1: Vitae Squares | BF1: Vitae Per Turn | BG1: Can Feed From | BH1: Academics Spec | BI1: Computer Spec | BJ1: Crafts Spec | BK1: Investigation Spec | BL1: Medicine Spec | BM1: Occult Spec | BN1: Politics Spec | BO1: Science Spec | BP1: Athletics Spec | BQ1: Brawl Spec | BR1: Drive Spec | BS1: Firearms Spec | BT1: Larceny Spec | BU1: Stealth Spec | BV1: Survival Spec | BW1: Weaponry Spec | BX1: Animal Ken Spec | BY1: Empathy Spec | BZ1: Expression Spec | CA1: Intimidation Spec | CB1: Persuasion Spec | CC1: Socialise Spec | CD1: Streetwise Spec | CE1: Subterfuge Spec | CF1: City Status | CG1: Clan Status | CH1: Covenant Status | CI1: Covenant 1 | CJ1: Covenant Status 1 | CK1: Covenant 2 | CL1: Covenant Status 2 | CM1: Covenant 3 | CN1: Covenant Status 3 | CO1: Covenant 4 | CP1: Covenant Status 4 | CQ1: Safe Place | CR1: Haven | CS1: Feeding Grounds | CT1: Herd | CU1: Mystery Cult Initiation | CV1: Mystery Cult Name | CW1: Professional Training | CX1: Prof Training Role | CY1: Hum | CZ1: Hum Icon | DA1: Humanity 10 | DB1: Humanity 9 | DC1: Humanity 8 | DD1: Humanity 7 | DE1: Humanity 6 | DF1: Humanity 5 | DG1: Humanity 4 | DH1: Humanity 3 | DI1: Humanity 2 | DJ1: Humanity 1 | DK1: Merit 1 | DL1: Merit 2 | DM1: Merit 3 | DN1: Merit 4 | DO1: Merit 5 | DP1: Merit 6 | DQ1: Merit 7 | DR1: Merit 8 | DS1: Merit 9 | DT1: Merit 10 | DU1: Merit 11 | DV1: Merit 12 | DW1: Merit 13 | DX1: Merit 14 | DY1: Merit 15 | DZ1: Merit 16 | EA1: Merit 17 | EB1: Merit 18 | EC1: Merit 19 | ED1: Merit 20 | EE1: Merit 21 | EF1: Merit 22 | EG1: Merit 23 | EH1: Merit 24 | EI1: Merit 25 | EJ1: Merit 26 | EK1: Merit 27 | EL1: Merit 28 | EM1: Merit 29 | EN1: Merit 30 | EO1: Merit Effect 1 | EP1: Merit Effect 2 | EQ1: Merit Effect 3 | ER1: Merit Effect 4 | ES1: Merit Effect 5 | ET1: Merit Effect 6 | EU1: Merit Effect 7 | EV1: Merit Effect 8 | EW1: Merit Effect 9 | EX1: Merit Effect 10 | EY1: Merit Effect 11 | EZ1: Merit Effect 12 | FA1: Merit Effect 13 | FB1: Merit Effect 14 | FC1: Merit Effect 15 | FD1: Merit Effect 16 | FE1: Merit Effect 17 | FF1: Merit Effect 18 | FG1: Merit Effect 19 | FH1: Merit Effect 20 | FI1: Merit Effect 21 | FJ1: Merit Effect 22 | FK1: Merit Effect 23 | FL1: Merit Effect 24 | FM1: Merit Effect 25 | FN1: Merit Effect 26 | FO1: Merit Effect 27 | FP1: Merit Effect 28 | FQ1: Merit Effect 29 | FR1: Merit Effect 30 | FS1: Influence | FT1: Influence Squares | FU1: Influence 1 | FV1: Influence 2 | FW1: Influence 3 | FX1: Influence 4 | FY1: Influence 5 | FZ1: Influence 6 | GA1: Influence 7 | GB1: Influence 8 | GC1: Influence 9 | GD1: Influence 10 | GE1: Influence 11 | GF1: Influence 12 | GG1: Influence 13 | GH1: Influence 14 | GI1: Influence 15 | GJ1: Influence 16 | GK1: Influence 17 | GL1: Influence 18 | GM1: Influence 19 | GN1: Influence 20 | GO1: Area 1 | GP1: Area 2 | GQ1: Area 3 | GR1: Area 4 | GS1: Area 5 | GT1: Area 6 | GU1: Area 7 | GV1: Area 8 | GW1: Area 9 | GX1: Area 10 | GY1: Area 11 | GZ1: Area 12 | HA1: Area 13 | HB1: Area 14 | HC1: Area 15 | HD1: Area 16 | HE1: Area 17 | HF1: Area 18 | HG1: Area 19 | HH1: Area 20 | HI1: Influence Dots 1 | HJ1: Influence Dots 2 | HK1: Influence Dots 3 | HL1: Influence Dots 4 | HM1: Influence Dots 5 | HN1: Influence Dots 6 | HO1: Influence Dots 7 | HP1: Influence Dots 8 | HQ1: Influence Dots 9 | HR1: Influence Dots 10 | HS1: Influence Dots 11 | HT1: Influence Dots 12 | HU1: Influence Dots 13 | HV1: Influence Dots 14 | HW1: Influence Dots 15 | HX1: Influence Dots 16 | HY1: Influence Dots 17 | HZ1: Influence Dots 18 | IA1: Influence Dots 19 | IB1: Influence Dots 20 | IC1: Animalism | ID1: Auspex | IE1: Celerity | IF1: Dominate | IG1: Majesty | IH1: Nightmare | II1: Obfuscate | IJ1: Protean | IK1: Resilience | IL1: Vigour | IM1: Cruac | IN1: Theban | IO1: Creation | IP1: Destruction | IQ1: Divination | IR1: Protection | IS1: Transmutation | IT1: Blood 1 | IU1: Blood 2 | IV1: Blood 3 | IW1: Blood 4 | IX1: Blood 5 | IY1: Blood 6 | IZ1: Blood 7 | JA1: Blood 8 | JB1: Blood 9 | JC1: Blood 10 | JD1: Blood 11 | JE1: Blood 12 | JF1: Blood 13 | JG1: Blood 14 | JH1: Blood 15 | JI1: Blood 16 | JJ1: Blood 17 | JK1: Blood 18 | JL1: Blood 19 | JM1: Blood 20 | JN1: Blood 21 | JO1: Blood 22 | JP1: Blood 23 | JQ1: Blood 24 | JR1: Blood 25 | JS1: Blood 26 | JT1: Blood 27 | JU1: Blood 28 | JV1: Blood 29 | JW1: Blood 30 | JX1: Blood Stats 1 | JY1: Blood Stats 2 | JZ1: Blood Stats 3 | KA1: Blood Stats 4 | KB1: Blood Stats 5 | KC1: Blood Stats 6 | KD1: Blood Stats 7 | KE1: Blood Stats 8 | KF1: Blood Stats 9 | KG1: Blood Stats 10 | KH1: Blood Stats 11 | KI1: Blood Stats 12 | KJ1: Blood Stats 13 | KK1: Blood Stats 14 | KL1: Blood Stats 15 | KM1: Blood Stats 16 | KN1: Blood Stats 17 | KO1: Blood Stats 18 | KP1: Blood Stats 19 | KQ1: Blood Stats 20 | KR1: Blood Stats 21 | KS1: Blood Stats 22 | KT1: Blood Stats 23 | KU1: Blood Stats 24 | KV1: Blood Stats 25 | KW1: Blood Stats 26 | KX1: Blood Stats 27 | KY1: Blood Stats 28 | KZ1: Blood Stats 29 | LA1: Blood Stats 30 | LB1: Blood Effect 1 | LC1: Blood Effect 2 | LD1: Blood Effect 3 | LE1: Blood Effect 4 | LF1: Blood Effect 5 | LG1: Blood Effect 6 | LH1: Blood Effect 7 | LI1: Blood Effect 8 | LJ1: Blood Effect 9 | LK1: Blood Effect 10 | LL1: Blood Effect 11 | LM1: Blood Effect 12 | LN1: Blood Effect 13 | LO1: Blood Effect 14 | LP1: Blood Effect 15 | LQ1: Blood Effect 16 | LR1: Blood Effect 17 | LS1: Blood Effect 18 | LT1: Blood Effect 19 | LU1: Blood Effect 20 | LV1: Blood Effect 21 | LW1: Blood Effect 22 | LX1: Blood Effect 23 | LY1: Blood Effect 24 | LZ1: Blood Effect 25 | MA1: Blood Effect 26 | MB1: Blood Effect 27 | MC1: Blood Effect 28 | MD1: Blood Effect 29 | ME1: Blood Effect 30 | MF1: Clan Bane | MG1: Bloodline Bane | MH1: Other Bane 1 | MI1: Other Bane 2 | MJ1: Other Bane 3 | MK1: Clan Bane Effect | ML1: Bloodline Bane Effect | MM1: Other Bane Effect 1 | MN1: Other Bane Effect 2 | MO1: Other Bane Effect 3 | MP1: Size | MQ1: Speed | MR1: Defence | MS1: Mask 1WP | MT1: Mask AllWP | MU1: Dirge 1WP | MV1: Dirge AllWP | MW1: Aspiration 1 | MX1: Aspiration 2 | MY1: Aspiration 3 | MZ1: Apparent Age | NA1: Features
A2: tblCharDataAlice | B2: 46104 | C2: 9 | D2: 32 | E2: Katherine H | F2: Alice Vunder | G2: Curious archivist | H2: she/her | I2: Mekhet | J2: D:\Terra Mortis\Character Sheets\Sheet Elements\Mekhet icon.svg | K2: ¬ | L2: Circle of the Crone | M2: D:\Terra Mortis\Character Sheets\Sheet Elements\Crone icon.svg | N2: Follower | O2: Scholar | P2: Regent | Q2: ●●●● | R2: ●●● | S2: ●● | T2: ● | U2: ●●● | V2: ●● | W2: ●●● | X2: ●● | Y2: ●● | Z2: ●● | AA2: ●●● | AC2: ●●● | AE2: ●●● | AL2: ●● | AM2: ●● | AQ2: ●● | AR2: ●●● | AU2: ●● | AX2: ●○○○○○○○○○ | AY2: 1 | BA2: □□□□□□□■■■■■■■■ | BB2: 4 / 4 | BC2: □□□□■■■■■■ | BD2: 10 / 10 | BE2: □□□□□□□□□□■■■■■■■■■■ | BF2: 1 | BG2: Animals | BH2: Research | BI2: Hacking | BY2: Motives | CF2: 2 | CG2: 1 | CH2: 1 | CI2: Crone | CJ2: ● | CK2: Carthian | CL2: - | CM2: Invictus | CN2: - | CO2: Lance | CP2: - | CQ2: ● | CR2: ● | CS2: - | CT2: - | CU2: ●●●●● | CV2: The Archive | CW2: - | CY2: 6 | CZ2: ~ | DA2: ○ | DB2: ○ | DC2: ○ | DD2: ○ | DE2: ● (Sister (unnamed)) | DF2: ● (One parent (unnamed)) | DG2: ● | DH2: ● | DI2: ● | DJ2: ● | DK2: Hobbyist Clique ● | DL2: Library (Occult) ●● | DM2: Viral Mythology ●●● | DN2: ¬ | DO2: ¬ | DP2: ¬ | DQ2: ¬ | DR2: ¬ | DS2: ¬ | DT2: ¬ | DU2: ¬ | DV2: ¬ | DW2: ¬ | DX2: ¬ | DY2: ¬ | DZ2: ¬ | EA2: ¬ | EB2: ¬ | EC2: ¬ | ED2: ¬ | EE2: ¬ | EF2: ¬ | EG2: ¬ | EH2: ¬ | EI2: ¬ | EJ2: ¬ | EK2: ¬ | EL2: ¬ | EM2: ¬ | EN2: ¬ | EO2: 9-Again on hobby Skill; +2 to extended actions with that Skill. | EP2: Add dots to extended rolls for a chosen Skill's subject matter. | EQ2: Presence + Expression vs Wits + Composure to inflict contagious awe. Allies and Herd double their yield. | ER2: ¬ | ES2: ¬ | ET2: ¬ | EU2: ¬ | EV2: ¬ | EW2: ¬ | EX2: ¬ | EY2: ¬ | EZ2: ¬ | FA2: ¬ | FB2: ¬ | FC2: ¬ | FD2: ¬ | FE2: ¬ | FF2: ¬ | FG2: ¬ | FH2: ¬ | FI2: ¬ | FJ2: ¬ | FK2: ¬ | FL2: ¬ | FM2: ¬ | FN2: ¬ | FO2: ¬ | FP2: ¬ | FQ2: ¬ | FR2: ¬ | FS2: 8 / 8 | FT2: □□□□□□□□ | FU2: Allies | FV2: Allies | FW2: Allies | FX2: Allies | FY2: Contacts | FZ2: ¬ | GA2: ¬ | GB2: ¬ | GC2: ¬ | GD2: ¬ | GE2: ¬ | GF2: ¬ | GG2: ¬ | GH2: ¬ | GI2: ¬ | GJ2: ¬ | GK2: ¬ | GL2: ¬ | GM2: ¬ | GN2: ¬ | GO2: Health | GP2: Politics | GQ2: Transportation | GR2: Underworld | GS2: Street, Occult, Industry | GT2: ¬ | GU2: ¬ | GV2: ¬ | GW2: ¬ | GX2: ¬ | GY2: ¬ | GZ2: ¬ | HA2: ¬ | HB2: ¬ | HC2: ¬ | HD2: ¬ | HE2: ¬ | HF2: ¬ | HG2: ¬ | HH2: ¬ | HI2: ●●● | HJ2: ●●● | HK2: ●●● | HL2: ●●● | HM2: ●●● | IC2: - | ID2: ● | IE2: ● | IF2: - | IG2: - | IH2: - | II2: ●●● | IJ2: - | IK2: - | IL2: - | IM2: ● | IN2: - | IO2: ● | IP2: - | IQ2: ● | IR2: ● | IS2: - | IT2: Auspex ● | Beast's Hackles | IU2: Celerity ● | IV2: Obfuscate ● | Face in the Crowd | IW2: Obfuscate ●● | Touch of Shadow | IX2: Obfuscate ●●● | Cloak of Night | IY2: Blood Sorcery | Creation ● | IZ2: Blood Sorcery | Divination ● | JA2: Blood Sorcery | Protection ● | JB2: ¬ | JC2: ¬ | JD2: ¬ | JE2: ¬ | JF2: ¬ | JG2: ¬ | JH2: ¬ | JI2: ¬ | JJ2: ¬ | JK2: ¬ | JL2: ¬ | JM2: ¬ | JN2: ¬ | JO2: ¬ | JP2: ¬ | JQ2: ¬ | JR2: ¬ | JS2: ¬ | JT2: ¬ | JU2: ¬ | JV2: ¬ | JW2: ¬ | JX2: Cost: Free (1 V for Insight) • Pool: - - Composure & Closed Book • Instant • Scene | JY2: Cost: 1 V per effect • Pool: - • Reflexive • 1 turn | JZ2: Cost: - • Pool: - • Instant • Scene | KA2: Cost: 1 V • Pool: 8 • Instant • Scene | KB2: Cost: 1 V • Pool: - • None | KC2: ¬ | KD2: ¬ | KE2: ¬ | KF2: ¬ | KG2: ¬ | KH2: ¬ | KI2: ¬ | KJ2: ¬ | KK2: ¬ | KL2: ¬ | KM2: ¬ | KN2: ¬ | KO2: ¬ | KP2: ¬ | KQ2: ¬ | KR2: ¬ | KS2: ¬ | KT2: ¬ | KU2: ¬ | KV2: ¬ | KW2: ¬ | KX2: ¬ | KY2: ¬ | KZ2: ¬ | LA2: ¬ | LB2: Add Auspex dots to any rolls to resist surprise. Access to Tier 1 Auspex Insight questions. | LC2: Persistent improved Defence or Dodge. Activate for supernatural speed benefits. Unnatural Grace: add Celerity dots as bonus dice to non-combat speed-based pools. | LD2: Blend into surroundings, visible but unnoticeable. Predatory aura fully on or off. Leaving combat: Wits + Composure - Obfuscate to notice; auto Clash of Wills vs Auspex. | LE2: Cast Face in the Crowd on object or person. Free and unlimited duration on carried/worn objects if not drawing attention. | LF2: Become invisible. Leaving combat: auto Clash of Wills vs Auspex 2. | LG2: Summon liquids, dead organic matter, sensory phenomena. Bonus/penalty = Potency. | LH2: Glimpse fragmented details about intended actions. Learn basic info about a target. | LI2: Subtract Potency from ritual rolls targeting subject. Heal bashing in vampires. Protect from the Kiss (add Potency to resistance). | LJ2: ¬ | LK2: ¬ | LL2: ¬ | LM2: ¬ | LN2: ¬ | LO2: ¬ | LP2: ¬ | LQ2: ¬ | LR2: ¬ | LS2: ¬ | LT2: ¬ | LU2: ¬ | LV2: ¬ | LW2: ¬ | LX2: ¬ | LY2: ¬ | LZ2: ¬ | MA2: ¬ | MB2: ¬ | MC2: ¬ | MD2: ¬ | ME2: ¬ | MF2: Tenebrous Curse | MG2: ¬ | MH2: Rat King/Queen | MI2: ¬ | MJ2: ¬ | MK2: Gain an extra bane at Humanity 6 (doesn't count towards cap); Humanity counts –1 for all Humanity-based banes. | ML2: ¬ | MM2: Surrounded by vermin; all Social rolls fail except Intimidation; WP can dismiss. | MN2: ¬ | MO2: ¬ | MP2: 5 | MQ2: 9 | MR2: 3 | MS2: Follow a directive blindly, for the sake of following. | MT2: Follow a dangerous directive without hesitation. | MU2: Uncover a lost piece of information. | MV2: Uncover forbidden knowledge. | MW2: ¬ | MX2: ¬ | MY2: ¬
A3: tblCharDataAnichka | B3: 46104 | C3: 2 | D3: 28 | E3: Katie H | F3: Anichka | G3: Feral Oracular Darling | H3: she/her | I3: Mekhet | J3: D:\Terra Mortis\Character Sheets\Sheet Elements\Mekhet icon.svg | K3: ¬ | L3: Circle of the Crone | M3: D:\Terra Mortis\Character Sheets\Sheet Elements\Crone icon.svg | N3: Questioner | O3: Scholar | P3: ¬ | Q3: ●● | R3: ●●● | S3: ●●● | T3: ●● | U3: ●● | V3: ●● | W3: ●● | X3: ●●● | Y3: ●●● | AE3: ●●●● | AH3: ●● | AM3: ●● | AN3: ●●● | AP3: ●● | AQ3: ●●● | AR3: ●● | AT3: ●● | AU3: ● | AV3: ● | AX3: ●○○○○○○○○○ | AY3: 1 | BA3: □□□□□□□■■■■■■■■ | BB3: 6 / 6 | BC3: □□□□□□■■■■ | BD3: 9 / 10 | BE3: □□□□□□□□□■■■■■■■■■■■ | BF3: 1 | BG3: Animals | BM3: prophecy & omens, dreams | BV3: Living off the land | CF3: 2 | CG3: 2 | CH3: 4 | CI3: Crone | CJ3: ●●●● | CK3: Carthian | CL3: - | CM3: Invictus | CN3: - | CO3: Lance | CP3: - | CQ3: ● | CR3: ● | CS3: - | CT3: ●● | CU3: - | CW3: - | CY3: 6 | CZ3: ~ | DA3: ○ | DB3: ○ | DC3: ○ | DD3: ○ | DE3: ● (Kateryna (grand-niece)) | DF3: ● | DG3: ● | DH3: ● | DI3: ● | DJ3: ● | DK3: Dream Visions ● | DL3: Language ● | DM3: Language ● | DN3: Tolerance for Biology ● | DO3: What You've Done For Her Lately ● | DP3: ¬ | DQ3: ¬ | DR3: ¬ | DS3: ¬ | DT3: ¬ | DU3: ¬ | DV3: ¬ | DW3: ¬ | DX3: ¬ | DY3: ¬ | DZ3: ¬ | EA3: ¬ | EB3: ¬ | EC3: ¬ | ED3: ¬ | EE3: ¬ | EF3: ¬ | EG3: ¬ | EH3: ¬ | EI3: ¬ | EJ3: ¬ | EK3: ¬ | EL3: ¬ | EM3: ¬ | EN3: ¬ | EO3: Once per night, roll Blood Potency for prophetic dreams about a new person or place. | EP3: Speak, read and write a chosen language. | EQ3: Speak, read and write a chosen language. | ER3: Ignore Resistance rolls from witnessing biological grotesquerie. | ES3: Once per story, after a Crúac ritual, add ritual level to effective Crone Status for the chapter (Social rolls, favours, Social Merits until sunrise). | ET3: ¬ | EU3: ¬ | EV3: ¬ | EW3: ¬ | EX3: ¬ | EY3: ¬ | EZ3: ¬ | FA3: ¬ | FB3: ¬ | FC3: ¬ | FD3: ¬ | FE3: ¬ | FF3: ¬ | FG3: ¬ | FH3: ¬ | FI3: ¬ | FJ3: ¬ | FK3: ¬ | FL3: ¬ | FM3: ¬ | FN3: ¬ | FO3: ¬ | FP3: ¬ | FQ3: ¬ | FR3: ¬ | FS3: 7 / 7 | FT3: □□□□□□□ | FU3: Retainer | FV3: ¬ | FW3: ¬ | FX3: ¬ | FY3: ¬ | FZ3: ¬ | GA3: ¬ | GB3: ¬ | GC3: ¬ | GD3: ¬ | GE3: ¬ | GF3: ¬ | GG3: ¬ | GH3: ¬ | GI3: ¬ | GJ3: ¬ | GK3: ¬ | GL3: ¬ | GM3: ¬ | GN3: ¬ | GO3: family | GP3: ¬ | GQ3: ¬ | GR3: ¬ | GS3: ¬ | GT3: ¬ | GU3: ¬ | GV3: ¬ | GW3: ¬ | GX3: ¬ | GY3: ¬ | GZ3: ¬ | HA3: ¬ | HB3: ¬ | HC3: ¬ | HD3: ¬ | HE3: ¬ | HF3: ¬ | HG3: ¬ | HH3: ¬ | HI3: ●●● | IC3: - | ID3: ●● | IE3: - | IF3: - | IG3: - | IH3: - | II3: ● | IJ3: ● | IK3: - | IL3: - | IM3: ●●● | IN3: - | IO3: ● | IP3: - | IQ3: ●●● | IR3: ● | IS3: - | IT3: Auspex ● | Beast's Hackles | IU3: Auspex ●● | Uncanny Perception | IV3: Obfuscate ● | Face in the Crowd | IW3: Protean ● | Unmarked Grave | IX3: Blood Sorcery | Creation ● | IY3: Blood Sorcery | Divination ● | IZ3: Blood Sorcery | Divination ●● | JA3: Blood Sorcery | Divination ●●● | JB3: Blood Sorcery | Protection ● | JC3: Cruac ● | The Pool of Forbidden Truths | JD3: ¬ | JE3: ¬ | JF3: ¬ | JG3: ¬ | JH3: ¬ | JI3: ¬ | JJ3: ¬ | JK3: ¬ | JL3: ¬ | JM3: ¬ | JN3: ¬ | JO3: ¬ | JP3: ¬ | JQ3: ¬ | JR3: ¬ | JS3: ¬ | JT3: ¬ | JU3: ¬ | JV3: ¬ | JW3: ¬ | JX3: Cost: Free (1 V for Insight) • Pool: - - Composure & Closed Book • Instant • Scene | JY3: Cost: Free (1 V for Insight) Must perceive target • Pool: - • Instant • Scene | JZ3: Cost: - • Pool: - • Instant • Scene | KA3: Cost: Varies • Pool: - • Instant • Indefinite | KB3: ¬ | KC3: ¬ | KD3: ¬ | KE3: ¬ | KF3: ¬ | KG3: Cost: 1 V 1 Successes • Pool: 10 • Ritual • Instant | KH3: ¬ | KI3: ¬ | KJ3: ¬ | KK3: ¬ | KL3: ¬ | KM3: ¬ | KN3: ¬ | KO3: ¬ | KP3: ¬ | KQ3: ¬ | KR3: ¬ | KS3: ¬ | KT3: ¬ | KU3: ¬ | KV3: ¬ | KW3: ¬ | KX3: ¬ | KY3: ¬ | KZ3: ¬ | LA3: ¬ | LB3: Add Auspex dots to any rolls to resist surprise. Access to Tier 1 Auspex Insight questions. | LC3: Persistent Acute Senses Merit, doubles actual merit. Access to Tier 2 Auspex Insight questions. | LD3: Blend into surroundings, visible but unnoticeable. Predatory aura fully on or off. Leaving combat: Wits + Composure - Obfuscate to notice; auto Clash of Wills vs Auspex. | LE3: Merge with soil. | LF3: Summon liquids, dead organic matter, sensory phenomena. Bonus/penalty = Potency. | LG3: Glimpse fragmented details about intended actions. Learn basic info about a target. | LH3: Ask specific questions about a target. Sense supernatural concealment on objects. Detect lies. | LI3: View past events (limited by Fog of Eternity). Locate hidden targets. Prophetic omens about near future. | LJ3: Subtract Potency from ritual rolls targeting subject. Heal bashing in vampires. Protect from the Kiss (add Potency to resistance). | LK3: Blood pool reveals subject's greatest fear or deepest desire | LL3: ¬ | LM3: ¬ | LN3: ¬ | LO3: ¬ | LP3: ¬ | LQ3: ¬ | LR3: ¬ | LS3: ¬ | LT3: ¬ | LU3: ¬ | LV3: ¬ | LW3: ¬ | LX3: ¬ | LY3: ¬ | LZ3: ¬ | MA3: ¬ | MB3: ¬ | MC3: ¬ | MD3: ¬ | ME3: ¬ | MF3: Tenebrous Curse | MG3: ¬ | MH3: ¬ | MI3: ¬ | MJ3: ¬ | MK3: Gain an extra bane at Humanity 6 (doesn't count towards cap); Humanity counts –1 for all Humanity-based banes. | ML3: ¬ | MN3: ¬ | MO3: ¬ | MP3: 5 | MQ3: 9 | MR3: 4 | MS3: Challenge an accepted truth. | MT3: Put a long-believed truth to the test, at your own peril. | MU3: Uncover a lost piece of information. | MV3: Uncover forbidden knowledge. | MW3: ¬ | MX3: ¬ | MY3: ¬ | MZ3: early 20s | NA3: smells like animals
A4: tblCharDataBrandy | B4: 46104 | C4: 1 | D4: 46 | E4: Ashley K | F4: Brandy LaRoux | G4: Trailer Royalty | H4: she/her | I4: Gangrel | J4: D:\Terra Mortis\Character Sheets\Sheet Elements\Gangrel icon.svg | K4: ¬ | L4: Circle of the Crone | M4: D:\Terra Mortis\Character Sheets\Sheet Elements\Crone icon.svg | N4: Perfectionist | O4: Monster | P4: Harpy | Q4: ●● | R4: ●● | S4: ●●● | T4: ●●● | U4: ●● | V4: ●●● | W4: ●●● | X4: ●● | Y4: ●●● | AB4: ● | AE4: ●●● | AI4: ●●●●● | AM4: ● | AN4: ● | AQ4: ●●● | AR4: ●● | AS4: ●●● | AT4: ● | AU4: ● | AW4: ● | AX4: ●○○○○○○○○○ | AY4: 1 | BA4: □□□□□□□□■■■■■■■ | BB4: 6 / 6 | BC4: □□□□□□■■■■ | BD4: 10 / 10 | BE4: □□□□□□□□□□■■■■■■■■■■ | BF4: 1 | BG4: Animals | BM4: Vodun | BQ4: Tooth & Claw | CE4: Put on airs | CF4: 4 | CG4: 2 | CH4: 2 | CI4: Crone | CJ4: ●● | CK4: Carthian | CL4: - | CM4: Invictus | CN4: - | CO4: Lance | CP4: - | CQ4: - | CR4: - | CS4: - | CT4: - | CU4: ●●●●● | CV4: Ducen Ducibus | CW4: - | CY4: 5 | CZ4: ~ | DA4: ○ | DB4: ○ | DC4: ○ | DD4: ○ | DE4: ○ (Tod Graves (husband)) | DF4: ● (Good Luck Molly (alligator)) | DG4: ● | DH4: ● | DI4: ● | DJ4: ● | DK4: Defensive Combat (Brawl) ● | DL4: Indomitable ●● | DM4: Inspiring ●●● | DN4: Meditative Mind ●● | DO4: Secret Society Junkie ● | DP4: Table Turner ● | DQ4: Viral Mythology ●●● | DR4: Riding the Wave ● | Ravage | DS4: Riding the Wave ●● | Primal Strength | DT4: Riding the Wave ●●● | In the Zone | DU4: Riding the Wave ●●●● | Unyielding | DV4: ¬ | DW4: ¬ | DX4: ¬ | DY4: ¬ | DZ4: ¬ | EA4: ¬ | EB4: ¬ | EC4: ¬ | ED4: ¬ | EE4: ¬ | EF4: ¬ | EG4: ¬ | EH4: ¬ | EI4: ¬ | EJ4: ¬ | EK4: ¬ | EL4: ¬ | EM4: ¬ | EN4: ¬ | EO4: Substitute chosen Skill for Athletics in Defence, if equipped for that Skill. | EP4: +2 to contest or resist supernatural mental influence. | EQ4: Roll Presence + Expression to confer the Inspired Condition. | ER4: Ignore penalties on meditation. (••) meditation grants +3 Resolve + Composure for the day. (••••) meditation needs only one success. | ES4: Dots in Status or Mystery Cult Initiation representing human secret societies also count as dots of Herd. | ET4: Spend Willpower to preempt Social Manoeuvring with your own Social action. | EU4: Presence + Expression vs Wits + Composure to inflict contagious awe. Allies and Herd double their yield. | EV4: Bite attacks take a 1L weapon rating. | EW4: Double your Strength bonus from frenzy when lifting, jumping, or destroying objects. | EX4: When you spend Willpower to ride the wave, you also apply the normal +3 action bonus. | EY4: After a scene where you rode the wave, recover any Willpower spent to do so. | EZ4: ¬ | FA4: ¬ | FB4: ¬ | FC4: ¬ | FD4: ¬ | FE4: ¬ | FF4: ¬ | FG4: ¬ | FH4: ¬ | FI4: ¬ | FJ4: ¬ | FK4: ¬ | FL4: ¬ | FM4: ¬ | FN4: ¬ | FO4: ¬ | FP4: ¬ | FQ4: ¬ | FR4: ¬ | FS4: 11 / 11 | FT4: □□□□□□□□□□□ | FU4: Allies | FV4: Allies | FW4: Allies | FX4: Allies | FY4: Resources | FZ4: ¬ | GA4: ¬ | GB4: ¬ | GC4: ¬ | GD4: ¬ | GE4: ¬ | GF4: ¬ | GG4: ¬ | GH4: ¬ | GI4: ¬ | GJ4: ¬ | GK4: ¬ | GL4: ¬ | GM4: ¬ | GN4: ¬ | GO4: High Society | GP4: Media | GQ4: Police | GR4: Underworld | GS4: ¬ | GT4: ¬ | GU4: ¬ | GV4: ¬ | GW4: ¬ | GX4: ¬ | GY4: ¬ | GZ4: ¬ | HA4: ¬ | HB4: ¬ | HC4: ¬ | HD4: ¬ | HE4: ¬ | HF4: ¬ | HG4: ¬ | HH4: ¬ | HI4: ●●● | HJ4: ●●● | HK4: ●●● | HL4: ●●● | HM4: ●●●●● | IC4: - | ID4: - | IE4: - | IF4: - | IG4: ● | IH4: - | II4: - | IJ4: ●●● | IK4: - | IL4: - | IM4: ● | IN4: - | IO4: ● | IP4: ● | IQ4: - | IR4: ● | IS4: - | IT4: Majesty ● | Awe | IU4: Protean ● | Unmarked Grave | IV4: Protean ●● | Predatory Aspect | IW4: Protean ●●● | Beast's Skin | IX4: Blood Sorcery | Creation ● | IY4: Blood Sorcery | Destruction ● | IZ4: Blood Sorcery | Protection ● | JA4: Cruac ● | Mantle of Amorous Fire | JB4: ¬ | JC4: ¬ | JD4: ¬ | JE4: ¬ | JF4: ¬ | JG4: ¬ | JH4: ¬ | JI4: ¬ | JJ4: ¬ | JK4: ¬ | JL4: ¬ | JM4: ¬ | JN4: ¬ | JO4: ¬ | JP4: ¬ | JQ4: ¬ | JR4: ¬ | JS4: ¬ | JT4: ¬ | JU4: ¬ | JV4: ¬ | JW4: ¬ | JX4: Cost: - • Pool: - • Instant • Scene | JY4: Cost: Varies • Pool: - • Instant • Indefinite | JZ4: Cost: 1 V • Pool: - • Instant • Scene | KA4: Cost: 2 V • Pool: - • Instant • Indefinite | KB4: ¬ | KC4: ¬ | KD4: ¬ | KE4: Cost: 1 V 1 Successes • Pool: 6 • Ritual • Scene | KF4: ¬ | KG4: ¬ | KH4: ¬ | KI4: ¬ | KJ4: ¬ | KK4: ¬ | KL4: ¬ | KM4: ¬ | KN4: ¬ | KO4: ¬ | KP4: ¬ | KQ4: ¬ | KR4: ¬ | KS4: ¬ | KT4: ¬ | KU4: ¬ | KV4: ¬ | KW4: ¬ | KX4: ¬ | KY4: ¬ | KZ4: ¬ | LA4: ¬ | LB4: Become centre of attention. Subjects become Awed. | LC4: Merge with soil. | LD4: Take on animal traits. | LE4: Transform into predatory animal. | LF4: Summon liquids, dead organic matter, sensory phenomena. Bonus/penalty = Potency. | LG4: Upgrade bashing to lethal. Produce poisons (Toxicity = Potency). | LH4: Subtract Potency from ritual rolls targeting subject. Heal bashing in vampires. Protect from the Kiss (add Potency to resistance). | LI4: Dance to exhaustion. Add Cruac as a Presence bonus for the night. | LJ4: ¬ | LK4: ¬ | LL4: ¬ | LM4: ¬ | LN4: ¬ | LO4: ¬ | LP4: ¬ | LQ4: ¬ | LR4: ¬ | LS4: ¬ | LT4: ¬ | LU4: ¬ | LV4: ¬ | LW4: ¬ | LX4: ¬ | LY4: ¬ | LZ4: ¬ | MA4: ¬ | MB4: ¬ | MC4: ¬ | MD4: ¬ | ME4: ¬ | MF4: Feral Curse | MG4: ¬ | MH4: ¬ | MI4: ¬ | MJ4: ¬ | MK4: Frenzy resistance dice pools capped by Humanity (doesn't affect Riding the Wave). | ML4: ¬ | MN4: ¬ | MO4: ¬ | MP4: 5 | MQ4: 10 | MR4: 2 | MS4: Revisit an already successful action to hammer out a flaw. | MT4: Stick with a failed and dangerous plan in order to fix what went wrong. | MU4: Cause pain for the sole intention of causing pain. | MV4: Commit a capital crime without additional motive. | MW4: ¬ | MX4: ¬ | MY4: ¬
A5: tblCharDataCarver | B5: 46104 | C5: 2 | D5: 50 | E5: Archer | F5: Carver | G5: Lance Lore Nerd | H5: he/him | I5: Ventrue | J5: D:\Terra Mortis\Character Sheets\Sheet Elements\Ventrue icon.svg | K5: Lasombra | L5: Lancea et Sanctum | M5: D:\Terra Mortis\Character Sheets\Sheet Elements\Lance icon.svg | N5: Scholar | O5: Authoritarian | P5: ¬ | Q5: ●●● | R5: ●● | S5: ●●● | T5: ●● | U5: ●● | V5: ●●○○ | W5: ●●● | X5: ●● | Y5: ●●● | Z5: ●●●● | AC5: ●● | AE5: ●●●● | AF5: ● | AL5: ●● | AM5: ●● | AQ5: ●●● | AS5: ●● | AT5: ●● | AX5: ●●○○○○○○○○ | AY5: 2 | AZ5: † | BA5: □□□□□□□□□■■■■■■ | BB5: 6 / 6 | BC5: □□□□□□■■■■ | BD5: 11 / 11 | BE5: □□□□□□□□□□□■■■■■■■■■ | BF5: 2 | BG5: Animals | BH5: law | BM5: artefacts | BY5: motives | CF5: 1 | CG5: 2 | CH5: 3 | CI5: Lance | CJ5: ●●● | CK5: Carthian | CL5: - | CM5: Crone | CN5: - | CO5: Invictus | CP5: - | CQ5: ●●●●● | CR5: ●●● | CS5: - | CT5: ●●● | CU5: - | CW5: - | CY5: 6 | CZ5: ~ | DA5: ○ | DB5: ○ | DC5: ○ | DD5: ○ (James (Crowley descendant)) | DE5: ● | DF5: ● | DG5: ● | DH5: ● | DI5: ● | DJ5: ● | DK5: Acute Senses ● | DL5: Eidetic Memory ● | DM5: Esoteric Armoury ● | DN5: Library (Academic) ●●● | DO5: Library (Occult) ●●● | DP5: Lorekeeper ● | DQ5: ¬ | DR5: ¬ | DS5: ¬ | DT5: ¬ | DU5: ¬ | DV5: ¬ | DW5: ¬ | DX5: ¬ | DY5: ¬ | DZ5: ¬ | EA5: ¬ | EB5: ¬ | EC5: ¬ | ED5: ¬ | EE5: ¬ | EF5: ¬ | EG5: ¬ | EH5: ¬ | EI5: ¬ | EJ5: ¬ | EK5: ¬ | EL5: ¬ | EM5: ¬ | EN5: ¬ | EO5: Add Blood Potency to sensory rolls. Exceptional success can inflict Obsession. | EP5: No rolls for recall. +2 to recall minute facts. | EQ5: Enough esoterica to supply the banes of ephemeral entities with a Rank up to your rating in this Merit. | ER5: Add dots to extended rolls for a chosen Skill's subject matter. | ES5: Add dots to extended rolls for a chosen Skill's subject matter. | ET5: Distribute Library dots among bonus Retainer and Herd. | EU5: ¬ | EV5: ¬ | EW5: ¬ | EX5: ¬ | EY5: ¬ | EZ5: ¬ | FA5: ¬ | FB5: ¬ | FC5: ¬ | FD5: ¬ | FE5: ¬ | FF5: ¬ | FG5: ¬ | FH5: ¬ | FI5: ¬ | FJ5: ¬ | FK5: ¬ | FL5: ¬ | FM5: ¬ | FN5: ¬ | FO5: ¬ | FP5: ¬ | FQ5: ¬ | FR5: ¬ | FS5: 7 / 7 | FT5: □□□□□□□ | FU5: Contacts | FV5: Resources | FW5: Retainer | FX5: ¬ | FY5: ¬ | FZ5: ¬ | GA5: ¬ | GB5: ¬ | GC5: ¬ | GD5: ¬ | GE5: ¬ | GF5: ¬ | GG5: ¬ | GH5: ¬ | GI5: ¬ | GJ5: ¬ | GK5: ¬ | GL5: ¬ | GM5: ¬ | GN5: ¬ | GO5: Occult, University, Beuracracy, Church, Legal | GP5: ¬ | GQ5: Nicole - EA | GR5: ¬ | GS5: ¬ | GT5: ¬ | GU5: ¬ | GV5: ¬ | GW5: ¬ | GX5: ¬ | GY5: ¬ | GZ5: ¬ | HA5: ¬ | HB5: ¬ | HC5: ¬ | HD5: ¬ | HE5: ¬ | HF5: ¬ | HG5: ¬ | HH5: ¬ | HI5: ●●●●● | HJ5: ●●● | HK5: ●●● | IC5: - | ID5: - | IE5: - | IF5: - | IG5: - | IH5: ●●●● | II5: - | IJ5: - | IK5: ●● | IL5: - | IM5: - | IN5: - | IO5: - | IP5: - | IQ5: - | IR5: - | IS5: - | IT5: Nightmare ● | Dread Presence | IU5: Nightmare ●● | Face of the Beast | IV5: Nightmare ●●● | Grand Delusion | IW5: Nightmare ●●●● | Waking Nightmare | IX5: Resilience ●● | IY5: Devotion | Skim the Void | IZ5: ¬ | JA5: ¬ | JB5: ¬ | JC5: ¬ | JD5: ¬ | JE5: ¬ | JF5: ¬ | JG5: ¬ | JH5: ¬ | JI5: ¬ | JJ5: ¬ | JK5: ¬ | JL5: ¬ | JM5: ¬ | JN5: ¬ | JO5: ¬ | JP5: ¬ | JQ5: ¬ | JR5: ¬ | JS5: ¬ | JT5: ¬ | JU5: ¬ | JV5: ¬ | JW5: ¬ | JX5: Cost: - • Pool: - • Instant • Scene | JY5: Cost: 1 V • Pool: 10 v Composure + BP • Contested • Instant | JZ5: Cost: 2 V • Pool: 9 v Composure + BP • Contested • 1 night | KA5: Cost: 1 V • Pool: 10 v highest Composure + BP • Contested • Scene | KB5: Cost: 1 V per effect • Pool: - • Reflexive • 1 turn | KC5: Cost: 1 V (Lasombra Only) • Pool: 6 • Instant • Instant | KD5: ¬ | KE5: ¬ | KF5: ¬ | KG5: ¬ | KH5: ¬ | KI5: ¬ | KJ5: ¬ | KK5: ¬ | KL5: ¬ | KM5: ¬ | KN5: ¬ | KO5: ¬ | KP5: ¬ | KQ5: ¬ | KR5: ¬ | KS5: ¬ | KT5: ¬ | KU5: ¬ | KV5: ¬ | KW5: ¬ | KX5: ¬ | KY5: ¬ | KZ5: ¬ | LA5: ¬ | LB5: Conjure brief illusions. Improve Intimidation. Prevent foes spending Willpower. | LC5: Impose Frightened Condition. Cause fleeing. | LD5: Impose Delusional Condition. | LE5: Create and control hallucinations. | LF5: Downgrade damage and increase Stamina. Improve Armour and Defences. Unnatural Fortitude: add Resilience dots as bonus dice to non-combat Stamina pools. | LG5: Step into any visible shadow and out of another instantly. Can carry objects but not people or animals. Torpid Kindred do not count as objects. | LH5: ¬ | LI5: ¬ | LJ5: ¬ | LK5: ¬ | LL5: ¬ | LM5: ¬ | LN5: ¬ | LO5: ¬ | LP5: ¬ | LQ5: ¬ | LR5: ¬ | LS5: ¬ | LT5: ¬ | LU5: ¬ | LV5: ¬ | LW5: ¬ | LX5: ¬ | LY5: ¬ | LZ5: ¬ | MA5: ¬ | MB5: ¬ | MC5: ¬ | MD5: ¬ | ME5: ¬ | MF5: Aloof Curse | MG5: ¬ | MH5: ¬ | MI5: ¬ | MJ5: ¬ | MK5: First Touchstone attaches to Humanity 7; losing it detaches on first Humanity loss. Breaking points always treated as one step lower. | ML5: ¬ | MN5: ¬ | MO5: ¬ | MP5: 5 | MQ5: 9 | MR5: 2 | MS5: Uncover a lost piece of information. | MT5: Uncover forbidden knowledge. | MU5: Cow someone into submission. | MV5: Commit a widespread hit against a rival's mortal connections. | MW5: ¬ | MX5: ¬ | MY5: ¬ | MZ5: mid 40s
A6: tblCharDataCazz | B6: 46104 | C6: 4 | D6: 34 | E6: Brae C | F6: Casamir 'Cazz' | G6: The Mad Dog | H6: he/they | I6: Ventrue | J6: D:\Terra Mortis\Character Sheets\Sheet Elements\Ventrue icon.svg | K6: Malkovians | L6: Carthian Movement | M6: D:\Terra Mortis\Character Sheets\Sheet Elements\Carthian icon.svg | N6: Scholar | O6: Jester | P6: ¬ | Q6: ●●● | R6: ●●● | S6: ●●● | T6: ●●● | U6: ●●● | V6: ●●●○ | W6: ●● | X6: ●● | Y6: ●● | Z6: ●● | AB6: ● | AC6: ● | AE6: ●● | AG6: ● | AH6: ●●●●● | AK6: ●●● | AL6: ● | AM6: ● | AN6: ● | AQ6: ● | AS6: ● | AW6: ●● | AX6: ●●○○○○○○○○ | AY6: 2 | AZ6: † | BA6: □□□□□□□□□■■■■■■ | BB6: 5 / 5 | BC6: □□□□□■■■■■ | BD6: 11 / 11 | BE6: □□□□□□□□□□□■■■■■■■■■ | BF6: 2 | BG6: Animals | BM6: ley lines | BP6: endurance | BS6: archery | CF6: 1 | CG6: 1 | CH6: 1 | CI6: Carthian | CJ6: ● | CK6: Crone | CL6: - | CM6: Invictus | CN6: - | CO6: Lance | CP6: - | CQ6: ● | CR6: - | CS6: - | CT6: ● | CU6: - | CW6: - | CY6: 6 | CZ6: ~ | DA6: ○ | DB6: ○ | DC6: ○ | DD6: ○ (University testamur (Simulacrum)) | DE6: ● | DF6: ● | DG6: ● | DH6: ● | DI6: ● | DJ6: ● | DK6: Quick Draw (Bow) ● | DL6: Combat Archery ● | Rapid Nock | DM6: Combat Archery ●● | Reflex Aiming | DN6: Combat Archery ●●● | Parthian Shot | DO6: Combat Archery ●●●● | Rain of Arrows | DP6: Combat Archery ●●●●● | Trick Shot | DQ6: ¬ | DR6: ¬ | DS6: ¬ | DT6: ¬ | DU6: ¬ | DV6: ¬ | DW6: ¬ | DX6: ¬ | DY6: ¬ | DZ6: ¬ | EA6: ¬ | EB6: ¬ | EC6: ¬ | ED6: ¬ | EE6: ¬ | EF6: ¬ | EG6: ¬ | EH6: ¬ | EI6: ¬ | EJ6: ¬ | EK6: ¬ | EL6: ¬ | EM6: ¬ | EN6: ¬ | EO6: Draw a weapon from a chosen Specialty reflexively while Defence is available. Initiative bonuses only apply if using the weapon. | EP6: Ignore bow Initiative penalties. String arrows reflexively. | EQ6: Ignore penalties for firing into close combat. | ER6: When you Dodge, inflict threshold successes as attack damage against the first close attack you beat each turn. | ES6: Make medium autofire attacks at triple range penalties. | ET6: Simultaneously perform a Combat Archery attack and an Athletics action, both at -2. | EU6: ¬ | EV6: ¬ | EW6: ¬ | EX6: ¬ | EY6: ¬ | EZ6: ¬ | FA6: ¬ | FB6: ¬ | FC6: ¬ | FD6: ¬ | FE6: ¬ | FF6: ¬ | FG6: ¬ | FH6: ¬ | FI6: ¬ | FJ6: ¬ | FK6: ¬ | FL6: ¬ | FM6: ¬ | FN6: ¬ | FO6: ¬ | FP6: ¬ | FQ6: ¬ | FR6: ¬ | FS6: 0 / 2 | FT6: ■■ | FU6: ¬ | FV6: ¬ | FW6: ¬ | FX6: ¬ | FY6: ¬ | FZ6: ¬ | GA6: ¬ | GB6: ¬ | GC6: ¬ | GD6: ¬ | GE6: ¬ | GF6: ¬ | GG6: ¬ | GH6: ¬ | GI6: ¬ | GJ6: ¬ | GK6: ¬ | GL6: ¬ | GM6: ¬ | GN6: ¬ | GO6: ¬ | GP6: ¬ | GQ6: ¬ | GR6: ¬ | GS6: ¬ | GT6: ¬ | GU6: ¬ | GV6: ¬ | GW6: ¬ | GX6: ¬ | GY6: ¬ | GZ6: ¬ | HA6: ¬ | HB6: ¬ | HC6: ¬ | HD6: ¬ | HE6: ¬ | HF6: ¬ | HG6: ¬ | HH6: ¬ | IC6: - | ID6: ● | IE6: ● | IF6: - | IG6: - | IH6: - | II6: ● | IJ6: - | IK6: ● | IL6: - | IM6: - | IN6: - | IO6: - | IP6: - | IQ6: - | IR6: - | IS6: - | IT6: Auspex ● | Beast's Hackles | IU6: Celerity ● | IV6: Obfuscate ● | Face in the Crowd | IW6: Resilience ● | IX6: ¬ | IY6: ¬ | IZ6: ¬ | JA6: ¬ | JB6: ¬ | JC6: ¬ | JD6: ¬ | JE6: ¬ | JF6: ¬ | JG6: ¬ | JH6: ¬ | JI6: ¬ | JJ6: ¬ | JK6: ¬ | JL6: ¬ | JM6: ¬ | JN6: ¬ | JO6: ¬ | JP6: ¬ | JQ6: ¬ | JR6: ¬ | JS6: ¬ | JT6: ¬ | JU6: ¬ | JV6: ¬ | JW6: ¬ | JX6: Cost: Free (1 V for Insight) • Pool: - - Composure & Closed Book • Instant • Scene | JY6: Cost: 1 V per effect • Pool: - • Reflexive • 1 turn | JZ6: Cost: - • Pool: - • Instant • Scene | KA6: Cost: 1 V per effect • Pool: - • Reflexive • 1 turn | KB6: ¬ | KC6: ¬ | KD6: ¬ | KE6: ¬ | KF6: ¬ | KG6: ¬ | KH6: ¬ | KI6: ¬ | KJ6: ¬ | KK6: ¬ | KL6: ¬ | KM6: ¬ | KN6: ¬ | KO6: ¬ | KP6: ¬ | KQ6: ¬ | KR6: ¬ | KS6: ¬ | KT6: ¬ | KU6: ¬ | KV6: ¬ | KW6: ¬ | KX6: ¬ | KY6: ¬ | KZ6: ¬ | LA6: ¬ | LB6: Add Auspex dots to any rolls to resist surprise. Access to Tier 1 Auspex Insight questions. | LC6: Persistent improved Defence or Dodge. Activate for supernatural speed benefits. Unnatural Grace: add Celerity dots as bonus dice to non-combat speed-based pools. | LD6: Blend into surroundings, visible but unnoticeable. Predatory aura fully on or off. Leaving combat: Wits + Composure - Obfuscate to notice; auto Clash of Wills vs Auspex. | LE6: Downgrade damage and increase Stamina. Improve Armour and Defences. Unnatural Fortitude: add Resilience dots as bonus dice to non-combat Stamina pools. | LF6: ¬ | LG6: ¬ | LH6: ¬ | LI6: ¬ | LJ6: ¬ | LK6: ¬ | LL6: ¬ | LM6: ¬ | LN6: ¬ | LO6: ¬ | LP6: ¬ | LQ6: ¬ | LR6: ¬ | LS6: ¬ | LT6: ¬ | LU6: ¬ | LV6: ¬ | LW6: ¬ | LX6: ¬ | LY6: ¬ | LZ6: ¬ | MA6: ¬ | MB6: ¬ | MC6: ¬ | MD6: ¬ | ME6: ¬ | MF6: Aloof Curse | MG6: ¬ | MH6: ¬ | MI6: ¬ | MJ6: ¬ | MK6: First Touchstone attaches to Humanity 7; losing it detaches on first Humanity loss. Breaking points always treated as one step lower. | ML6: ¬ | MN6: ¬ | MO6: ¬ | MP6: 5 | MQ6: 11 | MR6: 8 | MS6: Uncover a lost piece of information. | MT6: Uncover forbidden knowledge. | MU6: Point out an absurdity in the current state of affairs to lighten the tone. | MV6: Favour wit and cunning over direct self-defence in a situation of serious danger. | MW6: ¬ | MX6: ¬ | MY6: ¬ | MZ6: mid 30s
A7: tblCharDataCharles | B7: 46104 | C7: 1 | D7: 30 | E7: Leo T | F7: Charles Mercer-Willows | G7: Cult Leader | H7: he/him | I7: Ventrue | J7: D:\Terra Mortis\Character Sheets\Sheet Elements\Ventrue icon.svg | K7: Gorgons | L7: Circle of the Crone | M7: D:\Terra Mortis\Character Sheets\Sheet Elements\Crone icon.svg | N7: Nurturer | O7: Cult Leader | P7: ¬ | Q7: ●● | R7: ●●● | S7: ●●● | T7: ●● | U7: ●● | V7: ●● | W7: ●●● | X7: ●●● | Y7: ●● | AA7: ● | AB7: ●●● | AE7: ●●● | AH7: ● | AK7: ●● | AL7: ● | AP7: ● | AQ7: ● | AR7: ●●●● | AT7: ●●● | AU7: ● | AW7: ●● | AX7: ●○○○○○○○○○ | AY7: 1 | BA7: □□□□□□□■■■■■■■■ | BB7: 5 / 5 | BC7: □□□□□■■■■■ | BD7: 9 / 10 | BE7: □□□□□□□□□■■■■■■■■■■■ | BF7: 1 | BG7: Animals | BJ7: sculpting | BM7: Judeo-Christian Lore | BS7: rifles | BZ7: oratory | CF7: 2 | CG7: 2 | CH7: 3 | CI7: Crone | CJ7: ●●● | CK7: Carthian | CL7: - | CM7: Invictus | CN7: - | CO7: Lance | CP7: - | CQ7: ● | CR7: ● | CS7: - | CT7: ●●●●● | CU7: ●●●●● | CV7: <NAME REQUIRED> | CW7: - | CY7: 5 | CZ7: ~ | DA7: ○ | DB7: ○ | DC7: ○ | DD7: ○ (Ezekiel (Son)) | DE7: ○ (Unnamed congregant) | DF7: ● | DG7: ● | DH7: ● | DI7: ● | DJ7: ● | DK7: Closed Book ● | DL7: Inspiring ●●● | DM7: Secret Society Junkie ● | DN7: Viral Mythology ●●● | DO7: ¬ | DP7: ¬ | DQ7: ¬ | DR7: ¬ | DS7: ¬ | DT7: ¬ | DU7: ¬ | DV7: ¬ | DW7: ¬ | DX7: ¬ | DY7: ¬ | DZ7: ¬ | EA7: ¬ | EB7: ¬ | EC7: ¬ | ED7: ¬ | EE7: ¬ | EF7: ¬ | EG7: ¬ | EH7: ¬ | EI7: ¬ | EJ7: ¬ | EK7: ¬ | EL7: ¬ | EM7: ¬ | EN7: ¬ | EO7: Add dots to Doors and as bonus to contest Social assessments. | EP7: Roll Presence + Expression to confer the Inspired Condition. | EQ7: Dots in Status or Mystery Cult Initiation representing human secret societies also count as dots of Herd. | ER7: Presence + Expression vs Wits + Composure to inflict contagious awe. Allies and Herd double their yield. | ES7: ¬ | ET7: ¬ | EU7: ¬ | EV7: ¬ | EW7: ¬ | EX7: ¬ | EY7: ¬ | EZ7: ¬ | FA7: ¬ | FB7: ¬ | FC7: ¬ | FD7: ¬ | FE7: ¬ | FF7: ¬ | FG7: ¬ | FH7: ¬ | FI7: ¬ | FJ7: ¬ | FK7: ¬ | FL7: ¬ | FM7: ¬ | FN7: ¬ | FO7: ¬ | FP7: ¬ | FQ7: ¬ | FR7: ¬ | FS7: 5 / 5 | FT7: □□□□□ | FU7: Allies | FV7: Allies | FW7: Allies | FX7: Allies | FY7: Resources | FZ7: ¬ | GA7: ¬ | GB7: ¬ | GC7: ¬ | GD7: ¬ | GE7: ¬ | GF7: ¬ | GG7: ¬ | GH7: ¬ | GI7: ¬ | GJ7: ¬ | GK7: ¬ | GL7: ¬ | GM7: ¬ | GN7: ¬ | GO7: Legal | GP7: Media | GQ7: Occult | GR7: Underworld | GS7: ¬ | GT7: ¬ | GU7: ¬ | GV7: ¬ | GW7: ¬ | GX7: ¬ | GY7: ¬ | GZ7: ¬ | HA7: ¬ | HB7: ¬ | HC7: ¬ | HD7: ¬ | HE7: ¬ | HF7: ¬ | HG7: ¬ | HH7: ¬ | HI7: ●●● | HJ7: ●●● | HK7: ●●● | HL7: ●●● | HM7: ● | IC7: ● | ID7: - | IE7: - | IF7: ●● | IG7: - | IH7: - | II7: - | IJ7: ●● | IK7: - | IL7: - | IM7: ●● | IN7: - | IO7: ●● | IP7: - | IQ7: - | IR7: ● | IS7: ● | IT7: Animalism ● | Feral Whispers | IU7: Dominate ● | Mesmerise | IV7: Dominate ●● | Iron Edict | IW7: Protean ● | Unmarked Grave | IX7: Protean ●● | Predatory Aspect | IY7: Blood Sorcery | Creation ● | IZ7: Blood Sorcery | Creation ●● | JA7: Blood Sorcery | Protection ● | JB7: Blood Sorcery | Transmutation ● | JC7: Cruac ● | Fires of Inspiration | JD7: Cruac ●● | Wisdom of the Soul | JE7: ¬ | JF7: ¬ | JG7: ¬ | JH7: ¬ | JI7: ¬ | JJ7: ¬ | JK7: ¬ | JL7: ¬ | JM7: ¬ | JN7: ¬ | JO7: ¬ | JP7: ¬ | JQ7: ¬ | JR7: ¬ | JS7: ¬ | JT7: ¬ | JU7: ¬ | JV7: ¬ | JW7: ¬ | JX7: Cost: - • Pool: 5 • Instant • Scene (may persist) | JY7: Cost: - -3 in combat unless Blinded • Pool: 8 v Resolve + BP • Instant • Instant | JZ7: Cost: 1 V (0 in bond) (req: Mesmerised); -3 in combat unless Blinded • Pool: - • Instant • Instant | KA7: Cost: Varies • Pool: - • Instant • Indefinite | KB7: Cost: 1 V • Pool: - • Instant • Scene | KC7: ¬ | KD7: ¬ | KE7: ¬ | KF7: ¬ | KG7: Cost: 1 V 1 Successes • Pool: 8 • Ritual • 1 night | KH7: Cost: 1 V 2 Successes • Pool: 8 • Ritual • Instant | KI7: ¬ | KJ7: ¬ | KK7: ¬ | KL7: ¬ | KM7: ¬ | KN7: ¬ | KO7: ¬ | KP7: ¬ | KQ7: ¬ | KR7: ¬ | KS7: ¬ | KT7: ¬ | KU7: ¬ | KV7: ¬ | KW7: ¬ | KX7: ¬ | KY7: ¬ | KZ7: ¬ | LA7: ¬ | LB7: Speak with and command animals. | LC7: Impose Mesmerised Condition. Control with short commands. | LD7: Impose Dominated Condition. Give long, detailed commands. | LE7: Merge with soil. | LF7: Take on animal traits. | LG7: Summon liquids, dead organic matter, sensory phenomena. Bonus/penalty = Potency. | LH7: Summon living insects, vermin, amphibians, fungi, plants, drugs, gases. Under mental command while concentrating. | LI7: Subtract Potency from ritual rolls targeting subject. Heal bashing in vampires. Protect from the Kiss (add Potency to resistance). | LJ7: Minor cosmetic changes to living subjects. Warp dead matter. Animate liquids. | LK7: Gain dots in Cruac to Craft or Expression to create a specific work of art, but penalises all other such actions outside that. | LL7: Reveal if mortal/vampire/ghoul; Humanity rating; diablerie | LM7: ¬ | LN7: ¬ | LO7: ¬ | LP7: ¬ | LQ7: ¬ | LR7: ¬ | LS7: ¬ | LT7: ¬ | LU7: ¬ | LV7: ¬ | LW7: ¬ | LX7: ¬ | LY7: ¬ | LZ7: ¬ | MA7: ¬ | MB7: ¬ | MC7: ¬ | MD7: ¬ | ME7: ¬ | MF7: Aloof Curse | MG7: ¬ | MH7: ¬ | MI7: ¬ | MJ7: ¬ | MK7: First Touchstone attaches to Humanity 7; losing it detaches on first Humanity loss. Breaking points always treated as one step lower. | ML7: ¬ | MN7: ¬ | MO7: ¬ | MP7: 5 | MQ7: 9 | MR7: 3 | MS7: Put yourself out to help another succeed. | MT7: Take full responsibility for another's dangerous mistake. | MU7: Convince someone to deny logic because of your word. | MV7: Risk exile or death to defend your cult's belief system. | MW7: ¬ | MX7: ¬ | MY7: ¬ | MZ7: mid 30s
A8: tblCharDataCharlie | B8: 46104 | C8: 0 | D8: 62 | E8: Kurtis W | F8: Charlie Ballsack | G8: Putrescent Invictus secret police | H8: it/it | I8: Nosferatu | J8: D:\Terra Mortis\Character Sheets\Sheet Elements\Nosferatu icon.svg | K8: Order of Sir Martin | L8: Invictus | M8: D:\Terra Mortis\Character Sheets\Sheet Elements\Invictus icon.svg | N8: Conformist | O8: Rebel | P8: ¬ | Q8: ● | R8: ●●● | S8: ●●● | T8: ●●● | U8: ●●● | V8: ●●● | W8: ●● | X8: ●● | Y8: ●●● | AB8: ●●●●† | AH8: ●● | AL8: ●● | AM8: ●●●† | AO8: ●●●●○† | AQ8: ●●† | AS8: ●●† | AU8: ●●● | AX8: ●○○○○○○○○○ | AY8: 1 | BA8: □□□□□□□□■■■■■■■ | BB8: 6 / 6 | BC8: □□□□□□■■■■ | BD8: 10 / 10 | BE8: □□□□□□□□□□■■■■■■■■■■ | BF8: 1 | BG8: Animals | BJ8: Smithing | BU8: Coward Punch | BW8: Lgt Weapons +2, Weapon & Shield +2 | CA8: Interrogation | CF8: 1 | CG8: 2 | CH8: 3 | CI8: Invictus | CJ8: ●●● | CK8: Carthian | CL8: - | CM8: Crone | CN8: - | CO8: Lance | CP8: - | CQ8: ●●● | CR8: ●●● | CS8: - | CT8: ●●●●● | CU8: ●●●●● | CV8: The Ashen Path | CW8: ●●●● | CY8: 4 | CZ8: ˅ | DA8: ○ | DB8: ○ | DC8: ○ | DD8: ○ | DE8: ○ (Priya (saved assailant)) | DF8: ○ | DG8: ● | DH8: ● | DI8: ● | DJ8: ● | DK8: Area of Expertise (Coward Punch) ● | DL8: Area of Expertise (Light Weapons) ● | DM8: Area of Expertise (Weapon & Shield) ● | DN8: Closed Book ●●● | DO8: Defensive Combat (Weaponry) ● | DP8: Friends in High Places ● | DQ8: Indomitable ●● | DR8: Interdisciplinary Specialty (Coward Punch) ● | DS8: Invested ● | DT8: Secret Society Junkie ● | DU8: Courtoisie ● | Establish the Duel | DV8: Courtoisie ●●● | Demanding Attention | DW8: Light Weapons ●● | Thrust | DX8: Light Weapons ●●●● | Flurry | DY8: Strength Performance ● | Strength Tricks | DZ8: Strength Performance ●● | Lifting | EA8: Strength Performance ●●● | Push/Pull | EB8: Strength Performance ●●●● | Stronger Than You | EC8: Weapon and Shield ● | Shield Bash | ED8: Weapon and Shield ●●● | Pin Weapon | EE8: ¬ | EF8: ¬ | EG8: ¬ | EH8: ¬ | EI8: ¬ | EJ8: ¬ | EK8: ¬ | EL8: ¬ | EM8: ¬ | EN8: ¬ | EO8: Raise one Specialty's die bonus to +2. | EP8: Raise one Specialty's die bonus to +2. | EQ8: Raise one Specialty's die bonus to +2. | ER8: Add dots to Doors and as bonus to contest Social assessments. | ES8: Substitute chosen Skill for Athletics in Defence, if equipped for that Skill. | ET8: Once per chapter, use Invictus Status as Mortal Status in areas you don't possess. Drawback: Other Invictus may be informed. | EU8: +2 to contest or resist supernatural mental influence. | EV8: Apply one Specialty's bonus to relevant rolls of any Skill (not unskilled). | EW8: Distribute Invictus Status dots among free Herd, Mentor, Resources and Retainer. | EX8: Dots in Status or Mystery Cult Initiation representing human secret societies also count as dots of Herd. | EY8: Choose an attacker. So long as you don't attack anyone else, add Weaponry as a Defence bonus against outside parties, and deal a point of lethal damage when an outside party enters range. | EZ8: Once you Establish the Duel, if your opponent tries to disengage or attack someone else, you can deal your Socialise dots in lethal damage and leave him Knocked Down. | FA8: Sacrifice points of Defence for bonus attack dice. | FB8: Inflict a point of lethal damage per turn to opponents in range when your Defence is available. | FC8: Take +1 to nonviolent feats of strength, +2 when using Expression or Intimidation. | FD8: Receive the rote quality on Strength + Stamina feats and combat actions to demolish structures. | FE8: Double your effective Strength to shift objects across a plane, or quintuple it with wheels or other friction reductions. | FF8: Successful Strength rolls add an additional free success. | FG8: Add your shield's Size as bonus dice when dodging. Dodge successes in excess of your opponent's inflict bashing damage. | FH8: Disarm assailants on missed melee attacks. | FI8: ¬ | FJ8: ¬ | FK8: ¬ | FL8: ¬ | FM8: ¬ | FN8: ¬ | FO8: ¬ | FP8: ¬ | FQ8: ¬ | FR8: ¬ | FS8: 5 / 5 | FT8: □□□□□ | FU8: Allies | FV8: Contacts | FW8: Resources | FX8: ¬ | FY8: ¬ | FZ8: ¬ | GA8: ¬ | GB8: ¬ | GC8: ¬ | GD8: ¬ | GE8: ¬ | GF8: ¬ | GG8: ¬ | GH8: ¬ | GI8: ¬ | GJ8: ¬ | GK8: ¬ | GL8: ¬ | GM8: ¬ | GN8: ¬ | GO8: Police | GP8: Street, Underworld, Police | GQ8: ¬ | GR8: ¬ | GS8: ¬ | GT8: ¬ | GU8: ¬ | GV8: ¬ | GW8: ¬ | GX8: ¬ | GY8: ¬ | GZ8: ¬ | HA8: ¬ | HB8: ¬ | HC8: ¬ | HD8: ¬ | HE8: ¬ | HF8: ¬ | HG8: ¬ | HH8: ¬ | HI8: ● | HJ8: ●●● | HK8: ●●●●● | IC8: - | ID8: - | IE8: ● | IF8: - | IG8: - | IH8: ● | II8: ●●●●● | IJ8: - | IK8: - | IL8: - | IM8: - | IN8: - | IO8: - | IP8: - | IQ8: - | IR8: - | IS8: - | IT8: Celerity ● | IU8: Nightmare ● | Dread Presence | IV8: Obfuscate ● | Face in the Crowd | IW8: Obfuscate ●● | Touch of Shadow | IX8: Obfuscate ●●● | Cloak of Night | IY8: Obfuscate ●●●● | The Familiar Stranger | IZ8: Obfuscate ●●●●● | Oubliette | JA8: Devotion | Repulsive Mien | JB8: Oath of Fealty ● | JC8: Oath of the Hard Motherfucker ●● | JD8: Oath of the Safe Word ●● | JE8: Oath of the True Knight ●●●● | JF8: ¬ | JG8: ¬ | JH8: ¬ | JI8: ¬ | JJ8: ¬ | JK8: ¬ | JL8: ¬ | JM8: ¬ | JN8: ¬ | JO8: ¬ | JP8: ¬ | JQ8: ¬ | JR8: ¬ | JS8: ¬ | JT8: ¬ | JU8: ¬ | JV8: ¬ | JW8: ¬ | JX8: Cost: 1 V per effect • Pool: - • Reflexive • 1 turn | JY8: Cost: - • Pool: - • Instant • Scene | JZ8: Cost: - • Pool: - • Instant • Scene | KA8: Cost: 1 V • Pool: 10 • Instant • Scene | KB8: Cost: 1 V • Pool: - • None | KC8: Cost: 2 V • Pool: - • None | KD8: Cost: Free (Haven) / 3-9 V & 1 WP • Pool: - • Instant • 1 week per BP | KE8: Cost: 1 V (Order of Sir Martin Only); only affects other Leper Knights with concrete reasons for mistrust • Pool: - • Reflexive • Scene | KF8: ¬ | KG8: ¬ | KH8: ¬ | KI8: ¬ | KJ8: ¬ | KK8: ¬ | KL8: ¬ | KM8: ¬ | KN8: ¬ | KO8: ¬ | KP8: ¬ | KQ8: ¬ | KR8: ¬ | KS8: ¬ | KT8: ¬ | KU8: ¬ | KV8: ¬ | KW8: ¬ | KX8: ¬ | KY8: ¬ | KZ8: ¬ | LA8: ¬ | LB8: Persistent improved Defence or Dodge. Activate for supernatural speed benefits. Unnatural Grace: add Celerity dots as bonus dice to non-combat speed-based pools. | LC8: Conjure brief illusions. Improve Intimidation. Prevent foes spending Willpower. | LD8: Blend into surroundings, visible but unnoticeable. Predatory aura fully on or off. Leaving combat: Wits + Composure - Obfuscate to notice; auto Clash of Wills vs Auspex. | LE8: Cast Face in the Crowd on object or person. Free and unlimited duration on carried/worn objects if not drawing attention. | LF8: Become invisible. Leaving combat: auto Clash of Wills vs Auspex 2. | LG8: Disguise self or other as a desired person. Free unlimited duration to reskin carried/worn objects, but no equipment bonus without Vitae. | LH8: Always active on Haven/Safe Place at no cost. Further uses at standard cost. Use Obfuscate at distance on anything in area. | LI8: As Dread Presence but -3 to all actions against the Knight. Targets cannot spend WP to enhance actions against Knight. Victims can lash out with Beast to end the effect. Reflexive brief illusions affecting Knight's person (narrative only). | LJ8: Draw Invictus Status in Vitae weekly from liege without feeding. Liege knows when you lie. | LK8: Kill a Carthian or oathbreaker for Invictus Status 1, Friends in High Places 1, 9-Again on two Skills, and Allies/Contacts/Resources 1. All stripped if broken. | LL8: Share Willpower and one Social Merit with oath partner. Either can end to briefly paralyse the other. | LM8: Impartial covenant defender. Can't consume Vitae from any source; can't be woken from torpor by blood. Invictus Status protects from mental Disciplines and Kindred/ghoul attacks. | LN8: ¬ | LO8: ¬ | LP8: ¬ | LQ8: ¬ | LR8: ¬ | LS8: ¬ | LT8: ¬ | LU8: ¬ | LV8: ¬ | LW8: ¬ | LX8: ¬ | LY8: ¬ | LZ8: ¬ | MA8: ¬ | MB8: ¬ | MC8: ¬ | MD8: ¬ | ME8: ¬ | MF8: Lonely Curse | MG8: ¬ | MH8: Rat King/Queen | MI8: ¬ | MJ8: ¬ | MK8: With mortals, Humanity counts –2; Presence/Manipulation failures become dramatic failures. Intimidation and Subterfuge unaffected. | ML8: ¬ | MM8: Surrounded by vermin; all Social rolls fail except Intimidation; WP can dismiss. | MN8: ¬ | MO8: ¬ | MP8: 5 | MQ8: 11 | MR8: 5 | MS8: Choose an obviously disadvantageous path because it fits with protocol. | MT8: Stand by the losing side with shield at the ready, because it is your side. | MU8: Openly flout a tradition. | MV8: Openly flout a Kindred Tradition or a covenant taboo. | MW8: ¬ | MX8: ¬ | MY8: ¬ | MZ8: indeterminate
A9: tblCharDataConrad | B9: 46104 | C9: 0 | D9: 40 | E9: Arnold W | F9: Conrad Sondergaard | G9: Occult gentleman detective | H9: he/him | I9: Mekhet | J9: D:\Terra Mortis\Character Sheets\Sheet Elements\Mekhet icon.svg | K9: ¬ | L9: Lancea et Sanctum | M9: D:\Terra Mortis\Character Sheets\Sheet Elements\Lance icon.svg | N9: Follower | O9: Spy | P9: ¬ | Q9: ●●●● | R9: ●●● | S9: ●● | T9: ● | U9: ●●● | V9: ●● | W9: ●● | X9: ●● | Y9: ●●● | Z9: ●●●● | AC9: ●●●† | AE9: ●●●● | AK9: ● | AM9: ●●●† | AQ9: ●●●○† | AW9: ● | AX9: ●●○○○○○○○○ | AY9: 2 | AZ9: † | BA9: □□□□□□□■■■■■■■■ | BB9: 5 / 5 | BC9: □□□□□■■■■■ | BD9: 11 / 11 | BE9: □□□□□□□□□□□■■■■■■■■■ | BF9: 2 | BG9: Animals | BH9: Criminology | BK9: Crime Scene | BS9: Pistols | BU9: Stalking | BY9: Motives | CF9: 2 | CG9: 2 | CH9: 3 | CI9: Lance | CJ9: ●●● | CK9: Carthian | CL9: - | CM9: Crone | CN9: - | CO9: Invictus | CP9: - | CQ9: - | CR9: - | CS9: - | CT9: ● | CU9: - | CW9: ●●●● | CX9: Private Investigator | CY9: 7 | CZ9: ~ | DA9: ○ | DB9: ○ | DC9: ○ | DD9: ● | DE9: ● (Elise (Granddaughter)) | DF9: ● | DG9: ● | DH9: ● | DI9: ● | DJ9: ● | DK9: Acute Senses ● | DL9: ¬ | DM9: ¬ | DN9: ¬ | DO9: ¬ | DP9: ¬ | DQ9: ¬ | DR9: ¬ | DS9: ¬ | DT9: ¬ | DU9: ¬ | DV9: ¬ | DW9: ¬ | DX9: ¬ | DY9: ¬ | DZ9: ¬ | EA9: ¬ | EB9: ¬ | EC9: ¬ | ED9: ¬ | EE9: ¬ | EF9: ¬ | EG9: ¬ | EH9: ¬ | EI9: ¬ | EJ9: ¬ | EK9: ¬ | EL9: ¬ | EM9: ¬ | EN9: ¬ | EO9: Add Blood Potency to sensory rolls. Exceptional success can inflict Obsession. | EP9: ¬ | EQ9: ¬ | ER9: ¬ | ES9: ¬ | ET9: ¬ | EU9: ¬ | EV9: ¬ | EW9: ¬ | EX9: ¬ | EY9: ¬ | EZ9: ¬ | FA9: ¬ | FB9: ¬ | FC9: ¬ | FD9: ¬ | FE9: ¬ | FF9: ¬ | FG9: ¬ | FH9: ¬ | FI9: ¬ | FJ9: ¬ | FK9: ¬ | FL9: ¬ | FM9: ¬ | FN9: ¬ | FO9: ¬ | FP9: ¬ | FQ9: ¬ | FR9: ¬ | FS9: 5 / 5 | FT9: □□□□□ | FU9: Contacts | FV9: ¬ | FW9: ¬ | FX9: ¬ | FY9: ¬ | FZ9: ¬ | GA9: ¬ | GB9: ¬ | GC9: ¬ | GD9: ¬ | GE9: ¬ | GF9: ¬ | GG9: ¬ | GH9: ¬ | GI9: ¬ | GJ9: ¬ | GK9: ¬ | GL9: ¬ | GM9: ¬ | GN9: ¬ | GO9: Police, Underworld | GP9: ¬ | GQ9: ¬ | GR9: ¬ | GS9: ¬ | GT9: ¬ | GU9: ¬ | GV9: ¬ | GW9: ¬ | GX9: ¬ | GY9: ¬ | GZ9: ¬ | HA9: ¬ | HB9: ¬ | HC9: ¬ | HD9: ¬ | HE9: ¬ | HF9: ¬ | HG9: ¬ | HH9: ¬ | HI9: ●● | IC9: - | ID9: ●●●●● | IE9: - | IF9: - | IG9: - | IH9: - | II9: ● | IJ9: - | IK9: - | IL9: - | IM9: - | IN9: ●●●● | IO9: - | IP9: - | IQ9: ● | IR9: ●●●● | IS9: ● | IT9: Auspex ● | Beast's Hackles | IU9: Auspex ●● | Uncanny Perception | IV9: Auspex ●●● | Spirit's Touch | IW9: Auspex ●●●● | Lay Open the Mind | IX9: Auspex ●●●●● | Twilight Projection | IY9: Obfuscate ● | Face in the Crowd | IZ9: Blood Sorcery | Divination ● | JA9: Blood Sorcery | Protection ● | JB9: Blood Sorcery | Protection ●● | JC9: Blood Sorcery | Protection ●●● | JD9: Blood Sorcery | Protection ●●●● | JE9: Blood Sorcery | Transmutation ● | JF9: ¬ | JG9: ¬ | JH9: ¬ | JI9: ¬ | JJ9: ¬ | JK9: ¬ | JL9: ¬ | JM9: ¬ | JN9: ¬ | JO9: ¬ | JP9: ¬ | JQ9: ¬ | JR9: ¬ | JS9: ¬ | JT9: ¬ | JU9: ¬ | JV9: ¬ | JW9: ¬ | JX9: Cost: Free (1 V for Insight) • Pool: - - Composure & Closed Book • Instant • Scene | JY9: Cost: Free (1 V for Insight) Must perceive target • Pool: - • Instant • Scene | JZ9: Cost: Free (1 WP for clash / 1 V for Insight) • Pool: - v Resolve + Stealth + Obf • Reflexive • Immediate | KA9: Cost: 1 V • Pool: 8 v Resolve + BP • Instant • Scene | KB9: Cost: 2 V • Pool: 13 • Instant • Scene (while projected) | KC9: Cost: - • Pool: - • Instant • Scene | KD9: ¬ | KE9: ¬ | KF9: ¬ | KG9: ¬ | KH9: ¬ | KI9: ¬ | KJ9: ¬ | KK9: ¬ | KL9: ¬ | KM9: ¬ | KN9: ¬ | KO9: ¬ | KP9: ¬ | KQ9: ¬ | KR9: ¬ | KS9: ¬ | KT9: ¬ | KU9: ¬ | KV9: ¬ | KW9: ¬ | KX9: ¬ | KY9: ¬ | KZ9: ¬ | LA9: ¬ | LB9: Add Auspex dots to any rolls to resist surprise. Access to Tier 1 Auspex Insight questions. | LC9: Persistent Acute Senses Merit, doubles actual merit. Access to Tier 2 Auspex Insight questions. | LD9: Passively scan for anyone under Obfuscate 1 or 3, can provoke a challenge. Access to Tier 3 Auspex Insight questions. | LE9: Telepathy and mind-reading. Invoke Conditions. | LF9: Project senses into Twilight. May use Auspex 1-3 once per scene; cannot spend blood for additional uses. | LG9: Blend into surroundings, visible but unnoticeable. Predatory aura fully on or off. Leaving combat: Wits + Composure - Obfuscate to notice; auto Clash of Wills vs Auspex. | LH9: Glimpse fragmented details about intended actions. Learn basic info about a target. | LI9: Subtract Potency from ritual rolls targeting subject. Heal bashing in vampires. Protect from the Kiss (add Potency to resistance). | LJ9: Grant armour. Ward environmental hazards. Resist frenzy. | LK9: Render untouchable or unable to be fed from. Ward physical Discipline effects. Protect from staking. Heal lethal in vampires. | LL9: Ward mental Discipline effects (Majesty, Dominate). Protect from Vinculum. Remain active during day (Potency turns). | LM9: Minor cosmetic changes to living subjects. Warp dead matter. Animate liquids. | LN9: ¬ | LO9: ¬ | LP9: ¬ | LQ9: ¬ | LR9: ¬ | LS9: ¬ | LT9: ¬ | LU9: ¬ | LV9: ¬ | LW9: ¬ | LX9: ¬ | LY9: ¬ | LZ9: ¬ | MA9: ¬ | MB9: ¬ | MC9: ¬ | MD9: ¬ | ME9: ¬ | MF9: Tenebrous Curse | MG9: ¬ | MH9: ¬ | MI9: ¬ | MJ9: ¬ | MK9: Gain an extra bane at Humanity 6 (doesn't count towards cap); Humanity counts –1 for all Humanity-based banes. | ML9: ¬ | MN9: ¬ | MO9: ¬ | MP9: 5 | MQ9: 9 | MR9: 3 | MS9: Follow a directive blindly, for the sake of following. | MT9: Follow a dangerous directive without hesitation. | MU9: Build a new identity or uncover a secret. | MV9: Uncover a damning secret that could end someone. | MW9: ¬ | MX9: ¬ | MY9: ¬ | MZ9: late 20s
A10: tblCharDataCyrus | B10: 46104 | C10: 10 | D10: 26 | E10: Bill C | F10: Cyrus Reynolds | G10: Globetrotting DJ | H10: he/him | I10: Daeva | J10: D:\Terra Mortis\Character Sheets\Sheet Elements\Daeva icon.svg | K10: ¬ | L10: Circle of the Crone | M10: D:\Terra Mortis\Character Sheets\Sheet Elements\Crone icon.svg | N10: Courtesan | O10: Social Chameleon | P10: ¬ | Q10: ●● | R10: ●●● | S10: ●● | T10: ●● | U10: ●●● | V10: ●● | W10: ●●● | X10: ●● | Y10: ●●● | AA10: ●● | AE10: ●● | AH10: ●●● | AI10: ●● | AK10: ● | AM10: ● | AQ10: ●●● | AR10: ●●● | AU10: ●●● | AV10: ●● | AX10: ●○○○○○○○○○ | AY10: 1 | BA10: □□□□□□□■■■■■■■■ | BB10: 5 / 5 | BC10: □□□□□■■■■■ | BD10: 9 / 10 | BE10: □□□□□□□□□■■■■■■■■■■■ | BF10: 1 | BG10: Animals | CF10: 2 | CG10: 2 | CH10: 1 | CI10: Crone | CJ10: ● | CK10: Carthian | CL10: - | CM10: Invictus | CN10: - | CO10: Lance | CP10: - | CQ10: ● | CR10: ● | CS10: - | CT10: ●● | CU10: - | CW10: - | CY10: 6 | CZ10: ~ | DA10: ○ | DB10: ○ | DC10: ○ | DD10: ○ | DE10: ● (One living parent (unnamed)) | DF10: ● (Unnamed venue regular) | DG10: ● | DH10: ● | DI10: ● | DJ10: ● | DK10: Casual User ● | DL10: Fame ● | DM10: Language (German) ● | DN10: Language (Spanish) ● | DO10: ¬ | DP10: ¬ | DQ10: ¬ | DR10: ¬ | DS10: ¬ | DT10: ¬ | DU10: ¬ | DV10: ¬ | DW10: ¬ | DX10: ¬ | DY10: ¬ | DZ10: ¬ | EA10: ¬ | EB10: ¬ | EC10: ¬ | ED10: ¬ | EE10: ¬ | EF10: ¬ | EG10: ¬ | EH10: ¬ | EI10: ¬ | EJ10: ¬ | EK10: ¬ | EL10: ¬ | EM10: ¬ | EN10: ¬ | EO10: Benefits of one dot Carthian Status for social bonuses and Carthian Law effects. Once per story, call a small favour. | EP10: Known: (•) locally, (••) broadly, (•••) universally. Add dots to Social rolls on impressed targets, and to rolls to find/identify you. | EQ10: Speak, read and write a chosen language. | ER10: Speak, read and write a chosen language. | ES10: ¬ | ET10: ¬ | EU10: ¬ | EV10: ¬ | EW10: ¬ | EX10: ¬ | EY10: ¬ | EZ10: ¬ | FA10: ¬ | FB10: ¬ | FC10: ¬ | FD10: ¬ | FE10: ¬ | FF10: ¬ | FG10: ¬ | FH10: ¬ | FI10: ¬ | FJ10: ¬ | FK10: ¬ | FL10: ¬ | FM10: ¬ | FN10: ¬ | FO10: ¬ | FP10: ¬ | FQ10: ¬ | FR10: ¬ | FS10: 3 / 3 | FT10: □□□ | FU10: Allies | FV10: Contacts | FW10: Resources | FX10: Retainer | FY10: Retainer | FZ10: ¬ | GA10: ¬ | GB10: ¬ | GC10: ¬ | GD10: ¬ | GE10: ¬ | GF10: ¬ | GG10: ¬ | GH10: ¬ | GI10: ¬ | GJ10: ¬ | GK10: ¬ | GL10: ¬ | GM10: ¬ | GN10: ¬ | GO10: Street | GP10: ¬ | GQ10: ¬ | GR10: Melody | GS10: Rhythm | GT10: ¬ | GU10: ¬ | GV10: ¬ | GW10: ¬ | GX10: ¬ | GY10: ¬ | GZ10: ¬ | HA10: ¬ | HB10: ¬ | HC10: ¬ | HD10: ¬ | HE10: ¬ | HF10: ¬ | HG10: ¬ | HH10: ¬ | HI10: ●● | HJ10: ●● | HK10: ● | HL10: ● | HM10: ● | IC10: - | ID10: - | IE10: ● | IF10: - | IG10: ●● | IH10: - | II10: - | IJ10: - | IK10: - | IL10: - | IM10: ● | IN10: - | IO10: ● | IP10: - | IQ10: ● | IR10: ● | IS10: - | IT10: Celerity ● | IU10: Majesty ● | Awe | IV10: Majesty ●● | Confidant | IW10: Blood Sorcery | Creation ● | IX10: Blood Sorcery | Divination ● | IY10: Blood Sorcery | Protection ● | IZ10: Cruac ● | Taste of Knowledge | JA10: ¬ | JB10: ¬ | JC10: ¬ | JD10: ¬ | JE10: ¬ | JF10: ¬ | JG10: ¬ | JH10: ¬ | JI10: ¬ | JJ10: ¬ | JK10: ¬ | JL10: ¬ | JM10: ¬ | JN10: ¬ | JO10: ¬ | JP10: ¬ | JQ10: ¬ | JR10: ¬ | JS10: ¬ | JT10: ¬ | JU10: ¬ | JV10: ¬ | JW10: ¬ | JX10: Cost: 1 V per effect • Pool: - • Reflexive • 1 turn | JY10: Cost: - • Pool: - • Instant • Scene | JZ10: Cost: - (req: Awed) • Pool: 8 v Resolve + BP • Contested | KA10: ¬ | KB10: ¬ | KC10: ¬ | KD10: Cost: 1 V 1 Successes • Pool: 5 • Ritual • 1 night | KE10: ¬ | KF10: ¬ | KG10: ¬ | KH10: ¬ | KI10: ¬ | KJ10: ¬ | KK10: ¬ | KL10: ¬ | KM10: ¬ | KN10: ¬ | KO10: ¬ | KP10: ¬ | KQ10: ¬ | KR10: ¬ | KS10: ¬ | KT10: ¬ | KU10: ¬ | KV10: ¬ | KW10: ¬ | KX10: ¬ | KY10: ¬ | KZ10: ¬ | LA10: ¬ | LB10: Persistent improved Defence or Dodge. Activate for supernatural speed benefits. Unnatural Grace: add Celerity dots as bonus dice to non-combat speed-based pools. | LC10: Become centre of attention. Subjects become Awed. | LD10: Impose Charmed Condition. | LE10: Summon liquids, dead organic matter, sensory phenomena. Bonus/penalty = Potency. | LF10: Glimpse fragmented details about intended actions. Learn basic info about a target. | LG10: Subtract Potency from ritual rolls targeting subject. Heal bashing in vampires. Protect from the Kiss (add Potency to resistance). | LH10: Absorb one Skill at rating 1 (or +1) from vessel's blood | LI10: ¬ | LJ10: ¬ | LK10: ¬ | LL10: ¬ | LM10: ¬ | LN10: ¬ | LO10: ¬ | LP10: ¬ | LQ10: ¬ | LR10: ¬ | LS10: ¬ | LT10: ¬ | LU10: ¬ | LV10: ¬ | LW10: ¬ | LX10: ¬ | LY10: ¬ | LZ10: ¬ | MA10: ¬ | MB10: ¬ | MC10: ¬ | MD10: ¬ | ME10: ¬ | MF10: Wanton Curse | MG10: ¬ | MH10: Rat King/Queen | MI10: ¬ | MJ10: ¬ | MK10: Hungry at 5 or fewer Vitae, Starving at 3 or fewer. Dramatic Failures on feeding cause Persistent Dependent Condition toward a mortal NPC. | ML10: ¬ | MM10: Surrounded by vermin; all Social rolls fail except Intimidation; WP can dismiss. | MN10: ¬ | MO10: ¬ | MP10: 5 | MQ10: 10 | MR10: 6 | MS10: Put yourself out for another's pleasure. | MT10: Be the last one dancing when the party is on fire. | MU10: Ingratiate yourself to a new social clique. | MV10: Burn an important bridge to guarantee acceptance in a new group. | MW10: ¬ | MX10: ¬ | MY10: ¬ | MZ10: mid 30s | NA10: Fame
A11: tblCharDataDoc | B11: 46104 | C11: 3 | D11: 20 | E11: Jessica BC | F11: Margaret 'Doc' Kane | G11: Ex-Millitary Night Doctor | H11: she/her | I11: Gangrel | J11: D:\Terra Mortis\Character Sheets\Sheet Elements\Gangrel icon.svg | K11: Kerberos | L11: Carthian Movement | M11: D:\Terra Mortis\Character Sheets\Sheet Elements\Carthian icon.svg | N11: Authoritarian | O11: Rebel | P11: Protector | Q11: ●●● | R11: ●● | S11: ●● | T11: ●● | U11: ●● | V11: ●●○ | W11: ●●● | X11: ●●● | Y11: ●●● | AD11: ●●●† | AF11: ●●● | AG11: ● | AH11: ●● | AI11: ●● | AQ11: ●●●† | AS11: ●●●† | AT11: ●● | AV11: ● | AW11: ●● | AX11: ●●○○○○○○○○ | AY11: 2 | AZ11: † | BA11: □□□□□□□□■■■■■■■ | BB11: 5 / 5 | BC11: □□□□□■■■■■ | BD11: 11 / 11 | BE11: □□□□□□□□□□□■■■■■■■■■ | BF11: 2 | BG11: Animals | BL11: Surgery | BN11: Carthian Movement | BY11: Weakness, Confidant | CA11: Veiled Threats | CF11: 2 | CG11: 1 | CH11: 2 | CI11: Carthian | CJ11: ●● | CK11: Crone | CL11: - | CM11: Invictus | CN11: - | CO11: Lance | CP11: - | CQ11: - | CR11: - | CS11: - | CT11: - | CU11: - | CW11: ●●● | CX11: Combat Medic | CY11: 6 | CZ11: ~ | DA11: ○ | DB11: ○ | DC11: ○ | DD11: ○ | DE11: ● | DF11: ● | DG11: ● | DH11: ● | DI11: ● | DJ11: ● | DK11: Carthian Pull ● | DL11: Night Doctor Surgery ●●● | DM11: Three Heads of Kerberos ● | Honing - Competitive | DN11: Three Heads of Kerberos ●● | Internalising - Competitive | DO11: Three Heads of Kerberos ●●● | Cowing - Competitive | DP11: ¬ | DQ11: ¬ | DR11: ¬ | DS11: ¬ | DT11: ¬ | DU11: ¬ | DV11: ¬ | DW11: ¬ | DX11: ¬ | DY11: ¬ | DZ11: ¬ | EA11: ¬ | EB11: ¬ | EC11: ¬ | ED11: ¬ | EE11: ¬ | EF11: ¬ | EG11: ¬ | EH11: ¬ | EI11: ¬ | EJ11: ¬ | EK11: ¬ | EL11: ¬ | EM11: ¬ | EN11: ¬ | EO11: Monthly, access Carthian Status in dots of Allies, Contacts, Haven or Herd. | EP11: Intelligence + Medicine for an hour to reduce vampire's lethal to bashing. | EQ11: Add this Merit's dots to your dice pool when lashing out with the chosen Aspect. | ER11: Voluntarily take the chosen Aspect's Condition at any time to resolve it for Beats. | ES11: On a successful lash out, forgo the normal Condition to instead impose Subservient, limited to commands fitting the chosen Aspect. | ET11: ¬ | EU11: ¬ | EV11: ¬ | EW11: ¬ | EX11: ¬ | EY11: ¬ | EZ11: ¬ | FA11: ¬ | FB11: ¬ | FC11: ¬ | FD11: ¬ | FE11: ¬ | FF11: ¬ | FG11: ¬ | FH11: ¬ | FI11: ¬ | FJ11: ¬ | FK11: ¬ | FL11: ¬ | FM11: ¬ | FN11: ¬ | FO11: ¬ | FP11: ¬ | FQ11: ¬ | FR11: ¬ | FS11: 3 / 3 | FT11: □□□ | FU11: Contacts | FV11: ¬ | FW11: ¬ | FX11: ¬ | FY11: ¬ | FZ11: ¬ | GA11: ¬ | GB11: ¬ | GC11: ¬ | GD11: ¬ | GE11: ¬ | GF11: ¬ | GG11: ¬ | GH11: ¬ | GI11: ¬ | GJ11: ¬ | GK11: ¬ | GL11: ¬ | GM11: ¬ | GN11: ¬ | GO11: health, politics | GP11: ¬ | GQ11: ¬ | GR11: ¬ | GS11: ¬ | GT11: ¬ | GU11: ¬ | GV11: ¬ | GW11: ¬ | GX11: ¬ | GY11: ¬ | GZ11: ¬ | HA11: ¬ | HB11: ¬ | HC11: ¬ | HD11: ¬ | HE11: ¬ | HF11: ¬ | HG11: ¬ | HH11: ¬ | HI11: ●● | IC11: - | ID11: - | IE11: - | IF11: - | IG11: ●●● | IH11: - | II11: - | IJ11: ● | IK11: ● | IL11: - | IM11: - | IN11: - | IO11: - | IP11: - | IQ11: - | IR11: - | IS11: - | IT11: Majesty ● | Awe | IU11: Majesty ●● | Confidant | IV11: Majesty ●●● | Green Eyes | IW11: Protean ● | Unmarked Grave | IX11: Resilience ● | IY11: Devotion | Enfeebling Aura | IZ11: ¬ | JA11: ¬ | JB11: ¬ | JC11: ¬ | JD11: ¬ | JE11: ¬ | JF11: ¬ | JG11: ¬ | JH11: ¬ | JI11: ¬ | JJ11: ¬ | JK11: ¬ | JL11: ¬ | JM11: ¬ | JN11: ¬ | JO11: ¬ | JP11: ¬ | JQ11: ¬ | JR11: ¬ | JS11: ¬ | JT11: ¬ | JU11: ¬ | JV11: ¬ | JW11: ¬ | JX11: Cost: - • Pool: - • Instant • Scene | JY11: Cost: - (req: Awed) • Pool: 9 v Resolve + BP • Contested | JZ11: Cost: 1 V (req: Charmed / Enthralled) • Pool: - • Instant • Scene | KA11: Cost: Varies • Pool: - • Instant • Indefinite | KB11: Cost: 1 V per effect • Pool: - • Reflexive • 1 turn | KC11: Cost: 1 V • Pool: 9 v Composure + BP • Contested • Scene | KD11: ¬ | KE11: ¬ | KF11: ¬ | KG11: ¬ | KH11: ¬ | KI11: ¬ | KJ11: ¬ | KK11: ¬ | KL11: ¬ | KM11: ¬ | KN11: ¬ | KO11: ¬ | KP11: ¬ | KQ11: ¬ | KR11: ¬ | KS11: ¬ | KT11: ¬ | KU11: ¬ | KV11: ¬ | KW11: ¬ | KX11: ¬ | KY11: ¬ | KZ11: ¬ | LA11: ¬ | LB11: Become centre of attention. Subjects become Awed. | LC11: Impose Charmed Condition. | LD11: Shift emotions (1 V, any number of Charmed/Enthralled targets); rage/fear causes frenzy with no resist roll (Ride the Wave normal). Requests: 1 V per target, must be spoken and heard. | LE11: Merge with soil. | LF11: Downgrade damage and increase Stamina. Improve Armour and Defences. Unnatural Fortitude: add Resilience dots as bonus dice to non-combat Stamina pools. | LG11: Sacrifice Majesty dots for the scene to remove equal dots of victim's Celerity, Resilience, or Vigour (any combination), up to successes. | LH11: ¬ | LI11: ¬ | LJ11: ¬ | LK11: ¬ | LL11: ¬ | LM11: ¬ | LN11: ¬ | LO11: ¬ | LP11: ¬ | LQ11: ¬ | LR11: ¬ | LS11: ¬ | LT11: ¬ | LU11: ¬ | LV11: ¬ | LW11: ¬ | LX11: ¬ | LY11: ¬ | LZ11: ¬ | MA11: ¬ | MB11: ¬ | MC11: ¬ | MD11: ¬ | ME11: ¬ | MF11: Feral Curse | MG11: ¬ | MH11: Rat King/Queen | MI11: ¬ | MJ11: ¬ | MK11: Frenzy resistance dice pools capped by Humanity (doesn't affect Riding the Wave). | ML11: ¬ | MM11: Surrounded by vermin; all Social rolls fail except Intimidation; WP can dismiss. | MN11: ¬ | MO11: ¬ | MP11: 5 | MQ11: 9 | MR11: 4 | MS11: Cow someone into submission. | MT11: Commit a widespread hit against a rival's mortal connections. | MU11: Openly flout a tradition. | MV11: Openly flout a Kindred Tradition or a covenant taboo. | MW11: ¬ | MX11: ¬ | MY11: ¬
A12: tblCharDataEdna | B12: 46104 | C12: 11 | D12: 46 | E12: Arlo V | F12: Edna Judge | G12: Mother Heretic | H12: she/her | I12: Nosferatu | J12: D:\Terra Mortis\Character Sheets\Sheet Elements\Nosferatu icon.svg | K12: ¬ | L12: Lancea et Sanctum | M12: D:\Terra Mortis\Character Sheets\Sheet Elements\Lance icon.svg | N12: Visionary | O12: Authoritarian | P12: Primogen | Q12: ●● | R12: ●●● | S12: ●● | T12: ● | U12: ●● | V12: ●●● | W12: ●●● | X12: ●● | Y12: ●●●● | Z12: ●●●● | AB12: ●● | AE12: ●● | AF12: ●●● | AL12: ●● | AM12: ●● | AQ12: ●● | AR12: ●●● | AS12: ●●● | AW12: ●● | AX12: ●○○○○○○○○○○○○○○○○○○ | AY12: 1 | BA12: □□□□□□□□■■■■■■■ | BB12: 6 / 6 | BC12: □□□□□□■■■■ | BD12: 9 / 10 | BE12: □□□□□□□□□■■■■■■■■■■■ | BF12: 1 | BG12: Animals | BH12: Religion | BT12: Concealment | BY12: Prosetylisation | CF12: 3 | CG12: 2 | CH12: 4 | CI12: Lance | CJ12: ●●●● | CK12: Carthian | CL12: - | CM12: Crone | CN12: - | CO12: Invictus | CP12: - | CQ12: ● | CR12: ● | CS12: - | CT12: ●●● | CU12: - | CW12: - | CY12: 4 | CZ12: ˅ | DA12: ○ | DB12: ○ | DC12: ○ | DD12: ○ | DE12: ○ | DF12: ○ | DG12: ● | DH12: ● | DI12: ● | DJ12: ● | DK12: Flock ●●● | DL12: Stigmata ● | DM12: ¬ | DN12: ¬ | DO12: ¬ | DP12: ¬ | DQ12: ¬ | DR12: ¬ | DS12: ¬ | DT12: ¬ | DU12: ¬ | DV12: ¬ | DW12: ¬ | DX12: ¬ | DY12: ¬ | DZ12: ¬ | EA12: ¬ | EB12: ¬ | EC12: ¬ | ED12: ¬ | EE12: ¬ | EF12: ¬ | EG12: ¬ | EH12: ¬ | EI12: ¬ | EJ12: ¬ | EK12: ¬ | EL12: ¬ | EM12: ¬ | EN12: ¬ | EO12: Herd serves as Willpower source. Dots apply as additional Herd dots. | EP12: Bleed dots in Vitae weekly (or at will for Willpower). This Vitae inspires without addiction or bonding, bolstering Theban Sorcery and Willpower. | EQ12: ¬ | ER12: ¬ | ES12: ¬ | ET12: ¬ | EU12: ¬ | EV12: ¬ | EW12: ¬ | EX12: ¬ | EY12: ¬ | EZ12: ¬ | FA12: ¬ | FB12: ¬ | FC12: ¬ | FD12: ¬ | FE12: ¬ | FF12: ¬ | FG12: ¬ | FH12: ¬ | FI12: ¬ | FJ12: ¬ | FK12: ¬ | FL12: ¬ | FM12: ¬ | FN12: ¬ | FO12: ¬ | FP12: ¬ | FQ12: ¬ | FR12: ¬ | FS12: 5 / 6 | FT12: □□□□□■ | FU12: Retainer | FV12: ¬ | FW12: ¬ | FX12: ¬ | FY12: ¬ | FZ12: ¬ | GA12: ¬ | GB12: ¬ | GC12: ¬ | GD12: ¬ | GE12: ¬ | GF12: ¬ | GG12: ¬ | GH12: ¬ | GI12: ¬ | GJ12: ¬ | GK12: ¬ | GL12: ¬ | GM12: ¬ | GN12: ¬ | GO12: ghoul | GP12: ¬ | GQ12: ¬ | GR12: ¬ | GS12: ¬ | GT12: ¬ | GU12: ¬ | GV12: ¬ | GW12: ¬ | GX12: ¬ | GY12: ¬ | GZ12: ¬ | HA12: ¬ | HB12: ¬ | HC12: ¬ | HD12: ¬ | HE12: ¬ | HF12: ¬ | HG12: ¬ | HH12: ¬ | HI12: ● | IC12: - | ID12: - | IE12: - | IF12: - | IG12: - | IH12: ●● | II12: ●● | IJ12: - | IK12: - | IL12: - | IM12: - | IN12: ● | IO12: - | IP12: - | IQ12: ● | IR12: ● | IS12: ● | IT12: Nightmare ● | Dread Presence | IU12: Nightmare ●● | Face of the Beast | IV12: Obfuscate ● | Face in the Crowd | IW12: Obfuscate ●● | Touch of Shadow | IX12: Blood Sorcery | Divination ● | IY12: Blood Sorcery | Protection ● | IZ12: Blood Sorcery | Transmutation ● | JA12: ¬ | JB12: ¬ | JC12: ¬ | JD12: ¬ | JE12: ¬ | JF12: ¬ | JG12: ¬ | JH12: ¬ | JI12: ¬ | JJ12: ¬ | JK12: ¬ | JL12: ¬ | JM12: ¬ | JN12: ¬ | JO12: ¬ | JP12: ¬ | JQ12: ¬ | JR12: ¬ | JS12: ¬ | JT12: ¬ | JU12: ¬ | JV12: ¬ | JW12: ¬ | JX12: Cost: - • Pool: - • Instant • Scene | JY12: Cost: 1 V • Pool: 7 v Composure + BP • Contested • Instant | JZ12: Cost: - • Pool: - • Instant • Scene | KA12: Cost: 1 V • Pool: 7 • Instant • Scene | KB12: ¬ | KC12: ¬ | KD12: ¬ | KE12: ¬ | KF12: ¬ | KG12: ¬ | KH12: ¬ | KI12: ¬ | KJ12: ¬ | KK12: ¬ | KL12: ¬ | KM12: ¬ | KN12: ¬ | KO12: ¬ | KP12: ¬ | KQ12: ¬ | KR12: ¬ | KS12: ¬ | KT12: ¬ | KU12: ¬ | KV12: ¬ | KW12: ¬ | KX12: ¬ | KY12: ¬ | KZ12: ¬ | LA12: ¬ | LB12: Conjure brief illusions. Improve Intimidation. Prevent foes spending Willpower. | LC12: Impose Frightened Condition. Cause fleeing. | LD12: Blend into surroundings, visible but unnoticeable. Predatory aura fully on or off. Leaving combat: Wits + Composure - Obfuscate to notice; auto Clash of Wills vs Auspex. | LE12: Cast Face in the Crowd on object or person. Free and unlimited duration on carried/worn objects if not drawing attention. | LF12: Glimpse fragmented details about intended actions. Learn basic info about a target. | LG12: Subtract Potency from ritual rolls targeting subject. Heal bashing in vampires. Protect from the Kiss (add Potency to resistance). | LH12: Minor cosmetic changes to living subjects. Warp dead matter. Animate liquids. | LI12: ¬ | LJ12: ¬ | LK12: ¬ | LL12: ¬ | LM12: ¬ | LN12: ¬ | LO12: ¬ | LP12: ¬ | LQ12: ¬ | LR12: ¬ | LS12: ¬ | LT12: ¬ | LU12: ¬ | LV12: ¬ | LW12: ¬ | LX12: ¬ | LY12: ¬ | LZ12: ¬ | MA12: ¬ | MB12: ¬ | MC12: ¬ | MD12: ¬ | ME12: ¬ | MF12: Lonely Curse | MG12: ¬ | MH12: ¬ | MI12: ¬ | MJ12: ¬ | MK12: With mortals, Humanity counts –2; Presence/Manipulation failures become dramatic failures. Intimidation and Subterfuge unaffected. | ML12: ¬ | MN12: ¬ | MO12: ¬ | MP12: 5 | MQ12: 8 | MR12: 2 | MS12: Help someone by sharing your vision with them. | MT12: Put yourself at risk to show a group the power of your vision. | MU12: Cow someone into submission. | MV12: Commit a widespread hit against a rival's mortal connections. | MW12: ¬ | MX12: ¬ | MY12: ¬ | MZ12: late 50s
A13: tblCharDataEinar | B13: 46104 | C13: 1 | D13: 54 | E13: Nathan H | F13: Einar Solveig | G13: Techno Viking | H13: he/him | I13: Ventrue | J13: D:\Terra Mortis\Character Sheets\Sheet Elements\Ventrue icon.svg | K13: Rotgrafen | L13: Carthian Movement | M13: D:\Terra Mortis\Character Sheets\Sheet Elements\Carthian icon.svg | N13: Junkie | O13: Competitor | P13: ¬ | Q13: ●●● | R13: ●● | S13: ●●● | T13: ●●●○○ | U13: ●● | V13: ●●○ | W13: ●● | X13: ●● | Y13: ●●● | AB13: ● | AC13: ●●● | AH13: ● | AI13: ●●●●● | AM13: ● | AQ13: ● | AR13: ●●● | AS13: ●●● | AT13: ● | AV13: ●● | AW13: ● | AX13: ●●○○○○○○○○○○○○○○○○ | AY13: 2 | AZ13: † | BA13: □□□□□□□□■■■■■■■ | BB13: 6 / 6 | BC13: □□□□□□■■■■ | BD13: 11 / 11 | BE13: □□□□□□□□□□□■■■■■■■■■ | BF13: 2 | BG13: Animals | BJ13: Carpentry | BQ13: Claws (+2) | CA13: Direct Threats | CF13: 3 | CG13: 2 | CH13: 2 | CI13: Carthian | CJ13: ●● | CK13: Crone | CL13: - | CM13: Invictus | CN13: - | CO13: Lance | CP13: - | CQ13: ●● | CR13: ● | CS13: - | CT13: ● | CU13: - | CW13: - | CY13: 5 | CZ13: ~ | DA13: ○ | DB13: ○ | DC13: ○ | DD13: ○ ("Kyle") | DE13: ○ | DF13: ● | DG13: ● | DH13: ● | DI13: ● | DJ13: ● | DK13: Area of Expertise (Claws) ● | DL13: Claws of the Unholy ● | DM13: Defensive Combat (Brawl) ● | DN13: Indomitable ●● | DO13: Swarm Form ●● | DP13: Mobilise Outrage ● | Strike to Preempt | DQ13: Mobilise Outrage ●● | Unbreakable | DR13: Mobilise Outrage ●●● | Dying on Your Feet | DS13: Riding the Wave ● | Ravage | DT13: Riding the Wave ●● | Primal Strength | DU13: Riding the Wave ●●● | In the Zone | DV13: Riding the Wave ●●●● | Unyielding | DW13: ¬ | DX13: ¬ | DY13: ¬ | DZ13: ¬ | EA13: ¬ | EB13: ¬ | EC13: ¬ | ED13: ¬ | EE13: ¬ | EF13: ¬ | EG13: ¬ | EH13: ¬ | EI13: ¬ | EJ13: ¬ | EK13: ¬ | EL13: ¬ | EM13: ¬ | EN13: ¬ | EO13: Raise one Specialty's die bonus to +2. | EP13: Unnatural Aspect claws in frenzy become +2A. | EQ13: Substitute chosen Skill for Athletics in Defence, if equipped for that Skill. | ER13: +2 to contest or resist supernatural mental influence. | ES13: Beast's Skin can be a swarm (5 × Blood Potency yards). Attacks ignore Defence, deal lethal. Non-area attacks deal 1 damage max. | ET13: Sacrifice your Defence and your second turn to add your Willpower as bonus dice to attack on your first turn. | EU13: Add your full Willpower value when spending a point to contest or resist social or mental coercion in a combat situation. | EV13: During combat only, ignore wound penalties and do not fall to torpor from injury. | EW13: Bite attacks take a 1L weapon rating. | EX13: Double your Strength bonus from frenzy when lifting, jumping, or destroying objects. | EY13: When you spend Willpower to ride the wave, you also apply the normal +3 action bonus. | EZ13: After a scene where you rode the wave, recover any Willpower spent to do so. | FA13: ¬ | FB13: ¬ | FC13: ¬ | FD13: ¬ | FE13: ¬ | FF13: ¬ | FG13: ¬ | FH13: ¬ | FI13: ¬ | FJ13: ¬ | FK13: ¬ | FL13: ¬ | FM13: ¬ | FN13: ¬ | FO13: ¬ | FP13: ¬ | FQ13: ¬ | FR13: ¬ | FS13: 4 / 4 | FT13: □□□□ | FU13: ¬ | FV13: ¬ | FW13: ¬ | FX13: ¬ | FY13: ¬ | FZ13: ¬ | GA13: ¬ | GB13: ¬ | GC13: ¬ | GD13: ¬ | GE13: ¬ | GF13: ¬ | GG13: ¬ | GH13: ¬ | GI13: ¬ | GJ13: ¬ | GK13: ¬ | GL13: ¬ | GM13: ¬ | GN13: ¬ | GO13: ¬ | GP13: ¬ | GQ13: ¬ | GR13: ¬ | GS13: ¬ | GT13: ¬ | GU13: ¬ | GV13: ¬ | GW13: ¬ | GX13: ¬ | GY13: ¬ | GZ13: ¬ | HA13: ¬ | HB13: ¬ | HC13: ¬ | HD13: ¬ | HE13: ¬ | HF13: ¬ | HG13: ¬ | HH13: ¬ | IC13: - | ID13: - | IE13: - | IF13: ● | IG13: - | IH13: - | II13: - | IJ13: ●●●● | IK13: ● | IL13: ●● | IM13: - | IN13: - | IO13: - | IP13: - | IQ13: - | IR13: - | IS13: - | IT13: Dominate ● | Mesmerise | IU13: Protean ● | Unmarked Grave | IV13: Protean ●● | Predatory Aspect | IW13: Protean ●●● | Beast's Skin | IX13: Protean ●●●● | Unnatural Aspect | IY13: Resilience ● | IZ13: Vigour ●● | JA13: Devotion | Rime of Salt | JB13: ¬ | JC13: ¬ | JD13: ¬ | JE13: ¬ | JF13: ¬ | JG13: ¬ | JH13: ¬ | JI13: ¬ | JJ13: ¬ | JK13: ¬ | JL13: ¬ | JM13: ¬ | JN13: ¬ | JO13: ¬ | JP13: ¬ | JQ13: ¬ | JR13: ¬ | JS13: ¬ | JT13: ¬ | JU13: ¬ | JV13: ¬ | JW13: ¬ | JX13: Cost: - -3 in combat unless Blinded • Pool: 7 v Resolve + BP • Instant • Instant | JY13: Cost: Varies • Pool: - • Instant • Indefinite | JZ13: Cost: 1 V • Pool: - • Instant • Scene | KA13: Cost: 2 V • Pool: - • Instant • Indefinite | KB13: Cost: 1 V • Pool: - • None • Scene | KC13: Cost: 1 V per effect • Pool: - • Reflexive • 1 turn | KD13: Cost: 1 V per effect • Pool: - • Reflexive • 1 turn | KE13: Cost: Free (Ratgrafen Only) • Pool: - • Reflexive • Permanent | KF13: ¬ | KG13: ¬ | KH13: ¬ | KI13: ¬ | KJ13: ¬ | KK13: ¬ | KL13: ¬ | KM13: ¬ | KN13: ¬ | KO13: ¬ | KP13: ¬ | KQ13: ¬ | KR13: ¬ | KS13: ¬ | KT13: ¬ | KU13: ¬ | KV13: ¬ | KW13: ¬ | KX13: ¬ | KY13: ¬ | KZ13: ¬ | LA13: ¬ | LB13: Impose Mesmerised Condition. Control with short commands. | LC13: Merge with soil. | LD13: Take on animal traits. | LE13: Transform into predatory animal. | LF13: Take on a horrific trait. Barbed Hands damage is not lethal to vampires. | LG13: Downgrade damage and increase Stamina. Improve Armour and Defences. Unnatural Fortitude: add Resilience dots as bonus dice to non-combat Stamina pools. | LH13: Improve Strength. Add Vigour dots as bonus successes only if at least one net success achieved. | LI13: Protean weapons imbued with ocean salt. Wounded targets suffer -2 on their next action. | LJ13: ¬ | LK13: ¬ | LL13: ¬ | LM13: ¬ | LN13: ¬ | LO13: ¬ | LP13: ¬ | LQ13: ¬ | LR13: ¬ | LS13: ¬ | LT13: ¬ | LU13: ¬ | LV13: ¬ | LW13: ¬ | LX13: ¬ | LY13: ¬ | LZ13: ¬ | MA13: ¬ | MB13: ¬ | MC13: ¬ | MD13: ¬ | ME13: ¬ | MF13: Aloof Curse | MG13: ¬ | MH13: ¬ | MI13: ¬ | MJ13: ¬ | MK13: First Touchstone attaches to Humanity 7; losing it detaches on first Humanity loss. Breaking points always treated as one step lower. | ML13: ¬ | MN13: ¬ | MO13: ¬ | MP13: 5 | MQ13: 12 | MR13: 3 | MS13: Ignore a problem or responsibility in favour of immediate gratification. | MT13: Abandon an important relationship over your pursuit of pleasure. | MU13: Challenge someone clearly your superior. | MV13: Risk Final Death to prove you can handle something. | MW13: ¬ | MX13: ¬ | MY13: ¬ | MZ13: late 30s
A14: tblCharDataEve | B14: 46104 | C14: 2 | D14: 24 | E14: Jamie | F14: Eve Lockridge | G14: Benevolent Millionaire | H14: they/them | I14: Daeva | J14: D:\Terra Mortis\Character Sheets\Sheet Elements\Daeva icon.svg | K14: ¬ | L14: Carthian Movement | M14: D:\Terra Mortis\Character Sheets\Sheet Elements\Carthian icon.svg | N14: ¬ | O14: ¬ | P14: Premier | Q14: ●● | R14: ●●● | S14: ●● | T14: ● | U14: ●●● | V14: ●● | W14: ●●● | X14: ●●● | Y14: ●●● | AA14: ●● | AC14: ●● | AF14: ●●● | AH14: ●● | AK14: ●● | AQ14: ●●● | AR14: ●● | AT14: ●●● | AU14: ●●● | AX14: ●○○○○○○○○○○○○○○○○○○ | AY14: 1 | BA14: □□□□□□□■■■■■■■■ | BB14: 5 / 5 | BC14: □□□□□■■■■■ | BD14: 10 / 10 | BE14: □□□□□□□□□□■■■■■■■■■■ | BF14: 1 | BG14: Animals | CF14: 3 | CG14: 2 | CH14: 3 | CI14: Carthian | CJ14: ●●● | CK14: Crone | CL14: - | CM14: Invictus | CN14: - | CO14: Lance | CP14: - | CQ14: ● | CR14: - | CS14: - | CT14: ●●●●● | CU14: ●●●●● | CW14: - | CY14: 6 | CZ14: ~ | DA14: ○ | DB14: ○ | DC14: ○ | DD14: ○ | DE14: ● (Bill Manchester) | DF14: ● | DG14: ● | DH14: ● | DI14: ● | DJ14: ● | DK14: Carthian Pull ● | DL14: Fixer ●● | DM14: Fucking Thief (Secret Society Junkie) ● | DN14: Honey With Vinegar ● | DO14: Picket Line ●● | DP14: Secret Society Junkie ● | DQ14: ¬ | DR14: ¬ | DS14: ¬ | DT14: ¬ | DU14: ¬ | DV14: ¬ | DW14: ¬ | DX14: ¬ | DY14: ¬ | DZ14: ¬ | EA14: ¬ | EB14: ¬ | EC14: ¬ | ED14: ¬ | EE14: ¬ | EF14: ¬ | EG14: ¬ | EH14: ¬ | EI14: ¬ | EJ14: ¬ | EK14: ¬ | EL14: ¬ | EM14: ¬ | EN14: ¬ | EO14: Monthly, access Carthian Status in dots of Allies, Contacts, Haven or Herd. | EP14: Reduce all Availability costs by one. | EQ14: Steal flawed knowledge of a single one-dot advantage restricted to another covenant. | ER14: You earn influence from Allies, Contacts, and wide Mortal Status one step lower than normal. 1 point of influence at 2 dots or 4 dots respectively. | ES14: Each chapter, you have a pool of dots equal to their Contacts (max 5), which can be applied to Allies separately or as one amount, to raise their effective level when taking the Social Merit Blocking action. | ET14: Dots in Status or Mystery Cult Initiation representing human secret societies also count as dots of Herd. | EU14: ¬ | EV14: ¬ | EW14: ¬ | EX14: ¬ | EY14: ¬ | EZ14: ¬ | FA14: ¬ | FB14: ¬ | FC14: ¬ | FD14: ¬ | FE14: ¬ | FF14: ¬ | FG14: ¬ | FH14: ¬ | FI14: ¬ | FJ14: ¬ | FK14: ¬ | FL14: ¬ | FM14: ¬ | FN14: ¬ | FO14: ¬ | FP14: ¬ | FQ14: ¬ | FR14: ¬ | FS14: 7 / 11 | FT14: □□□□□□□■■■■ | FU14: Allies | FV14: Contacts | FW14: Resources | FX14: Status | FY14: ¬ | FZ14: ¬ | GA14: ¬ | GB14: ¬ | GC14: ¬ | GD14: ¬ | GE14: ¬ | GF14: ¬ | GG14: ¬ | GH14: ¬ | GI14: ¬ | GJ14: ¬ | GK14: ¬ | GL14: ¬ | GM14: ¬ | GN14: ¬ | GO14: Underworld | GP14: bureaucracy, industry | GQ14: ¬ | GR14: LGL - Logistics | GS14: ¬ | GT14: ¬ | GU14: ¬ | GV14: ¬ | GW14: ¬ | GX14: ¬ | GY14: ¬ | GZ14: ¬ | HA14: ¬ | HB14: ¬ | HC14: ¬ | HD14: ¬ | HE14: ¬ | HF14: ¬ | HG14: ¬ | HH14: ¬ | HI14: ●●● | HJ14: ●● | HK14: ●●●●● | HL14: ●●●●● | IC14: - | ID14: - | IE14: ● | IF14: ● | IG14: ●●● | IH14: - | II14: - | IJ14: - | IK14: - | IL14: - | IM14: - | IN14: - | IO14: - | IP14: - | IQ14: - | IR14: - | IS14: - | IT14: Celerity ● | IU14: Dominate ● | Mesmerise | IV14: Majesty ● | Awe | IW14: Majesty ●● | Confidant | IX14: Majesty ●●● | Green Eyes | IY14: ¬ | IZ14: ¬ | JA14: ¬ | JB14: ¬ | JC14: ¬ | JD14: ¬ | JE14: ¬ | JF14: ¬ | JG14: ¬ | JH14: ¬ | JI14: ¬ | JJ14: ¬ | JK14: ¬ | JL14: ¬ | JM14: ¬ | JN14: ¬ | JO14: ¬ | JP14: ¬ | JQ14: ¬ | JR14: ¬ | JS14: ¬ | JT14: ¬ | JU14: ¬ | JV14: ¬ | JW14: ¬ | JX14: Cost: 1 V per effect • Pool: - • Reflexive • 1 turn | JY14: Cost: - -3 in combat unless Blinded • Pool: 5 v Resolve + BP • Instant • Instant | JZ14: Cost: - • Pool: - • Instant • Scene | KA14: Cost: - (req: Awed) • Pool: 9 v Resolve + BP • Contested | KB14: Cost: 1 V (req: Charmed / Enthralled) • Pool: - • Instant • Scene | KC14: ¬ | KD14: ¬ | KE14: ¬ | KF14: ¬ | KG14: ¬ | KH14: ¬ | KI14: ¬ | KJ14: ¬ | KK14: ¬ | KL14: ¬ | KM14: ¬ | KN14: ¬ | KO14: ¬ | KP14: ¬ | KQ14: ¬ | KR14: ¬ | KS14: ¬ | KT14: ¬ | KU14: ¬ | KV14: ¬ | KW14: ¬ | KX14: ¬ | KY14: ¬ | KZ14: ¬ | LA14: ¬ | LB14: Persistent improved Defence or Dodge. Activate for supernatural speed benefits. Unnatural Grace: add Celerity dots as bonus dice to non-combat speed-based pools. | LC14: Impose Mesmerised Condition. Control with short commands. | LD14: Become centre of attention. Subjects become Awed. | LE14: Impose Charmed Condition. | LF14: Shift emotions (1 V, any number of Charmed/Enthralled targets); rage/fear causes frenzy with no resist roll (Ride the Wave normal). Requests: 1 V per target, must be spoken and heard. | LG14: ¬ | LH14: ¬ | LI14: ¬ | LJ14: ¬ | LK14: ¬ | LL14: ¬ | LM14: ¬ | LN14: ¬ | LO14: ¬ | LP14: ¬ | LQ14: ¬ | LR14: ¬ | LS14: ¬ | LT14: ¬ | LU14: ¬ | LV14: ¬ | LW14: ¬ | LX14: ¬ | LY14: ¬ | LZ14: ¬ | MA14: ¬ | MB14: ¬ | MC14: ¬ | MD14: ¬ | ME14: ¬ | MF14: Wanton Curse | MG14: ¬ | MH14: ¬ | MI14: ¬ | MJ14: ¬ | MK14: Hungry at 5 or fewer Vitae, Starving at 3 or fewer. Dramatic Failures on feeding cause Persistent Dependent Condition toward a mortal NPC. | ML14: ¬ | MN14: ¬ | MO14: ¬ | MP14: 5 | MQ14: 9 | MR14: 5 | MS14: ¬ | MT14: ¬ | MU14: ¬ | MV14: ¬ | MW14: ¬ | MX14: ¬ | MY14: ¬ | MZ14: mid 20s
A15: tblCharDataGel | B15: 46104 | C15: 0 | D15: 14 | E15: Stefan S | F15: Jelle 'Gel' Dunneweld | G15: Former Beat Cop | H15: he/him | I15: Daeva | J15: D:\Terra Mortis\Character Sheets\Sheet Elements\Daeva icon.svg | K15: ¬ | L15: Invictus | M15: D:\Terra Mortis\Character Sheets\Sheet Elements\Invictus icon.svg | N15: Follower | O15: Idealist | P15: ¬ | Q15: ●● | R15: ●●● | S15: ●● | T15: ●● | U15: ●● | V15: ●● | W15: ●● | X15: ●●● | Y15: ●●●● | AA15: ●● | AC15: ●●●●○† | AE15: ●●● | AG15: ●● | AH15: ● | AI15: ●●† | AO15: ● | AQ15: ●† | AS15: ● | AT15: ● | AW15: ● | AX15: ●○○○○○○○○○○○○○○○○○○ | AY15: 1 | BA15: □□□□□□□■■■■■■■■ | BB15: 6 / 6 | BC15: □□□□□□■■■■ | BD15: 10 / 10 | BE15: □□□□□□□□□□■■■■■■■■■■ | BF15: 1 | BG15: Animals | BK15: crime scene | BM15: mysteries | BQ15: street fighting | BY15: motives | CA15: command | CF15: 1 | CG15: 1 | CH15: 1 | CI15: Invictus | CJ15: ● | CK15: Carthian | CL15: - | CM15: Crone | CN15: - | CO15: Lance | CP15: - | CQ15: ●● | CR15: ●● | CS15: - | CT15: ●● | CU15: - | CW15: ●●●● | CX15: Police | CY15: 7 | CZ15: ~ | DA15: ○ | DB15: ○ | DC15: ○ | DD15: ● | DE15: ● | DF15: ● | DG15: ● | DH15: ● | DI15: ● | DJ15: ● | DK15: Police Tactics ● | Compliance Hold | DL15: Police Tactics ●● | Weapon Retention | DM15: ¬ | DN15: ¬ | DO15: ¬ | DP15: ¬ | DQ15: ¬ | DR15: ¬ | DS15: ¬ | DT15: ¬ | DU15: ¬ | DV15: ¬ | DW15: ¬ | DX15: ¬ | DY15: ¬ | DZ15: ¬ | EA15: ¬ | EB15: ¬ | EC15: ¬ | ED15: ¬ | EE15: ¬ | EF15: ¬ | EG15: ¬ | EH15: ¬ | EI15: ¬ | EJ15: ¬ | EK15: ¬ | EL15: ¬ | EM15: ¬ | EN15: ¬ | EO15: +2 bonus to all overpower rolls once Hold established. | EP15: Reduce successes to disarm or control your weapon by Weaponry (or Brawl for Brawling weapons). | EQ15: ¬ | ER15: ¬ | ES15: ¬ | ET15: ¬ | EU15: ¬ | EV15: ¬ | EW15: ¬ | EX15: ¬ | EY15: ¬ | EZ15: ¬ | FA15: ¬ | FB15: ¬ | FC15: ¬ | FD15: ¬ | FE15: ¬ | FF15: ¬ | FG15: ¬ | FH15: ¬ | FI15: ¬ | FJ15: ¬ | FK15: ¬ | FL15: ¬ | FM15: ¬ | FN15: ¬ | FO15: ¬ | FP15: ¬ | FQ15: ¬ | FR15: ¬ | FS15: 3 / 3 | FT15: □□□ | FU15: Allies | FV15: Allies | FW15: Contacts | FX15: ¬ | FY15: ¬ | FZ15: ¬ | GA15: ¬ | GB15: ¬ | GC15: ¬ | GD15: ¬ | GE15: ¬ | GF15: ¬ | GG15: ¬ | GH15: ¬ | GI15: ¬ | GJ15: ¬ | GK15: ¬ | GL15: ¬ | GM15: ¬ | GN15: ¬ | GO15: Police | GP15: Underworld | GQ15: Police, Street, Underworld | GR15: ¬ | GS15: ¬ | GT15: ¬ | GU15: ¬ | GV15: ¬ | GW15: ¬ | GX15: ¬ | GY15: ¬ | GZ15: ¬ | HA15: ¬ | HB15: ¬ | HC15: ¬ | HD15: ¬ | HE15: ¬ | HF15: ¬ | HG15: ¬ | HH15: ¬ | HI15: ●●● | HJ15: ● | HK15: ●● | IC15: - | ID15: - | IE15: ●● | IF15: - | IG15: ● | IH15: - | II15: - | IJ15: - | IK15: - | IL15: - | IM15: - | IN15: - | IO15: - | IP15: - | IQ15: - | IR15: - | IS15: - | IT15: Celerity ●● | IU15: Majesty ● | Awe | IV15: ¬ | IW15: ¬ | IX15: ¬ | IY15: ¬ | IZ15: ¬ | JA15: ¬ | JB15: ¬ | JC15: ¬ | JD15: ¬ | JE15: ¬ | JF15: ¬ | JG15: ¬ | JH15: ¬ | JI15: ¬ | JJ15: ¬ | JK15: ¬ | JL15: ¬ | JM15: ¬ | JN15: ¬ | JO15: ¬ | JP15: ¬ | JQ15: ¬ | JR15: ¬ | JS15: ¬ | JT15: ¬ | JU15: ¬ | JV15: ¬ | JW15: ¬ | JX15: Cost: 1 V per effect • Pool: - • Reflexive • 1 turn | JY15: Cost: - • Pool: - • Instant • Scene | JZ15: ¬ | KA15: ¬ | KB15: ¬ | KC15: ¬ | KD15: ¬ | KE15: ¬ | KF15: ¬ | KG15: ¬ | KH15: ¬ | KI15: ¬ | KJ15: ¬ | KK15: ¬ | KL15: ¬ | KM15: ¬ | KN15: ¬ | KO15: ¬ | KP15: ¬ | KQ15: ¬ | KR15: ¬ | KS15: ¬ | KT15: ¬ | KU15: ¬ | KV15: ¬ | KW15: ¬ | KX15: ¬ | KY15: ¬ | KZ15: ¬ | LA15: ¬ | LB15: Persistent improved Defence or Dodge. Activate for supernatural speed benefits. Unnatural Grace: add Celerity dots as bonus dice to non-combat speed-based pools. | LC15: Become centre of attention. Subjects become Awed. | LD15: ¬ | LE15: ¬ | LF15: ¬ | LG15: ¬ | LH15: ¬ | LI15: ¬ | LJ15: ¬ | LK15: ¬ | LL15: ¬ | LM15: ¬ | LN15: ¬ | LO15: ¬ | LP15: ¬ | LQ15: ¬ | LR15: ¬ | LS15: ¬ | LT15: ¬ | LU15: ¬ | LV15: ¬ | LW15: ¬ | LX15: ¬ | LY15: ¬ | LZ15: ¬ | MA15: ¬ | MB15: ¬ | MC15: ¬ | MD15: ¬ | ME15: ¬ | MF15: Wanton Curse | MG15: ¬ | MH15: ¬ | MI15: ¬ | MJ15: ¬ | MK15: Hungry at 5 or fewer Vitae, Starving at 3 or fewer. Dramatic Failures on feeding cause Persistent Dependent Condition toward a mortal NPC. | ML15: ¬ | MN15: ¬ | MO15: ¬ | MP15: 5 | MQ15: 9 | MR15: 3 | MS15: Follow a directive blindly, for the sake of following. | MT15: Follow a dangerous directive without hesitation. | MU15: Deny a compromise that would water down your ideal. | MV15: Refuse safety for fear of abandoning your ideal's purity. | MW15: ¬ | MX15: ¬ | MY15: ¬ | MZ15: mid 30s
A16: tblCharDataHazel | B16: 46104 | C16: 0 | D16: 28 | E16: Marni K | F16: Sister Hazel | G16: Dogmatic Nun Bruiser | H16: she/her | I16: Ventrue | J16: D:\Terra Mortis\Character Sheets\Sheet Elements\Ventrue icon.svg | K16: ¬ | L16: Lancea et Sanctum | M16: D:\Terra Mortis\Character Sheets\Sheet Elements\Lance icon.svg | N16: Penitent | O16: Authoritarian | P16: ¬ | Q16: ●●●● | R16: ●● | S16: ●●● | T16: ●●● | U16: ●● | V16: ●● | W16: ●● | X16: ● | Y16: ●●● | AC16: ●● | AE16: ●● | AM16: ●● | AO16: ●●●●● | AQ16: ● | AR16: ●●● | AT16: ● | AW16: ●●● | AX16: ●●○○○○○○○○○○○○○○○○ | AY16: 2 | AZ16: † | BA16: □□□□□□□■■■■■■■■ | BB16: 6 / 6 | BC16: □□□□□□■■■■ | BD16: 11 / 11 | BE16: □□□□□□□□□□□■■■■■■■■■ | BF16: 2 | BG16: Animals | BW16: Swords | CF16: 2 | CG16: 2 | CH16: 1 | CI16: Lance | CJ16: ● | CK16: Carthian | CL16: - | CM16: Crone | CN16: - | CO16: Invictus | CP16: - | CQ16: ●●●●● | CR16: ●●● | CS16: - | CT16: ●●●● | CU16: - | CW16: - | CY16: 4 | CZ16: ˅ | DA16: ○ | DB16: ○ | DC16: ○ | DD16: ○ (Unnamed laity member) | DE16: ○ | DF16: ○ | DG16: ● | DH16: ● | DI16: ● | DJ16: ● | DK16: Anointed ●● | DL16: Defensive Combat (Weaponry) ● | DM16: Flock ●● | DN16: Quick Draw (Swords) ● | DO16: Stigmata ● | DP16: Kindred Dueling ● | Hamstring | DQ16: Kindred Dueling ●● | Taunt | DR16: Kindred Dueling ●●● | Carving | DS16: Kindred Dueling ●●●● | Pincushion | DT16: Kindred Dueling ●●●●● | Spray | DU16: ¬ | DV16: ¬ | DW16: ¬ | DX16: ¬ | DY16: ¬ | DZ16: ¬ | EA16: ¬ | EB16: ¬ | EC16: ¬ | ED16: ¬ | EE16: ¬ | EF16: ¬ | EG16: ¬ | EH16: ¬ | EI16: ¬ | EJ16: ¬ | EK16: ¬ | EL16: ¬ | EM16: ¬ | EN16: ¬ | EO16: Once per session, roll Presence + Expression to preach the Raptured Condition. | EP16: Substitute chosen Skill for Athletics in Defence, if equipped for that Skill. | EQ16: Herd serves as Willpower source. Dots apply as additional Herd dots. | ER16: Draw a weapon from a chosen Specialty reflexively while Defence is available. Initiative bonuses only apply if using the weapon. | ES16: Bleed dots in Vitae weekly (or at will for Willpower). This Vitae inspires without addiction or bonding, bolstering Theban Sorcery and Willpower. | ET16: You can use a called shot to deny a vampire's limb the benefits of Physical Intensity. | EU16: Exchange up to your Weaponry in attack dice to provoke, on hit, a frenzy roll penalised by your exchanged dice. | EV16: Deal lethal damage to the Kindred body. | EW16: You can lodge your weapon into the victim on a hit, preventing the wound from healing with Vitae use. You can withdraw it reflexively, but others must roll Strength + Stamina - damage caused as an instant action. | EX16: Sacrifice your Defence to make an attack that can exchange points of damage inflicted for points of Vitae damaged. | EY16: ¬ | EZ16: ¬ | FA16: ¬ | FB16: ¬ | FC16: ¬ | FD16: ¬ | FE16: ¬ | FF16: ¬ | FG16: ¬ | FH16: ¬ | FI16: ¬ | FJ16: ¬ | FK16: ¬ | FL16: ¬ | FM16: ¬ | FN16: ¬ | FO16: ¬ | FP16: ¬ | FQ16: ¬ | FR16: ¬ | FS16: 3 / 4 | FT16: □□□■ | FU16: Allies | FV16: Retainer | FW16: ¬ | FX16: ¬ | FY16: ¬ | FZ16: ¬ | GA16: ¬ | GB16: ¬ | GC16: ¬ | GD16: ¬ | GE16: ¬ | GF16: ¬ | GG16: ¬ | GH16: ¬ | GI16: ¬ | GJ16: ¬ | GK16: ¬ | GL16: ¬ | GM16: ¬ | GN16: ¬ | GO16: Church | GP16: ¬ | GQ16: ¬ | GR16: ¬ | GS16: ¬ | GT16: ¬ | GU16: ¬ | GV16: ¬ | GW16: ¬ | GX16: ¬ | GY16: ¬ | GZ16: ¬ | HA16: ¬ | HB16: ¬ | HC16: ¬ | HD16: ¬ | HE16: ¬ | HF16: ¬ | HG16: ¬ | HH16: ¬ | HI16: ●●● | HJ16: ●● | IC16: - | ID16: - | IE16: ● | IF16: ●●● | IG16: - | IH16: - | II16: - | IJ16: - | IK16: - | IL16: - | IM16: - | IN16: - | IO16: - | IP16: - | IQ16: - | IR16: - | IS16: - | IT16: Celerity ● | IU16: Dominate ● | Mesmerise | IV16: Dominate ●● | Iron Edict | IW16: Dominate ●●● | Entombed Command | IX16: ¬ | IY16: ¬ | IZ16: ¬ | JA16: ¬ | JB16: ¬ | JC16: ¬ | JD16: ¬ | JE16: ¬ | JF16: ¬ | JG16: ¬ | JH16: ¬ | JI16: ¬ | JJ16: ¬ | JK16: ¬ | JL16: ¬ | JM16: ¬ | JN16: ¬ | JO16: ¬ | JP16: ¬ | JQ16: ¬ | JR16: ¬ | JS16: ¬ | JT16: ¬ | JU16: ¬ | JV16: ¬ | JW16: ¬ | JX16: Cost: 1 V per effect • Pool: - • Reflexive • 1 turn | JY16: Cost: - -3 in combat unless Blinded • Pool: 10 v Resolve + BP • Instant • Instant | JZ16: Cost: 1 V (0 in bond) (req: Mesmerised); -3 in combat unless Blinded • Pool: - • Instant • Instant | KA16: Cost: - (req: Mesmerised) • Pool: 10 - Resolve • Instant • 1 week/success (1 month bonded) | KB16: ¬ | KC16: ¬ | KD16: ¬ | KE16: ¬ | KF16: ¬ | KG16: ¬ | KH16: ¬ | KI16: ¬ | KJ16: ¬ | KK16: ¬ | KL16: ¬ | KM16: ¬ | KN16: ¬ | KO16: ¬ | KP16: ¬ | KQ16: ¬ | KR16: ¬ | KS16: ¬ | KT16: ¬ | KU16: ¬ | KV16: ¬ | KW16: ¬ | KX16: ¬ | KY16: ¬ | KZ16: ¬ | LA16: ¬ | LB16: Persistent improved Defence or Dodge. Activate for supernatural speed benefits. Unnatural Grace: add Celerity dots as bonus dice to non-combat speed-based pools. | LC16: Impose Mesmerised Condition. Control with short commands. | LD16: Impose Dominated Condition. Give long, detailed commands. | LE16: Establish triggers for other Dominate powers. | LF16: ¬ | LG16: ¬ | LH16: ¬ | LI16: ¬ | LJ16: ¬ | LK16: ¬ | LL16: ¬ | LM16: ¬ | LN16: ¬ | LO16: ¬ | LP16: ¬ | LQ16: ¬ | LR16: ¬ | LS16: ¬ | LT16: ¬ | LU16: ¬ | LV16: ¬ | LW16: ¬ | LX16: ¬ | LY16: ¬ | LZ16: ¬ | MA16: ¬ | MB16: ¬ | MC16: ¬ | MD16: ¬ | ME16: ¬ | MF16: Aloof Curse | MG16: ¬ | MH16: ¬ | MI16: ¬ | MJ16: ¬ | MK16: First Touchstone attaches to Humanity 7; losing it detaches on first Humanity loss. Breaking points always treated as one step lower. | ML16: ¬ | MN16: ¬ | MO16: ¬ | MP16: 5 | MQ16: 10 | MR16: 2 | MS16: Punish yourself for a mistake. | MT16: Risk death to correct an egregious error in judgement. | MU16: Cow someone into submission. | MV16: Commit a widespread hit against a rival's mortal connections. | MW16: ¬ | MX16: ¬ | MY16: ¬
A17: tblCharDataIvana | B17: 46104 | C17: 4 | D17: 54 | E17: Lyn | F17: Ivana Horvat | G17: Trauma Survivor | H17: she/her | I17: Gangrel | J17: D:\Terra Mortis\Character Sheets\Sheet Elements\Gangrel icon.svg | K17: Scions of the First City | L17: Circle of the Crone | M17: D:\Terra Mortis\Character Sheets\Sheet Elements\Crone icon.svg | N17: Child | O17: Competitor | P17: ¬ | Q17: ●●● | R17: ●●● | S17: ●● | T17: ●● | U17: ●●● | V17: ●● | W17: ● | X17: ●●●● | Y17: ●● | AC17: ● | AE17: ●●● | AH17: ●● | AK17: ●●● | AL17: ●● | AP17: ●●● | AQ17: ●●● | AS17: ●●● | AU17: ●● | AX17: ●○○○○○○○○○○○○○○○○○○ | AY17: 1 | BA17: □□□□□□□■■■■■■■■ | BB17: 4 / 4 | BC17: □□□□■■■■■■ | BD17: 10 / 10 | BE17: □□□□□□□□□□■■■■■■■■■■ | BF17: 1 | BG17: Animals | BS17: Crossbow | BU17: Hiding | BX17: Training | CF17: 1 | CG17: 1 | CH17: 1 | CI17: Crone | CJ17: ● | CK17: Carthian | CL17: - | CM17: Invictus | CN17: - | CO17: Lance | CP17: - | CQ17: ●●● | CR17: ●●● | CS17: - | CT17: - | CU17: ●●●● | CV17: The Ashen Path | CW17: - | CY17: 5 | CZ17: ~ | DA17: ○ | DB17: ○ | DC17: ○ | DD17: ○ | DE17: ○ (Lady Di) | DF17: ● | DG17: ● | DH17: ● | DI17: ● | DJ17: ● | DK17: Mandragora Garden (Shared (Keeper)) ●●● | DL17: Opening the Void ●● | DM17: The Mother-Daughter Bond ● | DN17: Falconry ● | Predator's Vigil | DO17: Falconry ●● | Flyby | DP17: K-9 ● | Detection | DQ17: K-9 ●● | Targeted Bite | DR17: K-9 ●●● | Tactical Positioning | DS17: Powered Projectile ● | Quick Reload | DT17: Powered Projectile ●● | Intercept Shot | DU17: Powered Projectile ●●● | Penetration | DV17: Powered Projectile ●●●● | Skewer | DW17: ¬ | DX17: ¬ | DY17: ¬ | DZ17: ¬ | EA17: ¬ | EB17: ¬ | EC17: ¬ | ED17: ¬ | EE17: ¬ | EF17: ¬ | EG17: ¬ | EH17: ¬ | EI17: ¬ | EJ17: ¬ | EK17: ¬ | EL17: ¬ | EM17: ¬ | EN17: ¬ | EO17: Remote Crúac into Safe Place. Add dots to Crúac rolls in garden. Sustain Merit dots in rituals indefinitely (don't count toward Sorcery Tolerance); reduce base cost of Merit dots in rituals by rating. Feed dots in Vitae monthly; produces double in animal blood (costume at game). Attacks provoke frenzy. Can share but not increase yields. | EP17: Crúac rites summon shadow-servants proportional to rite level. Spend Willpower to consign living beings to darkness (extended contested roll). | EQ17: When purchasing Mentor, gain additional dots in a chosen Crúac Style equal to Mentor. If Mentor exceeds Crúac, Style dots added as Crúac gained. | ER17: Your raptor's presence inflicts Shaken on animals its Size or smaller, and lesser predators flee. | ES17: Your bird contests Presence + Intimidation vs Resolve + Composure to inflict a -3 action penalty. | ET17: Under direction, your dog rolls Wits + Survival + K-9 dots (modified for Bonded) to track scent. | EU17: Command your dog to make called shots in combat, reducing the shot penalty by -2. | EV17: When you fight one opponent in tandem, choose roles each turn for you and your dog. One takes +1 Defence, the other +2 to attack. Ignore penalties for firing into melee around your dog. | EW17: Reload your weapon one turn quicker, down to a reflexive action. | EX17: When you Aim, you may make called shots against sailing projectiles to deflect their course. | EY17: Sacrifice Defence to make an attack with +2 armour piercing. | EZ17: Reduce called shot penalties by two dice. Resulting Tilts persist while projectile lodged; removing requires Strength + Stamina - remaining damage. Healed damage removes Tilt. | FA17: ¬ | FB17: ¬ | FC17: ¬ | FD17: ¬ | FE17: ¬ | FF17: ¬ | FG17: ¬ | FH17: ¬ | FI17: ¬ | FJ17: ¬ | FK17: ¬ | FL17: ¬ | FM17: ¬ | FN17: ¬ | FO17: ¬ | FP17: ¬ | FQ17: ¬ | FR17: ¬ | FS17: 2 / 2 | FT17: □□ | FU17: Mentor | FV17: Retainer | FW17: Retainer | FX17: ¬ | FY17: ¬ | FZ17: ¬ | GA17: ¬ | GB17: ¬ | GC17: ¬ | GD17: ¬ | GE17: ¬ | GF17: ¬ | GG17: ¬ | GH17: ¬ | GI17: ¬ | GJ17: ¬ | GK17: ¬ | GL17: ¬ | GM17: ¬ | GN17: ¬ | GO17: Baba Grozda | GP17: Void-Bird | GQ17: Void-Dog | GR17: ¬ | GS17: ¬ | GT17: ¬ | GU17: ¬ | GV17: ¬ | GW17: ¬ | GX17: ¬ | GY17: ¬ | GZ17: ¬ | HA17: ¬ | HB17: ¬ | HC17: ¬ | HD17: ¬ | HE17: ¬ | HF17: ¬ | HG17: ¬ | HH17: ¬ | HI17: ●● | HJ17: ● | HK17: ● | IC17: - | ID17: ●●●●● | IE17: - | IF17: - | IG17: - | IH17: - | II17: ●● | IJ17: - | IK17: - | IL17: - | IM17: ●● | IN17: - | IO17: ● | IP17: - | IQ17: ● | IR17: ●● | IS17: - | IT17: Auspex ● | Beast's Hackles | IU17: Auspex ●● | Uncanny Perception | IV17: Auspex ●●● | Spirit's Touch | IW17: Auspex ●●●● | Lay Open the Mind | IX17: Auspex ●●●●● | Twilight Projection | IY17: Obfuscate ● | Face in the Crowd | IZ17: Obfuscate ●● | Touch of Shadow | JA17: Devotion | City Attunement | JB17: Devotion | Incriminating Evidence | JC17: Devotion | Our Mother's Mind | JD17: Blood Sorcery | Creation ● | JE17: Blood Sorcery | Divination ● | JF17: Blood Sorcery | Protection ● | JG17: Blood Sorcery | Protection ●● | JH17: Cruac ●● | Blood Witness | JI17: Cruac ●● | Shed the Virulent Bowels | JJ17: ¬ | JK17: ¬ | JL17: ¬ | JM17: ¬ | JN17: ¬ | JO17: ¬ | JP17: ¬ | JQ17: ¬ | JR17: ¬ | JS17: ¬ | JT17: ¬ | JU17: ¬ | JV17: ¬ | JW17: ¬ | JX17: Cost: Free (1 V for Insight) • Pool: - - Composure & Closed Book • Instant • Scene | JY17: Cost: Free (1 V for Insight) Must perceive target • Pool: - • Instant • Scene | JZ17: Cost: Free (1 WP for clash / 1 V for Insight) • Pool: - v Resolve + Stealth + Obf • Reflexive • Immediate | KA17: Cost: 1 V • Pool: 10 v Resolve + BP • Instant • Scene | KB17: Cost: 2 V • Pool: 11 • Instant • Scene (while projected) | KC17: Cost: - • Pool: - • Instant • Scene | KD17: Cost: 1 V • Pool: 7 • Instant • Scene | KE17: Cost: 1 V (Scion of the First City Only); city must have 10,000+ inhabitants • Pool: - • Instant • 1 night | KF17: Cost: Free / 1 V (Scion of the First City Only); must have touched target that night; must be outdoors • Pool: 11 • Instant • Instant | KG17: Cost: 2 V (Scion of the First City Only); walk barefoot, Vitae on feet • Pool: 11 v Resolve + BP • Contested • Until found | KH17: ¬ | KI17: ¬ | KJ17: ¬ | KK17: ¬ | KL17: Cost: 1 V 2 Successes • Pool: 9 • Ritual • 1 day per extra Vitae | KM17: Cost: 1 V 2 Successes • Pool: 9 • Ritual • Scene | KN17: ¬ | KO17: ¬ | KP17: ¬ | KQ17: ¬ | KR17: ¬ | KS17: ¬ | KT17: ¬ | KU17: ¬ | KV17: ¬ | KW17: ¬ | KX17: ¬ | KY17: ¬ | KZ17: ¬ | LA17: ¬ | LB17: Add Auspex dots to any rolls to resist surprise. Access to Tier 1 Auspex Insight questions. | LC17: Persistent Acute Senses Merit, doubles actual merit. Access to Tier 2 Auspex Insight questions. | LD17: Passively scan for anyone under Obfuscate 1 or 3, can provoke a challenge. Access to Tier 3 Auspex Insight questions. | LE17: Telepathy and mind-reading. Invoke Conditions. | LF17: Project senses into Twilight. May use Auspex 1-3 once per scene; cannot spend blood for additional uses. | LG17: Blend into surroundings, visible but unnoticeable. Predatory aura fully on or off. Leaving combat: Wits + Composure - Obfuscate to notice; auto Clash of Wills vs Auspex. | LH17: Cast Face in the Crowd on object or person. Free and unlimited duration on carried/worn objects if not drawing attention. | LI17: Touch building or street to attune to city for the night. One city at a time. Must attune before using other Scion devotions. | LJ17: Focus on a previously touched person. City guides to evidence of wrongdoing; clues equal to successes. Leads to general location only, not specific doors. Clash of Wills vs Obfuscate. | LK17: Declare a target. City guides BP blocks per success toward target. Target's non-combat pools and Speed reduced by 1 per success. Must sacrifice access to a level of Contacts, Allies, Retainer, or Resources per success (returns after 1 week). | LL17: Summon liquids, dead organic matter, sensory phenomena. Bonus/penalty = Potency. | LM17: Glimpse fragmented details about intended actions. Learn basic info about a target. | LN17: Subtract Potency from ritual rolls targeting subject. Heal bashing in vampires. Protect from the Kiss (add Potency to resistance). | LO17: Grant armour. Ward environmental hazards. Resist frenzy. | LP17: Smear Vitae on an area. Remotely observe through the spilled blood for one day per extra Vitae spent. | LQ17: Use a lock of hair or sympathetic link to hang a curse over a living victim for a month. Trigger the curse to cause enough lethal damage to fill the victim's Health. | LR17: ¬ | LS17: ¬ | LT17: ¬ | LU17: ¬ | LV17: ¬ | LW17: ¬ | LX17: ¬ | LY17: ¬ | LZ17: ¬ | MA17: ¬ | MB17: ¬ | MC17: ¬ | MD17: ¬ | ME17: ¬ | MF17: Feral Curse | MG17: ¬ | MH17: ¬ | MI17: ¬ | MJ17: ¬ | MK17: Frenzy resistance dice pools capped by Humanity (doesn't affect Riding the Wave). | ML17: ¬ | MN17: ¬ | MO17: ¬ | MP17: 5 | MQ17: 10 | MR17: 5 | MS17: Find someone to take responsibility for your mistake. | MT17: Commit a terrible crime to see how authority might react. | MU17: Challenge someone clearly your superior. | MV17: Risk Final Death to prove you can handle something. | MW17: ¬ | MX17: ¬ | MY17: ¬
A18: tblCharDataJack | B18: 46104 | C18: 1 | D18: 40 | E18: George T | F18: Jack Fallow | G18: Failed Adult Film Director | H18: he/him | I18: Mekhet | J18: D:\Terra Mortis\Character Sheets\Sheet Elements\Mekhet icon.svg | K18: ¬ | L18: Circle of the Crone | M18: D:\Terra Mortis\Character Sheets\Sheet Elements\Crone icon.svg | N18: Spy | O18: Monster | P18: Regent | Q18: ●● | R18: ●●● | S18: ●●● | T18: ● | U18: ●● | V18: ●●● | W18: ●●● | X18: ●●● | Y18: ●● | AA18: ●●● | AB18: ●● | AC18: ● | AD18: ●● | AE18: ●●● | AH18: ● | AL18: ●● | AM18: ● | AQ18: ●● | AR18: ●● | AT18: ● | AU18: ● | AW18: ● | AX18: ●○○○○○○○○○○○○○○○○○○ | AY18: 1 | BA18: □□□□□□□□■■■■■■■ | BB18: 5 / 5 | BC18: □□□□□■■■■■ | BD18: 9 / 10 | BE18: □□□□□□□□□■■■■■■■■■■■ | BF18: 1 | BG18: Animals | BI18: Hacking | BK18: Surveillance | BL18: Backroom | CF18: 3 | CG18: 2 | CH18: 3 | CI18: Crone | CJ18: ●●● | CK18: Carthian | CL18: - | CM18: Invictus | CN18: - | CO18: Lance | CP18: - | CQ18: ● | CR18: - | CS18: - | CT18: ●●●●● | CU18: ●●●●● | CV18: The Moulding Room | CW18: - | CY18: 4 | CZ18: ˅ | DA18: ○ | DB18: ○ | DC18: ○ | DD18: ○ | DE18: ○ | DF18: ○ | DG18: ● | DH18: ● | DI18: ● | DJ18: ● | DK18: Eye for the Strange ●● | DL18: Indomitable ●● | DM18: Mandragora Garden ● | DN18: Secret Society Junkie ● | DO18: Trained Observer ● | DP18: Viral Mythology ●●● | DQ18: Cacophony Savvy ● | Gettin' Up | DR18: Cacophony Savvy ●● | Backpacker | DS18: ¬ | DT18: ¬ | DU18: ¬ | DV18: ¬ | DW18: ¬ | DX18: ¬ | DY18: ¬ | DZ18: ¬ | EA18: ¬ | EB18: ¬ | EC18: ¬ | ED18: ¬ | EE18: ¬ | EF18: ¬ | EG18: ¬ | EH18: ¬ | EI18: ¬ | EJ18: ¬ | EK18: ¬ | EL18: ¬ | EM18: ¬ | EN18: ¬ | EO18: Roll Intelligence + Composure to identify evidence of supernatural involvement. | EP18: +2 to contest or resist supernatural mental influence. | EQ18: Remote Crúac into Safe Place. Add dots to Crúac rolls in garden. Sustain Merit dots in rituals indefinitely (don't count toward Sorcery Tolerance); reduce base cost of Merit dots in rituals by rating. Feed dots in Vitae monthly; produces double in animal blood (costume at game). Attacks provoke frenzy. Can share but not increase yields. | ER18: Dots in Status or Mystery Cult Initiation representing human secret societies also count as dots of Herd. | ES18: Take 9-Again, or 8-Again with three dots, on Perception rolls. | ET18: Presence + Expression vs Wits + Composure to inflict contagious awe. Allies and Herd double their yield. | EU18: You can read the Cacophony with Intelligence + Streetwise. Within a vampire's Feeding Grounds, add their (not your) dots in that Merit as bonus dice. | EV18: You quickly learn who's who and where they hunt, even newcomers to the city. | EW18: ¬ | EX18: ¬ | EY18: ¬ | EZ18: ¬ | FA18: ¬ | FB18: ¬ | FC18: ¬ | FD18: ¬ | FE18: ¬ | FF18: ¬ | FG18: ¬ | FH18: ¬ | FI18: ¬ | FJ18: ¬ | FK18: ¬ | FL18: ¬ | FM18: ¬ | FN18: ¬ | FO18: ¬ | FP18: ¬ | FQ18: ¬ | FR18: ¬ | FS18: 10 / 10 | FT18: □□□□□□□□□□ | FU18: Allies | FV18: Allies | FW18: Allies | FX18: Allies | FY18: ¬ | FZ18: ¬ | GA18: ¬ | GB18: ¬ | GC18: ¬ | GD18: ¬ | GE18: ¬ | GF18: ¬ | GG18: ¬ | GH18: ¬ | GI18: ¬ | GJ18: ¬ | GK18: ¬ | GL18: ¬ | GM18: ¬ | GN18: ¬ | GO18: High Society | GP18: Media | GQ18: Occult | GR18: Police | GS18: ¬ | GT18: ¬ | GU18: ¬ | GV18: ¬ | GW18: ¬ | GX18: ¬ | GY18: ¬ | GZ18: ¬ | HA18: ¬ | HB18: ¬ | HC18: ¬ | HD18: ¬ | HE18: ¬ | HF18: ¬ | HG18: ¬ | HH18: ¬ | HI18: ●●● | HJ18: ●●● | HK18: ●●● | HL18: ●●● | IC18: - | ID18: ●●●● | IE18: ● | IF18: - | IG18: - | IH18: - | II18: ● | IJ18: - | IK18: - | IL18: - | IM18: ●● | IN18: - | IO18: ● | IP18: - | IQ18: ● | IR18: ● | IS18: ●● | IT18: Auspex ● | Beast's Hackles | IU18: Auspex ●● | Uncanny Perception | IV18: Auspex ●●● | Spirit's Touch | IW18: Auspex ●●●● | Lay Open the Mind | IX18: Celerity ● | IY18: Obfuscate ● | Face in the Crowd | IZ18: Blood Sorcery | Creation ● | JA18: Blood Sorcery | Divination ● | JB18: Blood Sorcery | Protection ● | JC18: Blood Sorcery | Transmutation ● | JD18: Blood Sorcery | Transmutation ●● | JE18: Cruac ● | Mantle of Amorous Fire | JF18: ¬ | JG18: ¬ | JH18: ¬ | JI18: ¬ | JJ18: ¬ | JK18: ¬ | JL18: ¬ | JM18: ¬ | JN18: ¬ | JO18: ¬ | JP18: ¬ | JQ18: ¬ | JR18: ¬ | JS18: ¬ | JT18: ¬ | JU18: ¬ | JV18: ¬ | JW18: ¬ | JX18: Cost: Free (1 V for Insight) • Pool: - - Composure & Closed Book • Instant • Scene | JY18: Cost: Free (1 V for Insight) Must perceive target • Pool: - • Instant • Scene | JZ18: Cost: Free (1 WP for clash / 1 V for Insight) • Pool: - v Resolve + Stealth + Obf • Reflexive • Immediate | KA18: Cost: 1 V • Pool: 7 v Resolve + BP • Instant • Scene | KB18: Cost: 1 V per effect • Pool: - • Reflexive • 1 turn | KC18: Cost: - • Pool: - • Instant • Scene | KD18: ¬ | KE18: ¬ | KF18: ¬ | KG18: ¬ | KH18: ¬ | KI18: Cost: 1 V 1 Successes • Pool: 8 • Ritual • Scene | KJ18: ¬ | KK18: ¬ | KL18: ¬ | KM18: ¬ | KN18: ¬ | KO18: ¬ | KP18: ¬ | KQ18: ¬ | KR18: ¬ | KS18: ¬ | KT18: ¬ | KU18: ¬ | KV18: ¬ | KW18: ¬ | KX18: ¬ | KY18: ¬ | KZ18: ¬ | LA18: ¬ | LB18: Add Auspex dots to any rolls to resist surprise. Access to Tier 1 Auspex Insight questions. | LC18: Persistent Acute Senses Merit, doubles actual merit. Access to Tier 2 Auspex Insight questions. | LD18: Passively scan for anyone under Obfuscate 1 or 3, can provoke a challenge. Access to Tier 3 Auspex Insight questions. | LE18: Telepathy and mind-reading. Invoke Conditions. | LF18: Persistent improved Defence or Dodge. Activate for supernatural speed benefits. Unnatural Grace: add Celerity dots as bonus dice to non-combat speed-based pools. | LG18: Blend into surroundings, visible but unnoticeable. Predatory aura fully on or off. Leaving combat: Wits + Composure - Obfuscate to notice; auto Clash of Wills vs Auspex. | LH18: Summon liquids, dead organic matter, sensory phenomena. Bonus/penalty = Potency. | LI18: Glimpse fragmented details about intended actions. Learn basic info about a target. | LJ18: Subtract Potency from ritual rolls targeting subject. Heal bashing in vampires. Protect from the Kiss (add Potency to resistance). | LK18: Minor cosmetic changes to living subjects. Warp dead matter. Animate liquids. | LL18: Disguise living/vampiric subjects. Transform dead matter completely. Animate gases and plants. Alter speech. Grant 9-again or WP/Vitae above maximum. | LM18: Dance to exhaustion. Add Cruac as a Presence bonus for the night. | LN18: ¬ | LO18: ¬ | LP18: ¬ | LQ18: ¬ | LR18: ¬ | LS18: ¬ | LT18: ¬ | LU18: ¬ | LV18: ¬ | LW18: ¬ | LX18: ¬ | LY18: ¬ | LZ18: ¬ | MA18: ¬ | MB18: ¬ | MC18: ¬ | MD18: ¬ | ME18: ¬ | MF18: Tenebrous Curse | MG18: ¬ | MH18: Plague of Purity | MI18: ¬ | MJ18: ¬ | MK18: Gain an extra bane at Humanity 6 (doesn't count towards cap); Humanity counts –1 for all Humanity-based banes. | ML18: ¬ | MM18: Touch by Integrity 8+ mortal causes (10 – Humanity) bashing damage. | MN18: ¬ | MO18: ¬ | MP18: 5 | MQ18: 8 | MR18: 3 | MS18: Build a new identity or uncover a secret. | MT18: Uncover a damning secret that could end someone. | MU18: Cause pain for the sole intention of causing pain. | MV18: Commit a capital crime without additional motive. | MW18: Build blackmail material dossier on Kindred | MX18: Establish Crone Praxis / Film Kindred | MY18: Dilute adherance to the Traditions / Subvert Moulding Room | MZ18: Mid 40's
A19: tblCharDataKeeper | B19: 46104 | C19: 1 | D19: 62 | E19: Symon | F19: Keeper | G19: Fallen Elder | H19: he/she/they | I19: Mekhet | J19: D:\Terra Mortis\Character Sheets\Sheet Elements\Mekhet icon.svg | K19: Mnemosyne | L19: Circle of the Crone | M19: D:\Terra Mortis\Character Sheets\Sheet Elements\Crone icon.svg | N19: Junkie | O19: Masochist | P19: ¬ | Q19: ●●●● | R19: ●● | S19: ●● | T19: ●● | U19: ●● | V19: ●● | W19: ●●● | X19: ●●● | Y19: ●● | AE19: ●●●● | AH19: ●●●●● | AM19: ●● | AQ19: ●●● | AR19: ●●●● | AS19: ● | AU19: ● | AW19: ●● | AX19: ●●○○○○○○○○○○○○○○○○ | AY19: 2 | AZ19: † | BA19: □□□□□□□■■■■■■■■ | BB19: 4 / 4 | BC19: □□□□■■■■■■ | BD19: 4 / 11 | BE19: □□□□■■■■■■■■■■■■■■■■ | BF19: 2 | BG19: Animals | BP19: Archery | BY19: Sin-Eater | BZ19: Mesmerise | CF19: 1 | CG19: 3 | CH19: 3 | CI19: Crone | CJ19: ●●● | CK19: Carthian | CL19: - | CM19: Invictus | CN19: ● | CO19: Lance | CP19: - | CQ19: ●●● | CR19: ●● | CS19: - | CT19: ●●●●● | CU19: ●●●●● | CV19: The Remembrance of the Lidles Eye | CW19: - | CY19: 3 | CZ19: ˅ | DA19: ○ | DB19: ○ | DC19: ○ | DD19: ○ | DE19: ○ (Odeliese (Dead Wife)) | DF19: ○ | DG19: ○ | DH19: ● | DI19: ● | DJ19: ● | DK19: Closed Book ●●● | DL19: Eidetic Memory ● | DM19: Empath ●● | DN19: Indomitable ●● | DO19: Mandragora Garden (Shared (Ivana)) ●●● | DP19: Peacemaker ●●● | DQ19: Secret Society Junkie ● | DR19: Table Turner ● | DS19: ¬ | DT19: ¬ | DU19: ¬ | DV19: ¬ | DW19: ¬ | DX19: ¬ | DY19: ¬ | DZ19: ¬ | EA19: ¬ | EB19: ¬ | EC19: ¬ | ED19: ¬ | EE19: ¬ | EF19: ¬ | EG19: ¬ | EH19: ¬ | EI19: ¬ | EJ19: ¬ | EK19: ¬ | EL19: ¬ | EM19: ¬ | EN19: ¬ | EO19: Add dots to Doors and as bonus to contest Social assessments. | EP19: No rolls for recall. +2 to recall minute facts. | EQ19: Wits + Empathy vs Manipulation + Subterfuge for mental state insight; can open Doors or ease breaking points. | ER19: +2 to contest or resist supernatural mental influence. | ES19: Remote Crúac into Safe Place. Add dots to Crúac rolls in garden. Sustain Merit dots in rituals indefinitely (don't count toward Sorcery Tolerance); reduce base cost of Merit dots in rituals by rating. Feed dots in Vitae monthly; produces double in animal blood (costume at game). Attacks provoke frenzy. Can share but not increase yields. | ET19: Spend Willpower to negotiate peace via Social Manoeuvring. (•••) can talk down supernatural rages. | EU19: Dots in Status or Mystery Cult Initiation representing human secret societies also count as dots of Herd. | EV19: Spend Willpower to preempt Social Manoeuvring with your own Social action. | EW19: ¬ | EX19: ¬ | EY19: ¬ | EZ19: ¬ | FA19: ¬ | FB19: ¬ | FC19: ¬ | FD19: ¬ | FE19: ¬ | FF19: ¬ | FG19: ¬ | FH19: ¬ | FI19: ¬ | FJ19: ¬ | FK19: ¬ | FL19: ¬ | FM19: ¬ | FN19: ¬ | FO19: ¬ | FP19: ¬ | FQ19: ¬ | FR19: ¬ | FS19: 10 / 10 | FT19: □□□□□□□□□□ | FU19: Resources | FV19: ¬ | FW19: ¬ | FX19: ¬ | FY19: ¬ | FZ19: ¬ | GA19: ¬ | GB19: ¬ | GC19: ¬ | GD19: ¬ | GE19: ¬ | GF19: ¬ | GG19: ¬ | GH19: ¬ | GI19: ¬ | GJ19: ¬ | GK19: ¬ | GL19: ¬ | GM19: ¬ | GN19: ¬ | GO19: ¬ | GP19: ¬ | GQ19: ¬ | GR19: ¬ | GS19: ¬ | GT19: ¬ | GU19: ¬ | GV19: ¬ | GW19: ¬ | GX19: ¬ | GY19: ¬ | GZ19: ¬ | HA19: ¬ | HB19: ¬ | HC19: ¬ | HD19: ¬ | HE19: ¬ | HF19: ¬ | HG19: ¬ | HH19: ¬ | HI19: ●●●●● | IC19: - | ID19: ● | IE19: ● | IF19: ●●●● | IG19: - | IH19: - | II19: ● | IJ19: - | IK19: - | IL19: - | IM19: ●●●● | IN19: - | IO19: ● | IP19: - | IQ19: - | IR19: ● | IS19: ●●●● | IT19: Auspex ● | Beast's Hackles | IU19: Celerity ● | IV19: Dominate ● | Mesmerise | IW19: Dominate ●● | Iron Edict | IX19: Dominate ●●● | Entombed Command | IY19: Dominate ●●●● | The Lying Mind | IZ19: Obfuscate ● | Face in the Crowd | JA19: Devotion | The Taste of Things Lived | JB19: Devotion | The Exchange of Things Past | JC19: Blood Sorcery | Creation ● | JD19: Blood Sorcery | Protection ● | JE19: Blood Sorcery | Transmutation ● | JF19: Blood Sorcery | Transmutation ●● | JG19: Blood Sorcery | Transmutation ●●● | JH19: Blood Sorcery | Transmutation ●●●● | JI19: Cruac ● | Mantle of Amorous Fire | JJ19: Cruac ●● | Wisdom of the Soul | JK19: Cruac ● | Deflection of Wooden Doom | JL19: Cruac ●●●● | Willful Vitae | JM19: Oath of the Safe Word ●● | JN19: ¬ | JO19: ¬ | JP19: ¬ | JQ19: ¬ | JR19: ¬ | JS19: ¬ | JT19: ¬ | JU19: ¬ | JV19: ¬ | JW19: ¬ | JX19: Cost: Free (1 V for Insight) • Pool: - - Composure & Closed Book • Instant • Scene | JY19: Cost: 1 V per effect • Pool: - • Reflexive • 1 turn | JZ19: Cost: - -3 in combat unless Blinded • Pool: 12 v Resolve + BP • Instant • Instant | KA19: Cost: 1 V (0 in bond) (req: Mesmerised); -3 in combat unless Blinded • Pool: - • Instant • Instant | KB19: Cost: - (req: Mesmerised) • Pool: 10 - Resolve • Instant • 1 week/success (1 month bonded) | KC19: Cost: 2 V (req: Mesmerised) • Pool: - • Instant • Permanent | KD19: Cost: - • Pool: - • Instant • Scene | KE19: Cost: 1 V (reflexive for insight) (Mnemosyne Only) • Pool: 7 • Reflexive • Scene | KF19: Cost: 1 V (Mnemosyne Only); blood tie to target; replaces The Lying Mind • Pool: 12 v Resolve + BP • Contested • Scene / Permanent (elective) | KG19: ¬ | KH19: ¬ | KI19: ¬ | KJ19: ¬ | KK19: ¬ | KL19: ¬ | KM19: Cost: 1 V 1 Successes • Pool: 11 • Ritual • Scene | KN19: Cost: 1 V 2 Successes • Pool: 11 • Ritual • Instant | KO19: Cost: 1 V 1 Successes • Pool: 11 • Ritual • Scene | KP19: Cost: 2 V 4 Successes • Pool: 11 • Ritual • Until used | KQ19: ¬ | KR19: ¬ | KS19: ¬ | KT19: ¬ | KU19: ¬ | KV19: ¬ | KW19: ¬ | KX19: ¬ | KY19: ¬ | KZ19: ¬ | LA19: ¬ | LB19: Add Auspex dots to any rolls to resist surprise. Access to Tier 1 Auspex Insight questions. | LC19: Persistent improved Defence or Dodge. Activate for supernatural speed benefits. Unnatural Grace: add Celerity dots as bonus dice to non-combat speed-based pools. | LD19: Impose Mesmerised Condition. Control with short commands. | LE19: Impose Dominated Condition. Give long, detailed commands. | LF19: Establish triggers for other Dominate powers. | LG19: Impose Amnesia or False Memories Condition. | LH19: Blend into surroundings, visible but unnoticeable. Predatory aura fully on or off. Leaving combat: Wits + Composure - Obfuscate to notice; auto Clash of Wills vs Auspex. | LI19: Feeding creates artificial blood ties (+2 Social vs target; Twice Removed for Blood Sympathy). Sever for 1 WP. Can effect blood ties with Touch of Shadow. Spend 1 V: +1 Mental per applicable human/vampire within 100 metres. | LJ19: Exchange memories with target. For each memory taken, must give one of equal length. Both gain False Memories condition. After scene, own memories return but exchanged memories remain, or elect to make permanent. Traumatic memories: vampire rolls Fear Frenzy, mortal Resolve + Composure or Shaken. | LK19: Summon liquids, dead organic matter, sensory phenomena. Bonus/penalty = Potency. | LL19: Subtract Potency from ritual rolls targeting subject. Heal bashing in vampires. Protect from the Kiss (add Potency to resistance). | LM19: Minor cosmetic changes to living subjects. Warp dead matter. Animate liquids. | LN19: Disguise living/vampiric subjects. Transform dead matter completely. Animate gases and plants. Alter speech. Grant 9-again or WP/Vitae above maximum. | LO19: Grant physical properties of other creatures to living/vampiric subjects. Change inorganic appearances. Animate animals. Bless/curse actions (Potency modifier). | LP19: Transform one living thing into another. Animate the dead (zombies). Force physical actions on sentient subjects. Grant material properties between objects. Neutralise blood. | LQ19: Dance to exhaustion. Add Cruac as a Presence bonus for the night. | LR19: Reveal if mortal/vampire/ghoul; Humanity rating; diablerie | LS19: Caster becomes immune to staking for one night. | LT19: Prevent the onset of blood addiction or the Vinculum for the night. | LU19: Share Willpower and one Social Merit with oath partner. Either can end to briefly paralyse the other. | LV19: ¬ | LW19: ¬ | LX19: ¬ | LY19: ¬ | LZ19: ¬ | MA19: ¬ | MB19: ¬ | MC19: ¬ | MD19: ¬ | ME19: ¬ | MF19: Tenebrous Curse | MG19: ¬ | MH19: Hated by Beasts | MI19: ¬ | MJ19: ¬ | MK19: Gain an extra bane at Humanity 6 (doesn't count towards cap); Humanity counts –1 for all Humanity-based banes. | ML19: ¬ | MM19: Animals react violently; Animal Ken/Animalism suffer (10 – Humanity) penalty. | MN19: ¬ | MO19: ¬ | MP19: 5 | MQ19: 9 | MR19: 7 | MS19: Ignore a problem or responsibility in favour of immediate gratification. | MT19: Abandon an important relationship over your pursuit of pleasure. | MU19: Find and experience a new source of hurt. | MV19: Willingly explore pain beyond the point of safety and reason. | MW19: Proliferate Blood-Ties | MX19: Collect Memories | MY19: Become desiered in society again | MZ19: Late 40s | NA19: Inhumanly high presence
A20: tblCharDataKirk | B20: 46104 | C20: 10 | D20: 53 | E20: Phillip G | F20: Kirk Grimm | G20: Church Grim | H20: he/him | I20: Gangrel | J20: D:\Terra Mortis\Character Sheets\Sheet Elements\Gangrel icon.svg | K20: ¬ | L20: Lancea et Sanctum | M20: D:\Terra Mortis\Character Sheets\Sheet Elements\Lance icon.svg | N20: Idealist | O20: Penitent | P20: ¬ | Q20: ●● | R20: ●● | S20: ●●● | T20: ●●● | U20: ●● | V20: ●●●●○○ | W20: ●●● | X20: ● | Y20: ●●● | AA20: ● | AB20: ● | AD20: ● | AE20: ●● | AF20: ● | AH20: ● | AI20: ●● | AK20: ● | AM20: ● | AN20: ● | AO20: ●●●●● | AP20: ●● | AQ20: ● | AS20: ●● | AV20: ● | AW20: ● | AX20: ●●○○○○○○○○○○○○○○○○ | AY20: 2 | AZ20: † | BA20: □□□□□□□□□□□■■■■ | BB20: 6 / 6 | BC20: □□□□□□■■■■ | BD20: 11 / 11 | BE20: □□□□□□□□□□□■■■■■■■■■ | BF20: 2 | BG20: Animals | BJ20: carpentry | BX20: canine | CD20: gangs | CF20: 1 | CG20: 3 | CH20: 2 | CI20: Lance | CJ20: ●● | CK20: Carthian | CL20: - | CM20: Crone | CN20: - | CO20: Invictus | CP20: - | CQ20: ● | CR20: - | CS20: - | CT20: ●● | CU20: - | CW20: - | CY20: 6 | CZ20: ~ | DA20: ○ | DB20: ○ | DC20: ○ | DD20: ○ | DE20: ● (Unnamed Dockworker) | DF20: ● (Bastard sword (object)) | DG20: ● (Star of David pendant (object)) | DH20: ● | DI20: ● | DJ20: ● | DK20: Sorcerous Eunuch ● | DL20: Crusade ● | Shield Against Sorcery | DM20: Crusade ●● | Silence | DN20: Kindred Dueling ● | Hamstring | DO20: Kindred Dueling ●● | Taunt | DP20: ¬ | DQ20: ¬ | DR20: ¬ | DS20: ¬ | DT20: ¬ | DU20: ¬ | DV20: ¬ | DW20: ¬ | DX20: ¬ | DY20: ¬ | DZ20: ¬ | EA20: ¬ | EB20: ¬ | EC20: ¬ | ED20: ¬ | EE20: ¬ | EF20: ¬ | EG20: ¬ | EH20: ¬ | EI20: ¬ | EJ20: ¬ | EK20: ¬ | EL20: ¬ | EM20: ¬ | EN20: ¬ | EO20: Penalise sorcery against you by Resolve. Can't learn blood sorcery. | EP20: While your Defence is fully available, penalise the use of sorcery around you by your Crusade dots. | EQ20: Make called shots to the throat at no penalty to mute someone. | ER20: You can use a called shot to deny a vampire's limb the benefits of Physical Intensity. | ES20: Exchange up to your Weaponry in attack dice to provoke, on hit, a frenzy roll penalised by your exchanged dice. | ET20: ¬ | EU20: ¬ | EV20: ¬ | EW20: ¬ | EX20: ¬ | EY20: ¬ | EZ20: ¬ | FA20: ¬ | FB20: ¬ | FC20: ¬ | FD20: ¬ | FE20: ¬ | FF20: ¬ | FG20: ¬ | FH20: ¬ | FI20: ¬ | FJ20: ¬ | FK20: ¬ | FL20: ¬ | FM20: ¬ | FN20: ¬ | FO20: ¬ | FP20: ¬ | FQ20: ¬ | FR20: ¬ | FS20: 0 / 5 | FT20: ■■■■■ | FU20: ¬ | FV20: ¬ | FW20: ¬ | FX20: ¬ | FY20: ¬ | FZ20: ¬ | GA20: ¬ | GB20: ¬ | GC20: ¬ | GD20: ¬ | GE20: ¬ | GF20: ¬ | GG20: ¬ | GH20: ¬ | GI20: ¬ | GJ20: ¬ | GK20: ¬ | GL20: ¬ | GM20: ¬ | GN20: ¬ | GO20: ¬ | GP20: ¬ | GQ20: ¬ | GR20: ¬ | GS20: ¬ | GT20: ¬ | GU20: ¬ | GV20: ¬ | GW20: ¬ | GX20: ¬ | GY20: ¬ | GZ20: ¬ | HA20: ¬ | HB20: ¬ | HC20: ¬ | HD20: ¬ | HE20: ¬ | HF20: ¬ | HG20: ¬ | HH20: ¬ | IC20: ● | ID20: - | IE20: - | IF20: - | IG20: - | IH20: - | II20: - | IJ20: ● | IK20: ●● | IL20: - | IM20: - | IN20: - | IO20: - | IP20: - | IQ20: - | IR20: - | IS20: - | IT20: Animalism ● | Feral Whispers | IU20: Protean ● | Unmarked Grave | IV20: Resilience ●● | IW20: ¬ | IX20: ¬ | IY20: ¬ | IZ20: ¬ | JA20: ¬ | JB20: ¬ | JC20: ¬ | JD20: ¬ | JE20: ¬ | JF20: ¬ | JG20: ¬ | JH20: ¬ | JI20: ¬ | JJ20: ¬ | JK20: ¬ | JL20: ¬ | JM20: ¬ | JN20: ¬ | JO20: ¬ | JP20: ¬ | JQ20: ¬ | JR20: ¬ | JS20: ¬ | JT20: ¬ | JU20: ¬ | JV20: ¬ | JW20: ¬ | JX20: Cost: - • Pool: 4 • Instant • Scene (may persist) | JY20: Cost: Varies • Pool: - • Instant • Indefinite | JZ20: Cost: 1 V per effect • Pool: - • Reflexive • 1 turn | KA20: ¬ | KB20: ¬ | KC20: ¬ | KD20: ¬ | KE20: ¬ | KF20: ¬ | KG20: ¬ | KH20: ¬ | KI20: ¬ | KJ20: ¬ | KK20: ¬ | KL20: ¬ | KM20: ¬ | KN20: ¬ | KO20: ¬ | KP20: ¬ | KQ20: ¬ | KR20: ¬ | KS20: ¬ | KT20: ¬ | KU20: ¬ | KV20: ¬ | KW20: ¬ | KX20: ¬ | KY20: ¬ | KZ20: ¬ | LA20: ¬ | LB20: Speak with and command animals. | LC20: Merge with soil. | LD20: Downgrade damage and increase Stamina. Improve Armour and Defences. Unnatural Fortitude: add Resilience dots as bonus dice to non-combat Stamina pools. | LE20: ¬ | LF20: ¬ | LG20: ¬ | LH20: ¬ | LI20: ¬ | LJ20: ¬ | LK20: ¬ | LL20: ¬ | LM20: ¬ | LN20: ¬ | LO20: ¬ | LP20: ¬ | LQ20: ¬ | LR20: ¬ | LS20: ¬ | LT20: ¬ | LU20: ¬ | LV20: ¬ | LW20: ¬ | LX20: ¬ | LY20: ¬ | LZ20: ¬ | MA20: ¬ | MB20: ¬ | MC20: ¬ | MD20: ¬ | ME20: ¬ | MF20: Feral Curse | MG20: ¬ | MH20: ¬ | MI20: ¬ | MJ20: ¬ | MK20: Frenzy resistance dice pools capped by Humanity (doesn't affect Riding the Wave). | ML20: ¬ | MN20: ¬ | MO20: ¬ | MP20: 5 | MQ20: 10 | MR20: 3 | MS20: Deny a compromise that would water down your ideal. | MT20: Refuse safety for fear of abandoning your ideal's purity. | MU20: Punish yourself for a mistake. | MV20: Risk death to correct an egregious error in judgement. | MW20: ¬ | MX20: ¬ | MY20: ¬
A21: tblCharDataLivia | B21: 46104 | C21: 3 | D21: 20 | E21: Clair H | F21: Livia | G21: Health Guru | H21: she/her | I21: Daeva | J21: D:\Terra Mortis\Character Sheets\Sheet Elements\Daeva icon.svg | K21: ¬ | L21: Lancea et Sanctum | M21: D:\Terra Mortis\Character Sheets\Sheet Elements\Lance icon.svg | N21: Guru | O21: Scholar | P21: ¬ | Q21: ●●● | R21: ●● | S21: ●●● | T21: ●● | U21: ●● | V21: ●● | W21: ●●● | X21: ●●● | Y21: ●● | Z21: ●●●● | AC21: ● | AD21: ●● | AE21: ●● | AG21: ●● | AH21: ●●● | AM21: ● | AQ21: ●● | AT21: ●●● | AW21: ●● | AX21: ●○○○○○○○○○○○○○○○○○○ | AY21: 1 | BA21: □□□□□□□■■■■■■■■ | BB21: 5 / 5 | BC21: □□□□□■■■■■ | BD21: 10 / 10 | BE21: □□□□□□□□□□■■■■■■■■■■ | BF21: 1 | BG21: Animals | BL21: Holistic Awareness | BO21: Blood | BY21: Burried Feelings | CB21: Inspiring | CF21: 1 | CG21: 2 | CH21: 1 | CI21: Lance | CJ21: ● | CK21: Carthian | CL21: - | CM21: Crone | CN21: - | CO21: Invictus | CP21: - | CQ21: ● | CR21: - | CS21: - | CT21: ●●● | CU21: ●●●●● | CW21: - | CY21: 6 | CZ21: ~ | DA21: ○ | DB21: ○ | DC21: ○ | DD21: ○ | DE21: ● (Undefined) | DF21: ● | DG21: ● | DH21: ● | DI21: ● | DJ21: ● | DK21: Closed Book ●● | DL21: Indomitable ●● | DM21: Inspiring ●●● | DN21: Library (Academics) ●●● | DO21: Lorekeeper ● | DP21: Striking Looks ● | DQ21: ¬ | DR21: ¬ | DS21: ¬ | DT21: ¬ | DU21: ¬ | DV21: ¬ | DW21: ¬ | DX21: ¬ | DY21: ¬ | DZ21: ¬ | EA21: ¬ | EB21: ¬ | EC21: ¬ | ED21: ¬ | EE21: ¬ | EF21: ¬ | EG21: ¬ | EH21: ¬ | EI21: ¬ | EJ21: ¬ | EK21: ¬ | EL21: ¬ | EM21: ¬ | EN21: ¬ | EO21: Add dots to Doors and as bonus to contest Social assessments. | EP21: +2 to contest or resist supernatural mental influence. | EQ21: Roll Presence + Expression to confer the Inspired Condition. | ER21: Add dots to extended rolls for a chosen Skill's subject matter. | ES21: Distribute Library dots among bonus Retainer and Herd. | ET21: Add dots to Social rolls benefiting from appearance, and to rolls to notice/remember you. | EU21: ¬ | EV21: ¬ | EW21: ¬ | EX21: ¬ | EY21: ¬ | EZ21: ¬ | FA21: ¬ | FB21: ¬ | FC21: ¬ | FD21: ¬ | FE21: ¬ | FF21: ¬ | FG21: ¬ | FH21: ¬ | FI21: ¬ | FJ21: ¬ | FK21: ¬ | FL21: ¬ | FM21: ¬ | FN21: ¬ | FO21: ¬ | FP21: ¬ | FQ21: ¬ | FR21: ¬ | FS21: 5 / 5 | FT21: □□□□□ | FU21: Allies | FV21: ¬ | FW21: ¬ | FX21: ¬ | FY21: ¬ | FZ21: ¬ | GA21: ¬ | GB21: ¬ | GC21: ¬ | GD21: ¬ | GE21: ¬ | GF21: ¬ | GG21: ¬ | GH21: ¬ | GI21: ¬ | GJ21: ¬ | GK21: ¬ | GL21: ¬ | GM21: ¬ | GN21: ¬ | GO21: Health | GP21: ¬ | GQ21: ¬ | GR21: ¬ | GS21: ¬ | GT21: ¬ | GU21: ¬ | GV21: ¬ | GW21: ¬ | GX21: ¬ | GY21: ¬ | GZ21: ¬ | HA21: ¬ | HB21: ¬ | HC21: ¬ | HD21: ¬ | HE21: ¬ | HF21: ¬ | HG21: ¬ | HH21: ¬ | HI21: ●●● | IC21: - | ID21: - | IE21: ● | IF21: - | IG21: ●●● | IH21: - | II21: - | IJ21: - | IK21: - | IL21: - | IM21: - | IN21: ●● | IO21: - | IP21: - | IQ21: ● | IR21: - | IS21: ● | IT21: Celerity ● | IU21: Majesty ● | Awe | IV21: Majesty ●● | Confidant | IW21: Majesty ●●● | Green Eyes | IX21: Blood Sorcery | Divination ● | IY21: Blood Sorcery | Transmutation ● | IZ21: Theban ● | Vitae Reliquary | JA21: Theban ●●●● | Damned Radiance | JB21: ¬ | JC21: ¬ | JD21: ¬ | JE21: ¬ | JF21: ¬ | JG21: ¬ | JH21: ¬ | JI21: ¬ | JJ21: ¬ | JK21: ¬ | JL21: ¬ | JM21: ¬ | JN21: ¬ | JO21: ¬ | JP21: ¬ | JQ21: ¬ | JR21: ¬ | JS21: ¬ | JT21: ¬ | JU21: ¬ | JV21: ¬ | JW21: ¬ | JX21: Cost: 1 V per effect • Pool: - • Reflexive • 1 turn | JY21: Cost: - • Pool: - • Instant • Scene | JZ21: Cost: - (req: Awed) • Pool: 8 v Resolve + BP • Contested | KA21: Cost: 1 V (req: Charmed / Enthralled) • Pool: - • Instant • Scene | KB21: ¬ | KC21: ¬ | KD21: Cost: 1 V 1 Successes • Pool: 5 • Ritual • 1 lunar month | KE21: Cost: 1 WP 4 Successes • Pool: 9 v Stamina + BP • Ritual • 1 night | KF21: ¬ | KG21: ¬ | KH21: ¬ | KI21: ¬ | KJ21: ¬ | KK21: ¬ | KL21: ¬ | KM21: ¬ | KN21: ¬ | KO21: ¬ | KP21: ¬ | KQ21: ¬ | KR21: ¬ | KS21: ¬ | KT21: ¬ | KU21: ¬ | KV21: ¬ | KW21: ¬ | KX21: ¬ | KY21: ¬ | KZ21: ¬ | LA21: ¬ | LB21: Persistent improved Defence or Dodge. Activate for supernatural speed benefits. Unnatural Grace: add Celerity dots as bonus dice to non-combat speed-based pools. | LC21: Become centre of attention. Subjects become Awed. | LD21: Impose Charmed Condition. | LE21: Shift emotions (1 V, any number of Charmed/Enthralled targets); rage/fear causes frenzy with no resist roll (Ride the Wave normal). Requests: 1 V per target, must be spoken and heard. | LF21: Glimpse fragmented details about intended actions. Learn basic info about a target. | LG21: Minor cosmetic changes to living subjects. Warp dead matter. Animate liquids. | LH21: Store Vitae equal to Potency in object (Size 3 or smaller) | LI21: Vampire appears mortal, -2 Disciplines | LJ21: ¬ | LK21: ¬ | LL21: ¬ | LM21: ¬ | LN21: ¬ | LO21: ¬ | LP21: ¬ | LQ21: ¬ | LR21: ¬ | LS21: ¬ | LT21: ¬ | LU21: ¬ | LV21: ¬ | LW21: ¬ | LX21: ¬ | LY21: ¬ | LZ21: ¬ | MA21: ¬ | MB21: ¬ | MC21: ¬ | MD21: ¬ | ME21: ¬ | MF21: Wanton Curse | MG21: ¬ | MH21: ¬ | MI21: ¬ | MJ21: ¬ | MK21: Hungry at 5 or fewer Vitae, Starving at 3 or fewer. Dramatic Failures on feeding cause Persistent Dependent Condition toward a mortal NPC. | ML21: ¬ | MN21: ¬ | MO21: ¬ | MP21: 5 | MQ21: 9 | MR21: 5 | MS21: Give advice that someone uses to succeed. | MT21: Give protected, dangerous information without asking for payment. | MU21: Uncover a lost piece of information. | MV21: Uncover forbidden knowledge. | MW21: ¬ | MX21: ¬ | MY21: ¬ | NA21: Striking Looks
A22: tblCharDataLudica | B22: 46104 | C22: 3 | D22: 30 | E22: Sky K | F22: Ludica Lachramore | G22: Information Broker | H22: she/her | I22: Mekhet | J22: D:\Terra Mortis\Character Sheets\Sheet Elements\Mekhet icon.svg | K22: ¬ | L22: Invictus | M22: D:\Terra Mortis\Character Sheets\Sheet Elements\Invictus icon.svg | N22: Scholar | O22: Spy | P22: ¬ | Q22: ●● | R22: ●●●● | S22: ●●● | T22: ● | U22: ●●● | V22: ●● | W22: ●● | X22: ●●● | Y22: ●● | Z22: ●● | AC22: ●●●● | AE22: ●●● | AF22: ●● | AH22: ●● | AM22: ●● | AQ22: ●●● | AS22: ●● | AU22: ●● | AW22: ● | AX22: ●○○○○○○○○○○○○○○○○○○ | AY22: 1 | BA22: □□□□□□□■■■■■■■■ | BB22: 5 / 5 | BC22: □□□□□■■■■■ | BD22: 10 / 10 | BE22: □□□□□□□□□□■■■■■■■■■■ | BF22: 1 | BG22: Animals | BK22: spycraft | BM22: bloodlines | CA22: blackmail | CF22: 3 | CG22: 1 | CH22: 1 | CI22: Invictus | CJ22: ● | CK22: Carthian | CL22: - | CM22: Crone | CN22: - | CO22: Lance | CP22: - | CQ22: ● | CR22: ● | CS22: - | CT22: ●●●●● | CU22: ●●●●● | CV22: <NAME REQUIRED> | CW22: - | CY22: 5 | CZ22: ~ | DA22: ○ | DB22: ○ | DC22: ○ | DD22: ○ | DE22: ○ (Former/Current Lover) | DF22: ● | DG22: ● | DH22: ● | DI22: ● | DJ22: ● | DK22: Alternate Identity ●●● | DL22: Crowdsourcing ●●● | DM22: Information Network ● | DN22: Peacemaker ●●● | DO22: Secret Society Junkie ● | DP22: Cacophony Savvy ● | Gettin' Up | DQ22: ¬ | DR22: ¬ | DS22: ¬ | DT22: ¬ | DU22: ¬ | DV22: ¬ | DW22: ¬ | DX22: ¬ | DY22: ¬ | DZ22: ¬ | EA22: ¬ | EB22: ¬ | EC22: ¬ | ED22: ¬ | EE22: ¬ | EF22: ¬ | EG22: ¬ | EH22: ¬ | EI22: ¬ | EJ22: ¬ | EK22: ¬ | EL22: ¬ | EM22: ¬ | EN22: ¬ | EO22: False identity: (•) informal, (••) documented, (•••) airtight. +1 Subterfuge to maintain, +2 at three dots. | EP22: Spend Willpower, roll Manipulation + Academics to transfer Social Merit dots between Invictus members, exceeding maximums by your dots. | EQ22: Use your Contacts as Skill Specialties. | ER22: Spend Willpower to negotiate peace via Social Manoeuvring. (•••) can talk down supernatural rages. | ES22: Dots in Status or Mystery Cult Initiation representing human secret societies also count as dots of Herd. | ET22: You can read the Cacophony with Intelligence + Streetwise. Within a vampire's Feeding Grounds, add their (not your) dots in that Merit as bonus dice. | EU22: ¬ | EV22: ¬ | EW22: ¬ | EX22: ¬ | EY22: ¬ | EZ22: ¬ | FA22: ¬ | FB22: ¬ | FC22: ¬ | FD22: ¬ | FE22: ¬ | FF22: ¬ | FG22: ¬ | FH22: ¬ | FI22: ¬ | FJ22: ¬ | FK22: ¬ | FL22: ¬ | FM22: ¬ | FN22: ¬ | FO22: ¬ | FP22: ¬ | FQ22: ¬ | FR22: ¬ | FS22: 4 / 6 | FT22: □□□□■■ | FU22: Allies | FV22: Contacts | FW22: Resources | FX22: ¬ | FY22: ¬ | FZ22: ¬ | GA22: ¬ | GB22: ¬ | GC22: ¬ | GD22: ¬ | GE22: ¬ | GF22: ¬ | GG22: ¬ | GH22: ¬ | GI22: ¬ | GJ22: ¬ | GK22: ¬ | GL22: ¬ | GM22: ¬ | GN22: ¬ | GO22: Underworld | GP22: high society, occult, politics | GQ22: ¬ | GR22: ¬ | GS22: ¬ | GT22: ¬ | GU22: ¬ | GV22: ¬ | GW22: ¬ | GX22: ¬ | GY22: ¬ | GZ22: ¬ | HA22: ¬ | HB22: ¬ | HC22: ¬ | HD22: ¬ | HE22: ¬ | HF22: ¬ | HG22: ¬ | HH22: ¬ | HI22: ●●● | HJ22: ●●● | HK22: ●●●●● | IC22: - | ID22: ●●●● | IE22: - | IF22: - | IG22: - | IH22: - | II22: ● | IJ22: - | IK22: - | IL22: - | IM22: - | IN22: - | IO22: - | IP22: - | IQ22: - | IR22: - | IS22: - | IT22: Auspex ● | Beast's Hackles | IU22: Auspex ●● | Uncanny Perception | IV22: Auspex ●●● | Spirit's Touch | IW22: Auspex ●●●● | Lay Open the Mind | IX22: Obfuscate ● | Face in the Crowd | IY22: ¬ | IZ22: ¬ | JA22: ¬ | JB22: ¬ | JC22: ¬ | JD22: ¬ | JE22: ¬ | JF22: ¬ | JG22: ¬ | JH22: ¬ | JI22: ¬ | JJ22: ¬ | JK22: ¬ | JL22: ¬ | JM22: ¬ | JN22: ¬ | JO22: ¬ | JP22: ¬ | JQ22: ¬ | JR22: ¬ | JS22: ¬ | JT22: ¬ | JU22: ¬ | JV22: ¬ | JW22: ¬ | JX22: Cost: Free (1 V for Insight) • Pool: - - Composure & Closed Book • Instant • Scene | JY22: Cost: Free (1 V for Insight) Must perceive target • Pool: - • Instant • Scene | JZ22: Cost: Free (1 WP for clash / 1 V for Insight) • Pool: - v Resolve + Stealth + Obf • Reflexive • Immediate | KA22: Cost: 1 V • Pool: 8 v Resolve + BP • Instant • Scene | KB22: Cost: - • Pool: - • Instant • Scene | KC22: ¬ | KD22: ¬ | KE22: ¬ | KF22: ¬ | KG22: ¬ | KH22: ¬ | KI22: ¬ | KJ22: ¬ | KK22: ¬ | KL22: ¬ | KM22: ¬ | KN22: ¬ | KO22: ¬ | KP22: ¬ | KQ22: ¬ | KR22: ¬ | KS22: ¬ | KT22: ¬ | KU22: ¬ | KV22: ¬ | KW22: ¬ | KX22: ¬ | KY22: ¬ | KZ22: ¬ | LA22: ¬ | LB22: Add Auspex dots to any rolls to resist surprise. Access to Tier 1 Auspex Insight questions. | LC22: Persistent Acute Senses Merit, doubles actual merit. Access to Tier 2 Auspex Insight questions. | LD22: Passively scan for anyone under Obfuscate 1 or 3, can provoke a challenge. Access to Tier 3 Auspex Insight questions. | LE22: Telepathy and mind-reading. Invoke Conditions. | LF22: Blend into surroundings, visible but unnoticeable. Predatory aura fully on or off. Leaving combat: Wits + Composure - Obfuscate to notice; auto Clash of Wills vs Auspex. | LG22: ¬ | LH22: ¬ | LI22: ¬ | LJ22: ¬ | LK22: ¬ | LL22: ¬ | LM22: ¬ | LN22: ¬ | LO22: ¬ | LP22: ¬ | LQ22: ¬ | LR22: ¬ | LS22: ¬ | LT22: ¬ | LU22: ¬ | LV22: ¬ | LW22: ¬ | LX22: ¬ | LY22: ¬ | LZ22: ¬ | MA22: ¬ | MB22: ¬ | MC22: ¬ | MD22: ¬ | ME22: ¬ | MF22: Tenebrous Curse | MG22: ¬ | MH22: ¬ | MI22: ¬ | MJ22: ¬ | MK22: Gain an extra bane at Humanity 6 (doesn't count towards cap); Humanity counts –1 for all Humanity-based banes. | ML22: ¬ | MN22: ¬ | MO22: ¬ | MP22: 5 | MQ22: 9 | MR22: 5 | MS22: Uncover a lost piece of information. | MT22: Uncover forbidden knowledge. | MU22: Build a new identity or uncover a secret. | MV22: Uncover a damning secret that could end someone. | MW22: ¬ | MX22: ¬ | MY22: ¬ | MZ22: mid 20s
A23: tblCharDataMac | B23: 46104 | C23: 2 | D23: 54 | E23: Charlie BC | F23: Macheath 'Mac' | G23: Urban Gorilla | H23: he/him | I23: Mekhet | J23: D:\Terra Mortis\Character Sheets\Sheet Elements\Mekhet icon.svg | K23: Norvegi | L23: Carthian Movement | M23: D:\Terra Mortis\Character Sheets\Sheet Elements\Carthian icon.svg | N23: Rebel | O23: Idealist | P23: ¬ | Q23: ●● | R23: ●●● | S23: ●●● | T23: ●●●○○○ | U23: ●●● | V23: ●● | W23: ●● | X23: ● | Y23: ●●● | AB23: ● | AC23: ●●† | AE23: ● | AH23: ●●● | AI23: ●●●●○† | AL23: ●● | AM23: ●●† | AQ23: ●● | AS23: ●● | AV23: ●● | AW23: ● | AX23: ●●○○○○○○○○○○○○○○○○ | AY23: 2 | AZ23: † | BA23: □□□□□□□■■■■■■■■ | BB23: 6 / 6 | BC23: □□□□□□■■■■ | BD23: 11 / 11 | BE23: □□□□□□□□□□□■■■■■■■■■ | BF23: 2 | BG23: Animals | BQ23: grappling | BU23: shadowing | BY23: weakness | CA23: direct threats | CE23: hiding emotion | CF23: 2 | CG23: 2 | CH23: 3 | CI23: Carthian | CJ23: ●●● | CK23: Crone | CL23: - | CM23: Invictus | CN23: - | CO23: Lance | CP23: - | CQ23: - | CR23: - | CS23: - | CT23: - | CU23: - | CW23: ●●●●● | CX23: Urban Gurrilla | CY23: 5 | CZ23: ~ | DA23: ○ | DB23: ○ | DC23: ○ | DD23: ○ | DE23: ○ (Fiona (conditional) or union activist) | DF23: ● | DG23: ● | DH23: ● | DI23: ● | DJ23: ● | DK23: Carthian Pull ● | DL23: Mobilise Outrage ● | Strike to Preempt | DM23: Mobilise Outrage ●● | Unbreakable | DN23: Mobilise Outrage ●●● | Dying on Your Feet | DO23: Regular ● | Clinch Strike | DP23: ¬ | DQ23: ¬ | DR23: ¬ | DS23: ¬ | DT23: ¬ | DU23: ¬ | DV23: ¬ | DW23: ¬ | DX23: ¬ | DY23: ¬ | DZ23: ¬ | EA23: ¬ | EB23: ¬ | EC23: ¬ | ED23: ¬ | EE23: ¬ | EF23: ¬ | EG23: ¬ | EH23: ¬ | EI23: ¬ | EJ23: ¬ | EK23: ¬ | EL23: ¬ | EM23: ¬ | EN23: ¬ | EO23: Monthly, access Carthian Status in dots of Allies, Contacts, Haven or Herd. | EP23: Sacrifice your Defence and your second turn to add your Willpower as bonus dice to attack on your first turn. | EQ23: Add your full Willpower value when spending a point to contest or resist social or mental coercion in a combat situation. | ER23: During combat only, ignore wound penalties and do not fall to torpor from injury. | ES23: Use Damage manoeuvre instantly in a grapple. | ET23: ¬ | EU23: ¬ | EV23: ¬ | EW23: ¬ | EX23: ¬ | EY23: ¬ | EZ23: ¬ | FA23: ¬ | FB23: ¬ | FC23: ¬ | FD23: ¬ | FE23: ¬ | FF23: ¬ | FG23: ¬ | FH23: ¬ | FI23: ¬ | FJ23: ¬ | FK23: ¬ | FL23: ¬ | FM23: ¬ | FN23: ¬ | FO23: ¬ | FP23: ¬ | FQ23: ¬ | FR23: ¬ | FS23: 5 / 5 | FT23: □□□□□ | FU23: Allies | FV23: Contacts | FW23: ¬ | FX23: ¬ | FY23: ¬ | FZ23: ¬ | GA23: ¬ | GB23: ¬ | GC23: ¬ | GD23: ¬ | GE23: ¬ | GF23: ¬ | GG23: ¬ | GH23: ¬ | GI23: ¬ | GJ23: ¬ | GK23: ¬ | GL23: ¬ | GM23: ¬ | GN23: ¬ | GO23: street | GP23: street, transport, underworld | GQ23: ¬ | GR23: ¬ | GS23: ¬ | GT23: ¬ | GU23: ¬ | GV23: ¬ | GW23: ¬ | GX23: ¬ | GY23: ¬ | GZ23: ¬ | HA23: ¬ | HB23: ¬ | HC23: ¬ | HD23: ¬ | HE23: ¬ | HF23: ¬ | HG23: ¬ | HH23: ¬ | HI23: ● | HJ23: ●●● | IC23: - | ID23: ●●● | IE23: ●● | IF23: - | IG23: - | IH23: - | II23: ● | IJ23: ● | IK23: - | IL23: ●●● | IM23: - | IN23: - | IO23: - | IP23: - | IQ23: - | IR23: - | IS23: - | IT23: Auspex ● | Beast's Hackles | IU23: Auspex ●● | Uncanny Perception | IV23: Auspex ●●● | Spirit's Touch | IW23: Celerity ●● | IX23: Obfuscate ● | Face in the Crowd | IY23: Protean ● | Unmarked Grave | IZ23: Vigour ●●● | JA23: Devotion | Vitae Spines | JB23: ¬ | JC23: ¬ | JD23: ¬ | JE23: ¬ | JF23: ¬ | JG23: ¬ | JH23: ¬ | JI23: ¬ | JJ23: ¬ | JK23: ¬ | JL23: ¬ | JM23: ¬ | JN23: ¬ | JO23: ¬ | JP23: ¬ | JQ23: ¬ | JR23: ¬ | JS23: ¬ | JT23: ¬ | JU23: ¬ | JV23: ¬ | JW23: ¬ | JX23: Cost: Free (1 V for Insight) • Pool: - - Composure & Closed Book • Instant • Scene | JY23: Cost: Free (1 V for Insight) Must perceive target • Pool: - • Instant • Scene | JZ23: Cost: Free (1 WP for clash / 1 V for Insight) • Pool: - v Resolve + Stealth + Obf • Reflexive • Immediate | KA23: Cost: 1 V per effect • Pool: - • Reflexive • 1 turn | KB23: Cost: - • Pool: - • Instant • Scene | KC23: Cost: Varies • Pool: - • Instant • Indefinite | KD23: Cost: 1 V per effect • Pool: - • Reflexive • 1 turn | KE23: Cost: 1 V per effect Norvegi Bloodline • Pool: - • Reflexive • Scene | KF23: ¬ | KG23: ¬ | KH23: ¬ | KI23: ¬ | KJ23: ¬ | KK23: ¬ | KL23: ¬ | KM23: ¬ | KN23: ¬ | KO23: ¬ | KP23: ¬ | KQ23: ¬ | KR23: ¬ | KS23: ¬ | KT23: ¬ | KU23: ¬ | KV23: ¬ | KW23: ¬ | KX23: ¬ | KY23: ¬ | KZ23: ¬ | LA23: ¬ | LB23: Add Auspex dots to any rolls to resist surprise. Access to Tier 1 Auspex Insight questions. | LC23: Persistent Acute Senses Merit, doubles actual merit. Access to Tier 2 Auspex Insight questions. | LD23: Passively scan for anyone under Obfuscate 1 or 3, can provoke a challenge. Access to Tier 3 Auspex Insight questions. | LE23: Persistent improved Defence or Dodge. Activate for supernatural speed benefits. Unnatural Grace: add Celerity dots as bonus dice to non-combat speed-based pools. | LF23: Blend into surroundings, visible but unnoticeable. Predatory aura fully on or off. Leaving combat: Wits + Composure - Obfuscate to notice; auto Clash of Wills vs Auspex. | LG23: Merge with soil. | LH23: Improve Strength. Add Vigour dots as bonus successes only if at least one net success achieved. | LI23: Choose one: feed through fingertip spines as if by fangs (requires touch or grapple; leaves dry, calloused skin); or extend organic blades (1L supernatural weapon, Strength + Brawl to attack, -2 to Dexterity-based manipulation; fine manipulation impossible). | LJ23: ¬ | LK23: ¬ | LL23: ¬ | LM23: ¬ | LN23: ¬ | LO23: ¬ | LP23: ¬ | LQ23: ¬ | LR23: ¬ | LS23: ¬ | LT23: ¬ | LU23: ¬ | LV23: ¬ | LW23: ¬ | LX23: ¬ | LY23: ¬ | LZ23: ¬ | MA23: ¬ | MB23: ¬ | MC23: ¬ | MD23: ¬ | ME23: ¬ | MF23: Tenebrous Curse | MG23: ¬ | MH23: ¬ | MI23: ¬ | MJ23: ¬ | MK23: Gain an extra bane at Humanity 6 (doesn't count towards cap); Humanity counts –1 for all Humanity-based banes. | ML23: ¬ | MN23: ¬ | MO23: ¬ | MP23: 5 | MQ23: 14 | MR23: 6 | MS23: Openly flout a tradition. | MT23: Openly flout a Kindred Tradition or a covenant taboo. | MU23: Deny a compromise that would water down your ideal. | MV23: Refuse safety for fear of abandoning your ideal's purity. | MW23: ¬ | MX23: ¬ | MY23: ¬
A24: tblCharDataMagda | B24: 46104 | C24: 0 | D24: 17 | E24: Tiana C | F24: Magda | G24: Faithful Militant | H24: she/her | I24: Nosferatu | J24: D:\Terra Mortis\Character Sheets\Sheet Elements\Nosferatu icon.svg | K24: ¬ | L24: Lancea et Sanctum | M24: D:\Terra Mortis\Character Sheets\Sheet Elements\Lance icon.svg | N24: Martyr | O24: Masochist | P24: ¬ | Q24: ●●● | R24: ●● | S24: ●●● | T24: ●● | U24: ●●● | V24: ●● | W24: ●●● | X24: ●● | Y24: ●● | Z24: ●●●● | AB24: ● | AC24: ● | AE24: ● | AI24: ●● | AK24: ●●● | AL24: ●● | AM24: ●● | AO24: ●● | AQ24: ●● | AS24: ●● | AX24: ●○○○○○○○○○○○○○○○○○○ | AY24: 1 | BA24: □□□□□□□■■■■■■■■ | BB24: 5 / 5 | BC24: □□□□□■■■■■ | BD24: 10 / 10 | BE24: □□□□□□□□□□■■■■■■■■■■ | BF24: 1 | BG24: Animals | BH24: theban | BS24: rifles | BW24: swords | BY24: motives | CF24: 1 | CG24: 1 | CH24: 2 | CI24: Lance | CJ24: ●● | CK24: Carthian | CL24: - | CM24: Crone | CN24: - | CO24: Invictus | CP24: - | CQ24: ●●●●● | CR24: ●●● | CS24: - | CT24: ●● | CU24: - | CW24: - | CY24: 7 | CZ24: ~ | DA24: ○ | DB24: ○ | DC24: ○ | DD24: ● | DE24: ● (Catholic Priest) | DF24: ● | DG24: ● | DH24: ● | DI24: ● | DJ24: ● | DK24: Danger Sense ●● | DL24: Fighting Finesse (Weaponry) ●● | DM24: Flock ●● | DN24: ¬ | DO24: ¬ | DP24: ¬ | DQ24: ¬ | DR24: ¬ | DS24: ¬ | DT24: ¬ | DU24: ¬ | DV24: ¬ | DW24: ¬ | DX24: ¬ | DY24: ¬ | DZ24: ¬ | EA24: ¬ | EB24: ¬ | EC24: ¬ | ED24: ¬ | EE24: ¬ | EF24: ¬ | EG24: ¬ | EH24: ¬ | EI24: ¬ | EJ24: ¬ | EK24: ¬ | EL24: ¬ | EM24: ¬ | EN24: ¬ | EO24: +2 bonus to detect an ambush. | EP24: Substitute Dexterity for Strength with a chosen Brawl or Weaponry Specialty. | EQ24: Herd serves as Willpower source. Dots apply as additional Herd dots. | ER24: ¬ | ES24: ¬ | ET24: ¬ | EU24: ¬ | EV24: ¬ | EW24: ¬ | EX24: ¬ | EY24: ¬ | EZ24: ¬ | FA24: ¬ | FB24: ¬ | FC24: ¬ | FD24: ¬ | FE24: ¬ | FF24: ¬ | FG24: ¬ | FH24: ¬ | FI24: ¬ | FJ24: ¬ | FK24: ¬ | FL24: ¬ | FM24: ¬ | FN24: ¬ | FO24: ¬ | FP24: ¬ | FQ24: ¬ | FR24: ¬ | FS24: 3 / 3 | FT24: □□□ | FU24: ¬ | FV24: ¬ | FW24: ¬ | FX24: ¬ | FY24: ¬ | FZ24: ¬ | GA24: ¬ | GB24: ¬ | GC24: ¬ | GD24: ¬ | GE24: ¬ | GF24: ¬ | GG24: ¬ | GH24: ¬ | GI24: ¬ | GJ24: ¬ | GK24: ¬ | GL24: ¬ | GM24: ¬ | GN24: ¬ | GO24: ¬ | GP24: ¬ | GQ24: ¬ | GR24: ¬ | GS24: ¬ | GT24: ¬ | GU24: ¬ | GV24: ¬ | GW24: ¬ | GX24: ¬ | GY24: ¬ | GZ24: ¬ | HA24: ¬ | HB24: ¬ | HC24: ¬ | HD24: ¬ | HE24: ¬ | HF24: ¬ | HG24: ¬ | HH24: ¬ | IC24: - | ID24: - | IE24: - | IF24: - | IG24: - | IH24: ● | II24: ● | IJ24: - | IK24: - | IL24: - | IM24: - | IN24: ●●●● | IO24: - | IP24: - | IQ24: ● | IR24: - | IS24: ● | IT24: Nightmare ● | Dread Presence | IU24: Obfuscate ● | Face in the Crowd | IV24: Blood Sorcery | Divination ● | IW24: Blood Sorcery | Transmutation ● | IX24: ¬ | IY24: ¬ | IZ24: ¬ | JA24: ¬ | JB24: ¬ | JC24: ¬ | JD24: ¬ | JE24: ¬ | JF24: ¬ | JG24: ¬ | JH24: ¬ | JI24: ¬ | JJ24: ¬ | JK24: ¬ | JL24: ¬ | JM24: ¬ | JN24: ¬ | JO24: ¬ | JP24: ¬ | JQ24: ¬ | JR24: ¬ | JS24: ¬ | JT24: ¬ | JU24: ¬ | JV24: ¬ | JW24: ¬ | JX24: Cost: - • Pool: - • Instant • Scene | JY24: Cost: - • Pool: - • Instant • Scene | JZ24: ¬ | KA24: ¬ | KB24: ¬ | KC24: ¬ | KD24: ¬ | KE24: ¬ | KF24: ¬ | KG24: ¬ | KH24: ¬ | KI24: ¬ | KJ24: ¬ | KK24: ¬ | KL24: ¬ | KM24: ¬ | KN24: ¬ | KO24: ¬ | KP24: ¬ | KQ24: ¬ | KR24: ¬ | KS24: ¬ | KT24: ¬ | KU24: ¬ | KV24: ¬ | KW24: ¬ | KX24: ¬ | KY24: ¬ | KZ24: ¬ | LA24: ¬ | LB24: Conjure brief illusions. Improve Intimidation. Prevent foes spending Willpower. | LC24: Blend into surroundings, visible but unnoticeable. Predatory aura fully on or off. Leaving combat: Wits + Composure - Obfuscate to notice; auto Clash of Wills vs Auspex. | LD24: Glimpse fragmented details about intended actions. Learn basic info about a target. | LE24: Minor cosmetic changes to living subjects. Warp dead matter. Animate liquids. | LF24: ¬ | LG24: ¬ | LH24: ¬ | LI24: ¬ | LJ24: ¬ | LK24: ¬ | LL24: ¬ | LM24: ¬ | LN24: ¬ | LO24: ¬ | LP24: ¬ | LQ24: ¬ | LR24: ¬ | LS24: ¬ | LT24: ¬ | LU24: ¬ | LV24: ¬ | LW24: ¬ | LX24: ¬ | LY24: ¬ | LZ24: ¬ | MA24: ¬ | MB24: ¬ | MC24: ¬ | MD24: ¬ | ME24: ¬ | MF24: Lonely Curse | MG24: ¬ | MH24: ¬ | MI24: ¬ | MJ24: ¬ | MK24: With mortals, Humanity counts –2; Presence/Manipulation failures become dramatic failures. Intimidation and Subterfuge unaffected. | ML24: ¬ | MN24: ¬ | MO24: ¬ | MP24: 5 | MQ24: 10 | MR24: 2 | MS24: Take another's burden upon yourself without expecting recompense. | MT24: Put yourself at risk to save someone else or an ideology. | MU24: Find and experience a new source of hurt. | MV24: Willingly explore pain beyond the point of safety and reason. | MW24: ¬ | MX24: ¬ | MY24: ¬
A25: tblCharDataMammon | B25: 46104 | C25: 0 | D25: 54 | E25: Peter K | F25: Yusuf 'Mammon' Kalusicj | G25: Nightmate Shadow Broker | H25: he/him | I25: Nosferatu | J25: D:\Terra Mortis\Character Sheets\Sheet Elements\Nosferatu icon.svg | K25: ¬ | L25: Carthian Movement | M25: D:\Terra Mortis\Character Sheets\Sheet Elements\Carthian icon.svg | N25: Cult Leader | O25: Penitent | P25: ¬ | Q25: ●● | R25: ●● | S25: ●●● | T25: ● | U25: ●●● | V25: ●● | W25: ●●●● | X25: ●●● | Y25: ●● | AC25: ●●● | AE25: ●● | AF25: ●● | AH25: ●● | AM25: ●● | AQ25: ●●●● | AS25: ●●●● | AW25: ●●● | AX25: ●●○○○○○○○○○○○○○○○○ | AY25: 2 | AZ25: † | BA25: □□□□□□□■■■■■■■■ | BB25: 5 / 5 | BC25: □□□□□■■■■■ | BD25: 11 / 11 | BE25: □□□□□□□□□□□■■■■■■■■■ | BF25: 2 | BG25: Animals | BK25: Forensic Accounting | BY25: Motives | CA25: Veiled Threats | CF25: 2 | CG25: 2 | CH25: 1 | CI25: Carthian | CJ25: ● | CK25: Crone | CL25: - | CM25: Invictus | CN25: - | CO25: Lance | CP25: - | CQ25: ● | CR25: - | CS25: - | CT25: ●●●●● | CU25: ●●●●● | CW25: - | CY25: 4 | CZ25: ˅ | DA25: ○ | DB25: ○ | DC25: ○ | DD25: ○ | DE25: ○ (Portrait of my Wife) | DF25: ○ (Turkish Laundrette Woman) | DG25: ● | DH25: ● | DI25: ● | DJ25: ● | DK25: Air of Menace ●● | DL25: Fucking Thief ● | DM25: Honey With Vinegar ● | DN25: Indomitable ●● | DO25: Secret Society Junkie ● | DP25: ¬ | DQ25: ¬ | DR25: ¬ | DS25: ¬ | DT25: ¬ | DU25: ¬ | DV25: ¬ | DW25: ¬ | DX25: ¬ | DY25: ¬ | DZ25: ¬ | EA25: ¬ | EB25: ¬ | EC25: ¬ | ED25: ¬ | EE25: ¬ | EF25: ¬ | EG25: ¬ | EH25: ¬ | EI25: ¬ | EJ25: ¬ | EK25: ¬ | EL25: ¬ | EM25: ¬ | EN25: ¬ | EO25: +2 to menace; others spend Willpower to pick fights. Social manoeuvring harder. | EP25: Steal flawed knowledge of a single one-dot advantage restricted to another covenant. | EQ25: You earn influence from Allies, Contacts, and wide Mortal Status one step lower than normal. 1 point of influence at 2 dots or 4 dots respectively. | ER25: +2 to contest or resist supernatural mental influence. | ES25: Dots in Status or Mystery Cult Initiation representing human secret societies also count as dots of Herd. | ET25: ¬ | EU25: ¬ | EV25: ¬ | EW25: ¬ | EX25: ¬ | EY25: ¬ | EZ25: ¬ | FA25: ¬ | FB25: ¬ | FC25: ¬ | FD25: ¬ | FE25: ¬ | FF25: ¬ | FG25: ¬ | FH25: ¬ | FI25: ¬ | FJ25: ¬ | FK25: ¬ | FL25: ¬ | FM25: ¬ | FN25: ¬ | FO25: ¬ | FP25: ¬ | FQ25: ¬ | FR25: ¬ | FS25: 10 / 10 | FT25: □□□□□□□□□□ | FU25: Allies | FV25: Allies | FW25: Allies | FX25: Contacts | FY25: Resources | FZ25: ¬ | GA25: ¬ | GB25: ¬ | GC25: ¬ | GD25: ¬ | GE25: ¬ | GF25: ¬ | GG25: ¬ | GH25: ¬ | GI25: ¬ | GJ25: ¬ | GK25: ¬ | GL25: ¬ | GM25: ¬ | GN25: ¬ | GO25: Finance | GP25: Politics | GQ25: Underworld | GR25: Police, High Society, Occult, Media, Street | GS25: ¬ | GT25: ¬ | GU25: ¬ | GV25: ¬ | GW25: ¬ | GX25: ¬ | GY25: ¬ | GZ25: ¬ | HA25: ¬ | HB25: ¬ | HC25: ¬ | HD25: ¬ | HE25: ¬ | HF25: ¬ | HG25: ¬ | HH25: ¬ | HI25: ●●● | HJ25: ●● | HK25: ●● | HL25: ●●●●● | HM25: ●●● | IC25: - | ID25: ● | IE25: - | IF25: - | IG25: - | IH25: ●●●● | II25: ●●●● | IJ25: - | IK25: - | IL25: - | IM25: - | IN25: - | IO25: - | IP25: - | IQ25: - | IR25: - | IS25: - | IT25: Auspex ● | Beast's Hackles | IU25: Nightmare ● | Dread Presence | IV25: Nightmare ●● | Face of the Beast | IW25: Nightmare ●●● | Grand Delusion | IX25: Nightmare ●●●● | Waking Nightmare | IY25: Obfuscate ● | Face in the Crowd | IZ25: Obfuscate ●● | Touch of Shadow | JA25: Obfuscate ●●● | Cloak of Night | JB25: Obfuscate ●●●● | The Familiar Stranger | JC25: ¬ | JD25: ¬ | JE25: ¬ | JF25: ¬ | JG25: ¬ | JH25: ¬ | JI25: ¬ | JJ25: ¬ | JK25: ¬ | JL25: ¬ | JM25: ¬ | JN25: ¬ | JO25: ¬ | JP25: ¬ | JQ25: ¬ | JR25: ¬ | JS25: ¬ | JT25: ¬ | JU25: ¬ | JV25: ¬ | JW25: ¬ | JX25: Cost: Free (1 V for Insight) • Pool: - - Composure & Closed Book • Instant • Scene | JY25: Cost: - • Pool: - • Instant • Scene | JZ25: Cost: 1 V • Pool: 12 v Composure + BP • Contested • Instant | KA25: Cost: 2 V • Pool: 11 v Composure + BP • Contested • 1 night | KB25: Cost: 1 V • Pool: 12 v highest Composure + BP • Contested • Scene | KC25: Cost: - • Pool: - • Instant • Scene | KD25: Cost: 1 V • Pool: 5 • Instant • Scene | KE25: Cost: 1 V • Pool: - • None | KF25: Cost: 2 V • Pool: - • None | KG25: ¬ | KH25: ¬ | KI25: ¬ | KJ25: ¬ | KK25: ¬ | KL25: ¬ | KM25: ¬ | KN25: ¬ | KO25: ¬ | KP25: ¬ | KQ25: ¬ | KR25: ¬ | KS25: ¬ | KT25: ¬ | KU25: ¬ | KV25: ¬ | KW25: ¬ | KX25: ¬ | KY25: ¬ | KZ25: ¬ | LA25: ¬ | LB25: Add Auspex dots to any rolls to resist surprise. Access to Tier 1 Auspex Insight questions. | LC25: Conjure brief illusions. Improve Intimidation. Prevent foes spending Willpower. | LD25: Impose Frightened Condition. Cause fleeing. | LE25: Impose Delusional Condition. | LF25: Create and control hallucinations. | LG25: Blend into surroundings, visible but unnoticeable. Predatory aura fully on or off. Leaving combat: Wits + Composure - Obfuscate to notice; auto Clash of Wills vs Auspex. | LH25: Cast Face in the Crowd on object or person. Free and unlimited duration on carried/worn objects if not drawing attention. | LI25: Become invisible. Leaving combat: auto Clash of Wills vs Auspex 2. | LJ25: Disguise self or other as a desired person. Free unlimited duration to reskin carried/worn objects, but no equipment bonus without Vitae. | LK25: ¬ | LL25: ¬ | LM25: ¬ | LN25: ¬ | LO25: ¬ | LP25: ¬ | LQ25: ¬ | LR25: ¬ | LS25: ¬ | LT25: ¬ | LU25: ¬ | LV25: ¬ | LW25: ¬ | LX25: ¬ | LY25: ¬ | LZ25: ¬ | MA25: ¬ | MB25: ¬ | MC25: ¬ | MD25: ¬ | ME25: ¬ | MF25: Lonely Curse | MG25: ¬ | MH25: Plague of Purity | MI25: ¬ | MJ25: ¬ | MK25: With mortals, Humanity counts –2; Presence/Manipulation failures become dramatic failures. Intimidation and Subterfuge unaffected. | ML25: ¬ | MM25: Touch by Integrity 8+ mortal causes (10 – Humanity) bashing damage. | MN25: ¬ | MO25: ¬ | MP25: 5 | MQ25: 9 | MR25: 4 | MS25: Convince someone to deny logic because of your word. | MT25: Risk exile or death to defend your cult's belief system. | MU25: Punish yourself for a mistake. | MV25: Risk death to correct an egregious error in judgement. | MW25: ¬ | MX25: ¬ | MY25: ¬ | MZ25: indeterminate | NA25: High Presence
A26: tblCharDataReed | B26: 46104 | C26: 2 | D26: 30 | E26: Conan F | F26: Reed Justice | G26: Opportunistic Predator | H26: he/him | I26: Ventrue | J26: D:\Terra Mortis\Character Sheets\Sheet Elements\Ventrue icon.svg | K26: ¬ | L26: Invictus | M26: D:\Terra Mortis\Character Sheets\Sheet Elements\Invictus icon.svg | N26: Visionary | O26: Authoritarian | P26: Regent | Q26: ●●●●● | R26: ●● | S26: ●● | T26: ●● | U26: ●● | V26: ●●○ | W26: ●● | X26: ●●● | Y26: ●● | Z26: ●● | AA26: ●●● | AF26: ●● | AH26: ● | AJ26: ● | AK26: ●● | AR26: ●●●● | AS26: ●● | AT26: ● | AV26: ● | AW26: ●●●● | AX26: ●○○○○○○○○○○○○○○○○○○ | AY26: 1 | BA26: □□□□□□□□■■■■■■■ | BB26: 4 / 4 | BC26: □□□□■■■■■■ | BD26: 10 / 10 | BE26: □□□□□□□□□□■■■■■■■■■■ | BF26: 1 | BG26: Animals | BI26: LLM/AI | BZ26: speeches | CE26: doublespeak | CF26: 2 | CG26: 2 | CH26: 2 | CI26: Invictus | CJ26: ●● | CK26: Carthian | CL26: - | CM26: Crone | CN26: - | CO26: Lance | CP26: - | CQ26: ● | CR26: ● | CS26: - | CT26: - | CU26: - | CW26: - | CY26: 6 | CZ26: ~ | DA26: ○ | DB26: ○ | DC26: ○ | DD26: ○ (Artwork of Mother) | DE26: ● | DF26: ● | DG26: ● | DH26: ● | DI26: ● | DJ26: ● | DK26: ¬ | DL26: ¬ | DM26: ¬ | DN26: ¬ | DO26: ¬ | DP26: ¬ | DQ26: ¬ | DR26: ¬ | DS26: ¬ | DT26: ¬ | DU26: ¬ | DV26: ¬ | DW26: ¬ | DX26: ¬ | DY26: ¬ | DZ26: ¬ | EA26: ¬ | EB26: ¬ | EC26: ¬ | ED26: ¬ | EE26: ¬ | EF26: ¬ | EG26: ¬ | EH26: ¬ | EI26: ¬ | EJ26: ¬ | EK26: ¬ | EL26: ¬ | EM26: ¬ | EN26: ¬ | EO26: ¬ | EP26: ¬ | EQ26: ¬ | ER26: ¬ | ES26: ¬ | ET26: ¬ | EU26: ¬ | EV26: ¬ | EW26: ¬ | EX26: ¬ | EY26: ¬ | EZ26: ¬ | FA26: ¬ | FB26: ¬ | FC26: ¬ | FD26: ¬ | FE26: ¬ | FF26: ¬ | FG26: ¬ | FH26: ¬ | FI26: ¬ | FJ26: ¬ | FK26: ¬ | FL26: ¬ | FM26: ¬ | FN26: ¬ | FO26: ¬ | FP26: ¬ | FQ26: ¬ | FR26: ¬ | FS26: 9 / 9 | FT26: □□□□□□□□□ | FU26: Resources | FV26: Status | FW26: Status | FX26: Status | FY26: ¬ | FZ26: ¬ | GA26: ¬ | GB26: ¬ | GC26: ¬ | GD26: ¬ | GE26: ¬ | GF26: ¬ | GG26: ¬ | GH26: ¬ | GI26: ¬ | GJ26: ¬ | GK26: ¬ | GL26: ¬ | GM26: ¬ | GN26: ¬ | GO26: ¬ | GP26: finance | GQ26: high society | GR26: underworld | GS26: ¬ | GT26: ¬ | GU26: ¬ | GV26: ¬ | GW26: ¬ | GX26: ¬ | GY26: ¬ | GZ26: ¬ | HA26: ¬ | HB26: ¬ | HC26: ¬ | HD26: ¬ | HE26: ¬ | HF26: ¬ | HG26: ¬ | HH26: ¬ | HI26: ●●●●● | HJ26: ●●● | HK26: ●●● | HL26: ●●● | IC26: - | ID26: - | IE26: - | IF26: ●●●●● | IG26: - | IH26: - | II26: - | IJ26: - | IK26: ● | IL26: - | IM26: - | IN26: - | IO26: - | IP26: - | IQ26: - | IR26: - | IS26: - | IT26: Dominate ● | Mesmerise | IU26: Dominate ●● | Iron Edict | IV26: Dominate ●●● | Entombed Command | IW26: Dominate ●●●● | The Lying Mind | IX26: Dominate ●●●●● | Possession | IY26: Resilience ● | IZ26: ¬ | JA26: ¬ | JB26: ¬ | JC26: ¬ | JD26: ¬ | JE26: ¬ | JF26: ¬ | JG26: ¬ | JH26: ¬ | JI26: ¬ | JJ26: ¬ | JK26: ¬ | JL26: ¬ | JM26: ¬ | JN26: ¬ | JO26: ¬ | JP26: ¬ | JQ26: ¬ | JR26: ¬ | JS26: ¬ | JT26: ¬ | JU26: ¬ | JV26: ¬ | JW26: ¬ | JX26: Cost: - -3 in combat unless Blinded • Pool: 14 v Resolve + BP • Instant • Instant | JY26: Cost: 1 V (0 in bond) (req: Mesmerised); -3 in combat unless Blinded • Pool: - • Instant • Instant | JZ26: Cost: - (req: Mesmerised) • Pool: 14 - Resolve • Instant • 1 week/success (1 month bonded) | KA26: Cost: 2 V (req: Mesmerised) • Pool: - • Instant • Permanent | KB26: Cost: 1 V & 1 WP (req: Mesmerised); -3 in combat unless Blinded • Pool: 12 - Resolve + Supernatural Tolerance • Instant • 1 scene per success | KC26: Cost: 1 V per effect • Pool: - • Reflexive • 1 turn | KD26: ¬ | KE26: ¬ | KF26: ¬ | KG26: ¬ | KH26: ¬ | KI26: ¬ | KJ26: ¬ | KK26: ¬ | KL26: ¬ | KM26: ¬ | KN26: ¬ | KO26: ¬ | KP26: ¬ | KQ26: ¬ | KR26: ¬ | KS26: ¬ | KT26: ¬ | KU26: ¬ | KV26: ¬ | KW26: ¬ | KX26: ¬ | KY26: ¬ | KZ26: ¬ | LA26: ¬ | LB26: Impose Mesmerised Condition. Control with short commands. | LC26: Impose Dominated Condition. Give long, detailed commands. | LD26: Establish triggers for other Dominate powers. | LE26: Impose Amnesia or False Memories Condition. | LF26: Control victim's body. Only walk in sun if victim normally can. | LG26: Downgrade damage and increase Stamina. Improve Armour and Defences. Unnatural Fortitude: add Resilience dots as bonus dice to non-combat Stamina pools. | LH26: ¬ | LI26: ¬ | LJ26: ¬ | LK26: ¬ | LL26: ¬ | LM26: ¬ | LN26: ¬ | LO26: ¬ | LP26: ¬ | LQ26: ¬ | LR26: ¬ | LS26: ¬ | LT26: ¬ | LU26: ¬ | LV26: ¬ | LW26: ¬ | LX26: ¬ | LY26: ¬ | LZ26: ¬ | MA26: ¬ | MB26: ¬ | MC26: ¬ | MD26: ¬ | ME26: ¬ | MF26: Aloof Curse | MG26: ¬ | MH26: ¬ | MI26: ¬ | MJ26: ¬ | MK26: First Touchstone attaches to Humanity 7; losing it detaches on first Humanity loss. Breaking points always treated as one step lower. | ML26: ¬ | MN26: ¬ | MO26: ¬ | MP26: 5 | MQ26: 9 | MR26: 3 | MS26: Help someone by sharing your vision with them. | MT26: Put yourself at risk to show a group the power of your vision. | MU26: Cow someone into submission. | MV26: Commit a widespread hit against a rival's mortal connections. | MW26: ¬ | MX26: ¬ | MY26: ¬ | MZ26: late 30s
A27: tblCharDataReneM | B27: 46104 | C27: 2 | D27: 56 | E27: Luca V | F27: René Meyer | G27: Insurgent | H27: she/her | I27: Daeva | J27: D:\Terra Mortis\Character Sheets\Sheet Elements\Daeva icon.svg | K27: Zelani | L27: Carthian Movement | M27: D:\Terra Mortis\Character Sheets\Sheet Elements\Carthian icon.svg | N27: Nurturer | O27: Idealist | P27: Regent | Q27: ●● | R27: ●●● | S27: ●●● | T27: ●○ | U27: ●●● | V27: ●● | W27: ●● | X27: ●●● | Y27: ●●● | AE27: ●● | AF27: ●● | AH27: ●● | AK27: ●● | AL27: ●●● | AQ27: ●●●† | AT27: ●● | AV27: ●●●† | AW27: ●●● | AX27: ●○○○○○○○○○○○○○○○○○○ | AY27: 1 | BA27: □□□□□□□■■■■■■■■ | BB27: 6 / 6 | BC27: □□□□□□■■■■ | BD27: 10 / 10 | BE27: □□□□□□□□□□■■■■■■■■■■ | BF27: 1 | BG27: Animals | BM27: Supernatural Compulsions | BN27: Activism | CD27: Rumours | CF27: 1 | CG27: 2 | CH27: 2 | CI27: Carthian | CJ27: ●● | CK27: Crone | CL27: - | CM27: Invictus | CN27: - | CO27: Lance | CP27: - | CQ27: ●● | CR27: ● | CS27: - | CT27: - | CU27: - | CW27: ●● | CY27: 5 | CZ27: ~ | DA27: ○ | DB27: ○ | DC27: ○ | DD27: ○ | DE27: ○ | DF27: ● | DG27: ● | DH27: ● | DI27: ● | DJ27: ● | DK27: Finger on the Pulse ● | DL27: Fucking Thief (Sorcerous Eunuch) ● | DM27: Honey With Vinegar ● | DN27: Indomitable ●● | DO27: Sorcerous Eunuch ● | DP27: Table Turner ● | DQ27: Cacophony Savvy ● | Gettin' Up | DR27: Cacophony Savvy ●● | Backpacker | DS27: Fast-Talking ● | Always Be Closing | DT27: Marksmanship ● | Through the Crosshairs | DU27: ¬ | DV27: ¬ | DW27: ¬ | DX27: ¬ | DY27: ¬ | DZ27: ¬ | EA27: ¬ | EB27: ¬ | EC27: ¬ | ED27: ¬ | EE27: ¬ | EF27: ¬ | EG27: ¬ | EH27: ¬ | EI27: ¬ | EJ27: ¬ | EK27: ¬ | EL27: ¬ | EM27: ¬ | EN27: ¬ | EO27: You are immersed in the Cacophony, and do not suffer the drawback of Cacophony Savvy. | EP27: Steal flawed knowledge of a single one-dot advantage restricted to another covenant. | EQ27: You earn influence from Allies, Contacts, and wide Mortal Status one step lower than normal. 1 point of influence at 2 dots or 4 dots respectively. | ER27: +2 to contest or resist supernatural mental influence. | ES27: Penalise sorcery against you by Resolve. Can't learn blood sorcery. | ET27: Spend Willpower to preempt Social Manoeuvring with your own Social action. | EU27: You can read the Cacophony with Intelligence + Streetwise. Within a vampire's Feeding Grounds, add their (not your) dots in that Merit as bonus dice. | EV27: You quickly learn who's who and where they hunt, even newcomers to the city. | EW27: Ignore one dot of a mark's Resolve or Composure when contested or resisted. | EX27: Raise your maximum Aim bonus to Composure + Firearms. | EY27: ¬ | EZ27: ¬ | FA27: ¬ | FB27: ¬ | FC27: ¬ | FD27: ¬ | FE27: ¬ | FF27: ¬ | FG27: ¬ | FH27: ¬ | FI27: ¬ | FJ27: ¬ | FK27: ¬ | FL27: ¬ | FM27: ¬ | FN27: ¬ | FO27: ¬ | FP27: ¬ | FQ27: ¬ | FR27: ¬ | FS27: 2 / 7 | FT27: □□■■■■■ | FU27: Contacts | FV27: Status | FW27: ¬ | FX27: ¬ | FY27: ¬ | FZ27: ¬ | GA27: ¬ | GB27: ¬ | GC27: ¬ | GD27: ¬ | GE27: ¬ | GF27: ¬ | GG27: ¬ | GH27: ¬ | GI27: ¬ | GJ27: ¬ | GK27: ¬ | GL27: ¬ | GM27: ¬ | GN27: ¬ | GO27: industry, politics, underworld, legal | GP27: media | GQ27: ¬ | GR27: ¬ | GS27: ¬ | GT27: ¬ | GU27: ¬ | GV27: ¬ | GW27: ¬ | GX27: ¬ | GY27: ¬ | GZ27: ¬ | HA27: ¬ | HB27: ¬ | HC27: ¬ | HD27: ¬ | HE27: ¬ | HF27: ¬ | HG27: ¬ | HH27: ¬ | HI27: ●●●● | HJ27: ●● | IC27: - | ID27: ●●● | IE27: ●●● | IF27: - | IG27: ● | IH27: - | II27: ● | IJ27: - | IK27: - | IL27: ● | IM27: - | IN27: - | IO27: - | IP27: - | IQ27: - | IR27: - | IS27: - | IT27: Auspex ● | Beast's Hackles | IU27: Auspex ●● | Uncanny Perception | IV27: Auspex ●●● | Spirit's Touch | IW27: Celerity ●●● | IX27: Majesty ● | Awe | IY27: Obfuscate ● | Face in the Crowd | IZ27: Vigour ● | JA27: Devotion | Turn of Phrase | JB27: Devotion | Quicken Sight | JC27: Devotion | Hold my Beer | JD27: ¬ | JE27: ¬ | JF27: ¬ | JG27: ¬ | JH27: ¬ | JI27: ¬ | JJ27: ¬ | JK27: ¬ | JL27: ¬ | JM27: ¬ | JN27: ¬ | JO27: ¬ | JP27: ¬ | JQ27: ¬ | JR27: ¬ | JS27: ¬ | JT27: ¬ | JU27: ¬ | JV27: ¬ | JW27: ¬ | JX27: Cost: Free (1 V for Insight) • Pool: - - Composure & Closed Book • Instant • Scene | JY27: Cost: Free (1 V for Insight) Must perceive target • Pool: - • Instant • Scene | JZ27: Cost: Free (1 WP for clash / 1 V for Insight) • Pool: - v Resolve + Stealth + Obf • Reflexive • Immediate | KA27: Cost: 1 V per effect • Pool: - • Reflexive • 1 turn | KB27: Cost: - • Pool: - • Instant • Scene | KC27: Cost: - • Pool: - • Instant • Scene | KD27: Cost: 1 V per effect • Pool: - • Reflexive • 1 turn | KE27: Cost: Free (Zelani Only) • Pool: - • Instant • Scene | KF27: Cost: 1 V • Pool: - • Reflexive • 1 turn | KG27: Cost: 1 WP (optional +1 V) (Zelani Only) • Pool: 8 • Reflexive • Scene | KH27: ¬ | KI27: ¬ | KJ27: ¬ | KK27: ¬ | KL27: ¬ | KM27: ¬ | KN27: ¬ | KO27: ¬ | KP27: ¬ | KQ27: ¬ | KR27: ¬ | KS27: ¬ | KT27: ¬ | KU27: ¬ | KV27: ¬ | KW27: ¬ | KX27: ¬ | KY27: ¬ | KZ27: ¬ | LA27: ¬ | LB27: Add Auspex dots to any rolls to resist surprise. Access to Tier 1 Auspex Insight questions. | LC27: Persistent Acute Senses Merit, doubles actual merit. Access to Tier 2 Auspex Insight questions. | LD27: Passively scan for anyone under Obfuscate 1 or 3, can provoke a challenge. Access to Tier 3 Auspex Insight questions. | LE27: Persistent improved Defence or Dodge. Activate for supernatural speed benefits. Unnatural Grace: add Celerity dots as bonus dice to non-combat speed-based pools. | LF27: Become centre of attention. Subjects become Awed. | LG27: Blend into surroundings, visible but unnoticeable. Predatory aura fully on or off. Leaving combat: Wits + Composure - Obfuscate to notice; auto Clash of Wills vs Auspex. | LH27: Improve Strength. Add Vigour dots as bonus successes only if at least one net success achieved. | LI27: Add Majesty dots to social pools for non-face-to-face communication (art, phone, letters, etc). | LJ27: Examine fast-moving details. Apply Defence to ranged attacks. Benefit from aiming instantly. | LK27: Distribute successes as dots among unskilled Skills (max 2 per Skill). +1 V: convert any Chance Die to a pool of 3 dice. | LL27: ¬ | LM27: ¬ | LN27: ¬ | LO27: ¬ | LP27: ¬ | LQ27: ¬ | LR27: ¬ | LS27: ¬ | LT27: ¬ | LU27: ¬ | LV27: ¬ | LW27: ¬ | LX27: ¬ | LY27: ¬ | LZ27: ¬ | MA27: ¬ | MB27: ¬ | MC27: ¬ | MD27: ¬ | ME27: ¬ | MF27: Wanton Curse | MG27: ¬ | MH27: ¬ | MI27: ¬ | MJ27: ¬ | MK27: Hungry at 5 or fewer Vitae, Starving at 3 or fewer. Dramatic Failures on feeding cause Persistent Dependent Condition toward a mortal NPC. | ML27: ¬ | MN27: ¬ | MO27: ¬ | MP27: 5 | MQ27: 10 | MR27: 5 | MS27: Put yourself out to help another succeed. | MT27: Take full responsibility for another's dangerous mistake. | MU27: Deny a compromise that would water down your ideal. | MV27: Refuse safety for fear of abandoning your ideal's purity. | MW27: ¬ | MX27: ¬ | MY27: ¬ | MZ27: late 20s
A28: tblCharDataReneSt | B28: 46104 | C28: 0 | D28: 34 | E28: Matt B | F28: René St. Dominique | G28: Dillitant | H28: he/him | I28: Ventrue | J28: D:\Terra Mortis\Character Sheets\Sheet Elements\Ventrue icon.svg | K28: Apollinaire | L28: Invictus | M28: D:\Terra Mortis\Character Sheets\Sheet Elements\Invictus icon.svg | N28: Courtesan | O28: Deviant | P28: Primogen | Q28: ●●● | R28: ●●● | S28: ●●● | T28: ●● | U28: ●●● | V28: ●○ | W28: ●●● | X28: ●● | Y28: ●● | AB28: ●●●● | AE28: ●●●●● | AF28: ● | AL28: ●● | AM28: ●● | AR28: ●●●●● | AS28: ●● | AT28: ●●● | AW28: ●●● | AX28: ●●○○○○○○○○○○○○○○○○ | AY28: 2 | AZ28: † | BA28: □□□□□□□■■■■■■■■ | BB28: 5 / 5 | BC28: □□□□□■■■■■ | BD28: 11 / 11 | BE28: □□□□□□□□□□□■■■■■■■■■ | BF28: 2 | BG28: Animals | BM28: A9A Voudun | BN28: Invictus lore | BZ28: A9A something | CB28: A9A something | CF28: 1 | CG28: 2 | CH28: 4 | CI28: Invictus | CJ28: ●●●● | CK28: Carthian | CL28: - | CM28: Crone | CN28: - | CO28: Lance | CP28: - | CQ28: ●●●●● | CR28: ● | CS28: - | CT28: ● | CU28: - | CW28: ●●●● | CX28: Voudun Priest | CY28: 5 | CZ28: ~ | DA28: ○ | DB28: ○ | DC28: ○ | DD28: ○ (Unnamed lawyer/clerk) | DE28: ○ | DF28: ● | DG28: ● | DH28: ● | DI28: ● | DJ28: ● | DK28: Attaché ● | DL28: Friends in High Places ● | DM28: Invested ● | DN28: Notary ●● | DO28: ¬ | DP28: ¬ | DQ28: ¬ | DR28: ¬ | DS28: ¬ | DT28: ¬ | DU28: ¬ | DV28: ¬ | DW28: ¬ | DX28: ¬ | DY28: ¬ | DZ28: ¬ | EA28: ¬ | EB28: ¬ | EC28: ¬ | ED28: ¬ | EE28: ¬ | EF28: ¬ | EG28: ¬ | EH28: ¬ | EI28: ¬ | EJ28: ¬ | EK28: ¬ | EL28: ¬ | EM28: ¬ | EN28: ¬ | EO28: Retainers gain your Invictus Status in dots of Contacts, Resources and Safe Place. | EP28: Once per chapter, use Invictus Status as Mortal Status in areas you don't possess. Drawback: Other Invictus may be informed. | EQ28: Distribute Invictus Status dots among free Herd, Mentor, Resources and Retainer. | ER28: Preside over Invictus Oaths. Invictus Status can't be used against you. Monthly, call one dot of Allies, Contacts, Herd, Mentor or Resources. | ES28: ¬ | ET28: ¬ | EU28: ¬ | EV28: ¬ | EW28: ¬ | EX28: ¬ | EY28: ¬ | EZ28: ¬ | FA28: ¬ | FB28: ¬ | FC28: ¬ | FD28: ¬ | FE28: ¬ | FF28: ¬ | FG28: ¬ | FH28: ¬ | FI28: ¬ | FJ28: ¬ | FK28: ¬ | FL28: ¬ | FM28: ¬ | FN28: ¬ | FO28: ¬ | FP28: ¬ | FQ28: ¬ | FR28: ¬ | FS28: 9 / 9 | FT28: □□□□□□□□□ | FU28: Allies | FV28: Contacts | FW28: Resources | FX28: Retainer | FY28: ¬ | FZ28: ¬ | GA28: ¬ | GB28: ¬ | GC28: ¬ | GD28: ¬ | GE28: ¬ | GF28: ¬ | GG28: ¬ | GH28: ¬ | GI28: ¬ | GJ28: ¬ | GK28: ¬ | GL28: ¬ | GM28: ¬ | GN28: ¬ | GO28: ¬ | GP28: ¬ | GQ28: ¬ | GR28: ¬ | GS28: ¬ | GT28: ¬ | GU28: ¬ | GV28: ¬ | GW28: ¬ | GX28: ¬ | GY28: ¬ | GZ28: ¬ | HA28: ¬ | HB28: ¬ | HC28: ¬ | HD28: ¬ | HE28: ¬ | HF28: ¬ | HG28: ¬ | HH28: ¬ | HI28: ● | HJ28: ●●● | HK28: ● | HL28: ●●●●● | IC28: - | ID28: - | IE28: - | IF28: ● | IG28: - | IH28: - | II28: ●●● | IJ28: - | IK28: ● | IL28: - | IM28: - | IN28: - | IO28: - | IP28: - | IQ28: - | IR28: - | IS28: - | IT28: Dominate ● | Mesmerise | IU28: Obfuscate ● | Face in the Crowd | IV28: Obfuscate ●● | Touch of Shadow | IW28: Obfuscate ●●● | Cloak of Night | IX28: Resilience ● | IY28: Devotion | Govi Trap | IZ28: Devotion | Skeleton Key | JA28: Devotion | Veve Passageway | JB28: Oath of the Hard Motherfucker ●● | JC28: ¬ | JD28: ¬ | JE28: ¬ | JF28: ¬ | JG28: ¬ | JH28: ¬ | JI28: ¬ | JJ28: ¬ | JK28: ¬ | JL28: ¬ | JM28: ¬ | JN28: ¬ | JO28: ¬ | JP28: ¬ | JQ28: ¬ | JR28: ¬ | JS28: ¬ | JT28: ¬ | JU28: ¬ | JV28: ¬ | JW28: ¬ | JX28: Cost: - -3 in combat unless Blinded • Pool: 9 v Resolve + BP • Instant • Instant | JY28: Cost: - • Pool: - • Instant • Scene | JZ28: Cost: 1 V • Pool: 8 • Instant • Scene | KA28: Cost: 1 V • Pool: - • None | KB28: Cost: 1 V per effect • Pool: - • Reflexive • 1 turn | KC28: Cost: 1 V (Apollinaire Only); ghost within sight; small container with lid • Pool: 7 v Finesse + Resistance • Contested • 1 hour per Dominate dot | KD28: Cost: 1 V (Apollinaire Only) • Pool: 6 • Instant • Instant / Permanent | KE28: Cost: 1 V (Apollinaire Only); white chalk • Pool: 10 • Instant • 1 hour per success | KF28: ¬ | KG28: ¬ | KH28: ¬ | KI28: ¬ | KJ28: ¬ | KK28: ¬ | KL28: ¬ | KM28: ¬ | KN28: ¬ | KO28: ¬ | KP28: ¬ | KQ28: ¬ | KR28: ¬ | KS28: ¬ | KT28: ¬ | KU28: ¬ | KV28: ¬ | KW28: ¬ | KX28: ¬ | KY28: ¬ | KZ28: ¬ | LA28: ¬ | LB28: Impose Mesmerised Condition. Control with short commands. | LC28: Blend into surroundings, visible but unnoticeable. Predatory aura fully on or off. Leaving combat: Wits + Composure - Obfuscate to notice; auto Clash of Wills vs Auspex. | LD28: Cast Face in the Crowd on object or person. Free and unlimited duration on carried/worn objects if not drawing attention. | LE28: Become invisible. Leaving combat: auto Clash of Wills vs Auspex 2. | LF28: Downgrade damage and increase Stamina. Improve Armour and Defences. Unnatural Fortitude: add Resilience dots as bonus dice to non-combat Stamina pools. | LG28: Compel a ghost to enter and remain in a govi (container). Released if lid removed or container broken. | LH28: Open any door regardless of locks/security without triggering alarms. Or lock any door until destroyed or Skeleton Key used again. +1 V prevents other Gatekeepers using Skeleton Key on it. | LI28: Draw a door on a wall. It becomes a real door opening to nearest room or empty space (up to 1 mile behind the drawing). | LJ28: Kill a Carthian or oathbreaker for Invictus Status 1, Friends in High Places 1, 9-Again on two Skills, and Allies/Contacts/Resources 1. All stripped if broken. | LK28: ¬ | LL28: ¬ | LM28: ¬ | LN28: ¬ | LO28: ¬ | LP28: ¬ | LQ28: ¬ | LR28: ¬ | LS28: ¬ | LT28: ¬ | LU28: ¬ | LV28: ¬ | LW28: ¬ | LX28: ¬ | LY28: ¬ | LZ28: ¬ | MA28: ¬ | MB28: ¬ | MC28: ¬ | MD28: ¬ | ME28: ¬ | MF28: Aloof Curse | MG28: ¬ | MH28: ¬ | MI28: ¬ | MJ28: ¬ | MK28: First Touchstone attaches to Humanity 7; losing it detaches on first Humanity loss. Breaking points always treated as one step lower. | ML28: ¬ | MN28: ¬ | MO28: ¬ | MP28: 5 | MQ28: 10 | MR28: 3 | MS28: Put yourself out for another's pleasure. | MT28: Be the last one dancing when the party is on fire. | MU28: Commit a crime against your recognised society. | MV28: Commit a high crime in plain view of an authority. | MW28: ¬ | MX28: ¬ | MY28: ¬
A29: tblCharDataRyan | B29: 46104 | C29: 1 | D29: 16 | E29: Patrick T | F29: Ryan Ambrose | G29: Ruthless Rising Star | H29: ¬ | I29: Gangrel | J29: D:\Terra Mortis\Character Sheets\Sheet Elements\Gangrel icon.svg | K29: ¬ | L29: Invictus | M29: D:\Terra Mortis\Character Sheets\Sheet Elements\Invictus icon.svg | N29: Competitor | O29: Follower | P29: ¬ | Q29: ● | R29: ●●● | S29: ●●● | T29: ●●●● | U29: ●● | V29: ●●○ | W29: ●●● | X29: ●● | Y29: ●●● | AA29: ●● | AC29: ● | AF29: ● | AH29: ●●● | AI29: ●●● | AJ29: ● | AK29: ● | AR29: ●● | AS29: ●●● | AT29: ● | AU29: ●● | AV29: ●●● | AX29: ●○○○○○○○○○○○○○○○○○○ | AY29: 1 | BA29: □□□□□□□□■■■■■■■ | BB29: 6 / 6 | BC29: □□□□□□■■■■ | BD29: 10 / 10 | BE29: □□□□□□□□□□■■■■■■■■■■ | BF29: 1 | BG29: Animals | BR29: speeding | CA29: veiled threats | CD29: Navigation | CF29: 1 | CG29: 2 | CH29: 0 | CI29: Invictus | CK29: Carthian | CL29: - | CM29: Crone | CN29: - | CO29: Lance | CP29: - | CQ29: ● | CR29: ● | CS29: - | CT29: - | CU29: - | CW29: - | CY29: 7 | CZ29: ~ | DA29: ○ | DB29: ○ | DC29: ○ | DD29: ● | DE29: ● | DF29: ● | DG29: ● | DH29: ● | DI29: ● | DJ29: ● | DK29: Riding the Wave ● | Ravage | DL29: Riding the Wave ●● | Primal Strength | DM29: Riding the Wave ●●● | In the Zone | DN29: ¬ | DO29: ¬ | DP29: ¬ | DQ29: ¬ | DR29: ¬ | DS29: ¬ | DT29: ¬ | DU29: ¬ | DV29: ¬ | DW29: ¬ | DX29: ¬ | DY29: ¬ | DZ29: ¬ | EA29: ¬ | EB29: ¬ | EC29: ¬ | ED29: ¬ | EE29: ¬ | EF29: ¬ | EG29: ¬ | EH29: ¬ | EI29: ¬ | EJ29: ¬ | EK29: ¬ | EL29: ¬ | EM29: ¬ | EN29: ¬ | EO29: Bite attacks take a 1L weapon rating. | EP29: Double your Strength bonus from frenzy when lifting, jumping, or destroying objects. | EQ29: When you spend Willpower to ride the wave, you also apply the normal +3 action bonus. | ER29: ¬ | ES29: ¬ | ET29: ¬ | EU29: ¬ | EV29: ¬ | EW29: ¬ | EX29: ¬ | EY29: ¬ | EZ29: ¬ | FA29: ¬ | FB29: ¬ | FC29: ¬ | FD29: ¬ | FE29: ¬ | FF29: ¬ | FG29: ¬ | FH29: ¬ | FI29: ¬ | FJ29: ¬ | FK29: ¬ | FL29: ¬ | FM29: ¬ | FN29: ¬ | FO29: ¬ | FP29: ¬ | FQ29: ¬ | FR29: ¬ | FS29: 2 / 2 | FT29: □□ | FU29: Resources | FV29: Staff | FW29: ¬ | FX29: ¬ | FY29: ¬ | FZ29: ¬ | GA29: ¬ | GB29: ¬ | GC29: ¬ | GD29: ¬ | GE29: ¬ | GF29: ¬ | GG29: ¬ | GH29: ¬ | GI29: ¬ | GJ29: ¬ | GK29: ¬ | GL29: ¬ | GM29: ¬ | GN29: ¬ | GO29: ¬ | GP29: Larceny | GQ29: ¬ | GR29: ¬ | GS29: ¬ | GT29: ¬ | GU29: ¬ | GV29: ¬ | GW29: ¬ | GX29: ¬ | GY29: ¬ | GZ29: ¬ | HA29: ¬ | HB29: ¬ | HC29: ¬ | HD29: ¬ | HE29: ¬ | HF29: ¬ | HG29: ¬ | HH29: ¬ | HI29: ● | HJ29: ● | IC29: - | ID29: - | IE29: - | IF29: - | IG29: - | IH29: - | II29: - | IJ29: ●●● | IK29: ● | IL29: - | IM29: - | IN29: - | IO29: - | IP29: - | IQ29: - | IR29: - | IS29: - | IT29: Protean ● | Unmarked Grave | IU29: Protean ●● | Predatory Aspect | IV29: Protean ●●● | Beast's Skin | IW29: Resilience ● | IX29: Oath of the Hard Motherfucker ●● | IY29: ¬ | IZ29: ¬ | JA29: ¬ | JB29: ¬ | JC29: ¬ | JD29: ¬ | JE29: ¬ | JF29: ¬ | JG29: ¬ | JH29: ¬ | JI29: ¬ | JJ29: ¬ | JK29: ¬ | JL29: ¬ | JM29: ¬ | JN29: ¬ | JO29: ¬ | JP29: ¬ | JQ29: ¬ | JR29: ¬ | JS29: ¬ | JT29: ¬ | JU29: ¬ | JV29: ¬ | JW29: ¬ | JX29: Cost: Varies • Pool: - • Instant • Indefinite | JY29: Cost: 1 V • Pool: - • Instant • Scene | JZ29: Cost: 2 V • Pool: - • Instant • Indefinite | KA29: Cost: 1 V per effect • Pool: - • Reflexive • 1 turn | KB29: ¬ | KC29: ¬ | KD29: ¬ | KE29: ¬ | KF29: ¬ | KG29: ¬ | KH29: ¬ | KI29: ¬ | KJ29: ¬ | KK29: ¬ | KL29: ¬ | KM29: ¬ | KN29: ¬ | KO29: ¬ | KP29: ¬ | KQ29: ¬ | KR29: ¬ | KS29: ¬ | KT29: ¬ | KU29: ¬ | KV29: ¬ | KW29: ¬ | KX29: ¬ | KY29: ¬ | KZ29: ¬ | LA29: ¬ | LB29: Merge with soil. | LC29: Take on animal traits. | LD29: Transform into predatory animal. | LE29: Downgrade damage and increase Stamina. Improve Armour and Defences. Unnatural Fortitude: add Resilience dots as bonus dice to non-combat Stamina pools. | LF29: Kill a Carthian or oathbreaker for Invictus Status 1, Friends in High Places 1, 9-Again on two Skills, and Allies/Contacts/Resources 1. All stripped if broken. | LG29: ¬ | LH29: ¬ | LI29: ¬ | LJ29: ¬ | LK29: ¬ | LL29: ¬ | LM29: ¬ | LN29: ¬ | LO29: ¬ | LP29: ¬ | LQ29: ¬ | LR29: ¬ | LS29: ¬ | LT29: ¬ | LU29: ¬ | LV29: ¬ | LW29: ¬ | LX29: ¬ | LY29: ¬ | LZ29: ¬ | MA29: ¬ | MB29: ¬ | MC29: ¬ | MD29: ¬ | ME29: ¬ | MF29: Feral Curse | MG29: ¬ | MH29: ¬ | MI29: ¬ | MJ29: ¬ | MK29: Frenzy resistance dice pools capped by Humanity (doesn't affect Riding the Wave). | ML29: ¬ | MN29: ¬ | MO29: ¬ | MP29: 5 | MQ29: 11 | MR29: 5 | MS29: Challenge someone clearly your superior. | MT29: Risk Final Death to prove you can handle something. | MU29: Follow a directive blindly, for the sake of following. | MV29: Follow a dangerous directive without hesitation. | MW29: ¬ | MX29: ¬ | MY29: ¬
A30: tblCharDataTegan | B30: 46104 | C30: 4 | D30: 42 | E30: Alana W | F30: Tegan Groves | G30: ¬ | H30: she/her | I30: Gangrel | J30: D:\Terra Mortis\Character Sheets\Sheet Elements\Gangrel icon.svg | K30: ¬ | L30: Lancea et Sanctum | M30: D:\Terra Mortis\Character Sheets\Sheet Elements\Lance icon.svg | N30: Nurturer | O30: Survivor | P30: ¬ | Q30: ● | R30: ●●● | S30: ●●● | T30: ●●● | U30: ●● | V30: ●●●●○○ | W30: ●● | X30: ●●● | Y30: ●●● | AA30: ● | AB30: ● | AC30: ●● | AH30: ● | AI30: ●● | AJ30: ● | AM30: ● | AN30: ●● | AP30: ●● | AQ30: ● | AR30: ●● | AT30: ●●● | AU30: ● | AV30: ● | AW30: ●● | AX30: ●○○○○○○○○○○○○○○○○○○ | AY30: 1 | BA30: □□□□□□□□□□□■■■■ | BB30: 6 / 6 | BC30: □□□□□□■■■■ | BD30: 10 / 10 | BE30: □□□□□□□□□□■■■■■■■■■■ | BF30: 1 | BG30: Animals | CF30: 3 | CG30: 2 | CH30: 1 | CI30: Lance | CJ30: ● | CK30: Carthian | CL30: - | CM30: Crone | CN30: - | CO30: Invictus | CP30: - | CQ30: ● | CR30: ● | CS30: - | CT30: - | CU30: - | CW30: - | CY30: 6 | CZ30: ~ | DA30: ○ | DB30: ○ | DC30: ○ | DD30: ○ | DE30: ● (Sister Tahliah) | DF30: ● (Old Pine Log) | DG30: ● | DH30: ● | DI30: ● | DJ30: ● | DK30: Indomitable ●● | DL30: Iron Stamina ●● | DM30: Language (Hindi) ● | DN30: Pusher ● | DO30: ¬ | DP30: ¬ | DQ30: ¬ | DR30: ¬ | DS30: ¬ | DT30: ¬ | DU30: ¬ | DV30: ¬ | DW30: ¬ | DX30: ¬ | DY30: ¬ | DZ30: ¬ | EA30: ¬ | EB30: ¬ | EC30: ¬ | ED30: ¬ | EE30: ¬ | EF30: ¬ | EG30: ¬ | EH30: ¬ | EI30: ¬ | EJ30: ¬ | EK30: ¬ | EL30: ¬ | EM30: ¬ | EN30: ¬ | EO30: +2 to contest or resist supernatural mental influence. | EP30: Ignore fatigue or wound penalties up to dots. | EQ30: Speak, read and write a chosen language. | ER30: When you use soft leverage, improve your impression as if you'd also satisfied the mark's Vice. | ES30: ¬ | ET30: ¬ | EU30: ¬ | EV30: ¬ | EW30: ¬ | EX30: ¬ | EY30: ¬ | EZ30: ¬ | FA30: ¬ | FB30: ¬ | FC30: ¬ | FD30: ¬ | FE30: ¬ | FF30: ¬ | FG30: ¬ | FH30: ¬ | FI30: ¬ | FJ30: ¬ | FK30: ¬ | FL30: ¬ | FM30: ¬ | FN30: ¬ | FO30: ¬ | FP30: ¬ | FQ30: ¬ | FR30: ¬ | FS30: 4 / 4 | FT30: □□□□ | FU30: Allies | FV30: ¬ | FW30: ¬ | FX30: ¬ | FY30: ¬ | FZ30: ¬ | GA30: ¬ | GB30: ¬ | GC30: ¬ | GD30: ¬ | GE30: ¬ | GF30: ¬ | GG30: ¬ | GH30: ¬ | GI30: ¬ | GJ30: ¬ | GK30: ¬ | GL30: ¬ | GM30: ¬ | GN30: ¬ | GO30: transportation | GP30: ¬ | GQ30: ¬ | GR30: ¬ | GS30: ¬ | GT30: ¬ | GU30: ¬ | GV30: ¬ | GW30: ¬ | GX30: ¬ | GY30: ¬ | GZ30: ¬ | HA30: ¬ | HB30: ¬ | HC30: ¬ | HD30: ¬ | HE30: ¬ | HF30: ¬ | HG30: ¬ | HH30: ¬ | HI30: ●●● | IC30: ● | ID30: - | IE30: - | IF30: - | IG30: - | IH30: - | II30: - | IJ30: ●● | IK30: ●● | IL30: - | IM30: - | IN30: - | IO30: - | IP30: - | IQ30: - | IR30: - | IS30: - | IT30: Animalism ● | Feral Whispers | IU30: Protean ● | Unmarked Grave | IV30: Protean ●● | Predatory Aspect | IW30: Resilience ●● | IX30: ¬ | IY30: ¬ | IZ30: ¬ | JA30: ¬ | JB30: ¬ | JC30: ¬ | JD30: ¬ | JE30: ¬ | JF30: ¬ | JG30: ¬ | JH30: ¬ | JI30: ¬ | JJ30: ¬ | JK30: ¬ | JL30: ¬ | JM30: ¬ | JN30: ¬ | JO30: ¬ | JP30: ¬ | JQ30: ¬ | JR30: ¬ | JS30: ¬ | JT30: ¬ | JU30: ¬ | JV30: ¬ | JW30: ¬ | JX30: Cost: - • Pool: 6 • Instant • Scene (may persist) | JY30: Cost: Varies • Pool: - • Instant • Indefinite | JZ30: Cost: 1 V • Pool: - • Instant • Scene | KA30: Cost: 1 V per effect • Pool: - • Reflexive • 1 turn | KB30: ¬ | KC30: ¬ | KD30: ¬ | KE30: ¬ | KF30: ¬ | KG30: ¬ | KH30: ¬ | KI30: ¬ | KJ30: ¬ | KK30: ¬ | KL30: ¬ | KM30: ¬ | KN30: ¬ | KO30: ¬ | KP30: ¬ | KQ30: ¬ | KR30: ¬ | KS30: ¬ | KT30: ¬ | KU30: ¬ | KV30: ¬ | KW30: ¬ | KX30: ¬ | KY30: ¬ | KZ30: ¬ | LA30: ¬ | LB30: Speak with and command animals. | LC30: Merge with soil. | LD30: Take on animal traits. | LE30: Downgrade damage and increase Stamina. Improve Armour and Defences. Unnatural Fortitude: add Resilience dots as bonus dice to non-combat Stamina pools. | LF30: ¬ | LG30: ¬ | LH30: ¬ | LI30: ¬ | LJ30: ¬ | LK30: ¬ | LL30: ¬ | LM30: ¬ | LN30: ¬ | LO30: ¬ | LP30: ¬ | LQ30: ¬ | LR30: ¬ | LS30: ¬ | LT30: ¬ | LU30: ¬ | LV30: ¬ | LW30: ¬ | LX30: ¬ | LY30: ¬ | LZ30: ¬ | MA30: ¬ | MB30: ¬ | MC30: ¬ | MD30: ¬ | ME30: ¬ | MF30: Feral Curse | MG30: ¬ | MH30: ¬ | MI30: ¬ | MJ30: ¬ | MK30: Frenzy resistance dice pools capped by Humanity (doesn't affect Riding the Wave). | ML30: ¬ | MN30: ¬ | MO30: ¬ | MP30: 5 | MQ30: 10 | MR30: 3 | MS30: Put yourself out to help another succeed. | MT30: Take full responsibility for another's dangerous mistake. | MU30: Favour the safe path over the higher risk, higher reward path. | MV30: Abandon a social group or relationship in order to stay safe. | MW30: ¬ | MX30: ¬ | MY30: ¬ | MZ30: mid 20s
A31: tblCharDataWan | B31: 46104 | C31: 0 | D31: 20 | E31: Michael V | F31: Wan Yelong | G31: Handler | H31: he/him | I31: Mekhet | J31: D:\Terra Mortis\Character Sheets\Sheet Elements\Mekhet icon.svg | K31: ¬ | L31: Invictus | M31: D:\Terra Mortis\Character Sheets\Sheet Elements\Invictus icon.svg | N31: Scholar | O31: Spy | P31: ¬ | Q31: ●●● | R31: ●●● | S31: ●●● | T31: ●● | U31: ●●● | V31: ● | W31: ●●● | X31: ●●● | Y31: ● | Z31: ●●† | AA31: ● | AC31: ●● | AE31: ●●●●○† | AF31: ●●† | AH31: ● | AM31: ●●● | AQ31: ●●● | AU31: ● | AW31: ●●● | AX31: ●○○○○○○○○○○○○○○○○○○ | AY31: 1 | BA31: □□□□□□■■■■■■■■■ | BB31: 4 / 4 | BC31: □□□□■■■■■■ | BD31: 10 / 10 | BE31: □□□□□□□□□□■■■■■■■■■■ | BF31: 1 | BG31: Animals | BH31: history | BM31: symbolism, societies | BN31: fine arts, diplomacy | CF31: 2 | CG31: 1 | CH31: 2 | CI31: Invictus | CJ31: ●● | CK31: Carthian | CL31: - | CM31: Crone | CN31: - | CO31: Lance | CP31: - | CQ31: ● | CR31: - | CS31: - | CT31: - | CU31: - | CW31: ●●●●● | CX31: Diplomatic Attache | CY31: 6 | CZ31: ~ | DA31: ○ | DB31: ○ | DC31: ○ | DD31: ○ | DE31: ● (Unnamed staffer/academic) | DF31: ● | DG31: ● | DH31: ● | DI31: ● | DJ31: ● | DK31: Encyclopaedic Knowledge ● | DL31: Friends in High Places ● | DM31: Indomitable ●● | DN31: Multilingual (Mandarin, Mongolian) ● | DO31: ¬ | DP31: ¬ | DQ31: ¬ | DR31: ¬ | DS31: ¬ | DT31: ¬ | DU31: ¬ | DV31: ¬ | DW31: ¬ | DX31: ¬ | DY31: ¬ | DZ31: ¬ | EA31: ¬ | EB31: ¬ | EC31: ¬ | ED31: ¬ | EE31: ¬ | EF31: ¬ | EG31: ¬ | EH31: ¬ | EI31: ¬ | EJ31: ¬ | EK31: ¬ | EL31: ¬ | EM31: ¬ | EN31: ¬ | EO31: Roll Intelligence + Wits to recall trivia about a chosen field. | EP31: Once per chapter, use Invictus Status as Mortal Status in areas you don't possess. Drawback: Other Invictus may be informed. | EQ31: +2 to contest or resist supernatural mental influence. | ER31: Speak two chosen languages conversationally. Intelligence + Academics to read. | ES31: ¬ | ET31: ¬ | EU31: ¬ | EV31: ¬ | EW31: ¬ | EX31: ¬ | EY31: ¬ | EZ31: ¬ | FA31: ¬ | FB31: ¬ | FC31: ¬ | FD31: ¬ | FE31: ¬ | FF31: ¬ | FG31: ¬ | FH31: ¬ | FI31: ¬ | FJ31: ¬ | FK31: ¬ | FL31: ¬ | FM31: ¬ | FN31: ¬ | FO31: ¬ | FP31: ¬ | FQ31: ¬ | FR31: ¬ | FS31: 3 / 3 | FT31: □□□ | FU31: Contacts | FV31: Resources | FW31: Status | FX31: ¬ | FY31: ¬ | FZ31: ¬ | GA31: ¬ | GB31: ¬ | GC31: ¬ | GD31: ¬ | GE31: ¬ | GF31: ¬ | GG31: ¬ | GH31: ¬ | GI31: ¬ | GJ31: ¬ | GK31: ¬ | GL31: ¬ | GM31: ¬ | GN31: ¬ | GO31: high society, politics | GP31: ¬ | GQ31: Academia | GR31: ¬ | GS31: ¬ | GT31: ¬ | GU31: ¬ | GV31: ¬ | GW31: ¬ | GX31: ¬ | GY31: ¬ | GZ31: ¬ | HA31: ¬ | HB31: ¬ | HC31: ¬ | HD31: ¬ | HE31: ¬ | HF31: ¬ | HG31: ¬ | HH31: ¬ | HI31: ●● | HJ31: ● | HK31: ● | IC31: - | ID31: ●● | IE31: - | IF31: - | IG31: - | IH31: - | II31: ●●●●● | IJ31: - | IK31: - | IL31: - | IM31: - | IN31: - | IO31: - | IP31: - | IQ31: - | IR31: - | IS31: - | IT31: Auspex ● | Beast's Hackles | IU31: Auspex ●● | Uncanny Perception | IV31: Obfuscate ● | Face in the Crowd | IW31: Obfuscate ●● | Touch of Shadow | IX31: Obfuscate ●●● | Cloak of Night | IY31: Obfuscate ●●●● | The Familiar Stranger | IZ31: Obfuscate ●●●●● | Oubliette | JA31: ¬ | JB31: ¬ | JC31: ¬ | JD31: ¬ | JE31: ¬ | JF31: ¬ | JG31: ¬ | JH31: ¬ | JI31: ¬ | JJ31: ¬ | JK31: ¬ | JL31: ¬ | JM31: ¬ | JN31: ¬ | JO31: ¬ | JP31: ¬ | JQ31: ¬ | JR31: ¬ | JS31: ¬ | JT31: ¬ | JU31: ¬ | JV31: ¬ | JW31: ¬ | JX31: Cost: Free (1 V for Insight) • Pool: - - Composure & Closed Book • Instant • Scene | JY31: Cost: Free (1 V for Insight) Must perceive target • Pool: - • Instant • Scene | JZ31: Cost: - • Pool: - • Instant • Scene | KA31: Cost: 1 V • Pool: 7 • Instant • Scene | KB31: Cost: 1 V • Pool: - • None | KC31: Cost: 2 V • Pool: - • None | KD31: Cost: Free (Haven) / 3-9 V & 1 WP • Pool: - • Instant • 1 week per BP | KE31: ¬ | KF31: ¬ | KG31: ¬ | KH31: ¬ | KI31: ¬ | KJ31: ¬ | KK31: ¬ | KL31: ¬ | KM31: ¬ | KN31: ¬ | KO31: ¬ | KP31: ¬ | KQ31: ¬ | KR31: ¬ | KS31: ¬ | KT31: ¬ | KU31: ¬ | KV31: ¬ | KW31: ¬ | KX31: ¬ | KY31: ¬ | KZ31: ¬ | LA31: ¬ | LB31: Add Auspex dots to any rolls to resist surprise. Access to Tier 1 Auspex Insight questions. | LC31: Persistent Acute Senses Merit, doubles actual merit. Access to Tier 2 Auspex Insight questions. | LD31: Blend into surroundings, visible but unnoticeable. Predatory aura fully on or off. Leaving combat: Wits + Composure - Obfuscate to notice; auto Clash of Wills vs Auspex. | LE31: Cast Face in the Crowd on object or person. Free and unlimited duration on carried/worn objects if not drawing attention. | LF31: Become invisible. Leaving combat: auto Clash of Wills vs Auspex 2. | LG31: Disguise self or other as a desired person. Free unlimited duration to reskin carried/worn objects, but no equipment bonus without Vitae. | LH31: Always active on Haven/Safe Place at no cost. Further uses at standard cost. Use Obfuscate at distance on anything in area. | LI31: ¬ | LJ31: ¬ | LK31: ¬ | LL31: ¬ | LM31: ¬ | LN31: ¬ | LO31: ¬ | LP31: ¬ | LQ31: ¬ | LR31: ¬ | LS31: ¬ | LT31: ¬ | LU31: ¬ | LV31: ¬ | LW31: ¬ | LX31: ¬ | LY31: ¬ | LZ31: ¬ | MA31: ¬ | MB31: ¬ | MC31: ¬ | MD31: ¬ | ME31: ¬ | MF31: Tenebrous Curse | MG31: ¬ | MH31: ¬ | MI31: ¬ | MJ31: ¬ | MK31: Gain an extra bane at Humanity 6 (doesn't count towards cap); Humanity counts –1 for all Humanity-based banes. | ML31: ¬ | MN31: ¬ | MO31: ¬ | MP31: 5 | MQ31: 10 | MR31: 4 | MS31: Uncover a lost piece of information. | MT31: Uncover forbidden knowledge. | MU31: Build a new identity or uncover a secret. | MV31: Uncover a damning secret that could end someone. | MW31: ¬ | MX31: ¬ | MY31: ¬

Sheet Attendance
A1: Daeva | B1: {=SUMPRODUCT( (tblCharacterCapture[Clan]=A1) * tblCharacterCapture[City Status] )} -> 8 | C1: Daeva | E1: {=SUMPRODUCT( (ISNUMBER(E$14:E$103))*(E$14:E$103>0) * (IFERROR(VLOOKUP($C$14:$C$103,tblCharacterCapture[[Character Name]:[Clan]],4,0),"")=$A1) * IFERROR(VLOOKUP($C$14:$C$103,tblCharacterCapture[[Character Name]:[City Status]],79,0),0) )} -> 7 | J1: {=SUMPRODUCT( (ISNUMBER(J$14:J$103))*(J$14:J$103>0) * (IFERROR(VLOOKUP($C$14:$C$103,tblCharacterCapture[[Character Name]:[Clan]],4,0),"")=$A1) * IFERROR(VLOOKUP($C$14:$C$103,tblCharacterCapture[[Character Name]:[City Status]],79,0),0) )} -> 0 | O1: {=SUMPRODUCT( (ISNUMBER(O$14:O$103))*(O$14:O$103>0) * (IFERROR(VLOOKUP($C$14:$C$103,tblCharacterCapture[[Character Name]:[Clan]],4,0),"")=$A1) * IFERROR(VLOOKUP($C$14:$C$103,tblCharacterCapture[[Character Name]:[City Status]],79,0),0) )} -> 0 | T1: {=SUMPRODUCT( (ISNUMBER(T$14:T$103))*(T$14:T$103>0) * (IFERROR(VLOOKUP($C$14:$C$103,tblCharacterCapture[[Character Name]:[Clan]],4,0),"")=$A1) * IFERROR(VLOOKUP($C$14:$C$103,tblCharacterCapture[[Character Name]:[City Status]],79,0),0) )} -> 0 | Y1: {=SUMPRODUCT( (ISNUMBER(Y$14:Y$103))*(Y$14:Y$103>0) * (IFERROR(VLOOKUP($C$14:$C$103,tblCharacterCapture[[Character Name]:[Clan]],4,0),"")=$A1) * IFERROR(VLOOKUP($C$14:$C$103,tblCharacterCapture[[Character Name]:[City Status]],79,0),0) )} -> 0 | AD1: {=SUMPRODUCT( (ISNUMBER(AD$14:AD$103))*(AD$14:AD$103>0) * (IFERROR(VLOOKUP($C$14:$C$103,tblCharacterCapture[[Character Name]:[Clan]],4,0),"")=$A1) * IFERROR(VLOOKUP($C$14:$C$103,tblCharacterCapture[[Character Name]:[City Status]],79,0),0) )} -> 0 | AI1: {=SUMPRODUCT( (ISNUMBER(AI$14:AI$103))*(AI$14:AI$103>0) * (IFERROR(VLOOKUP($C$14:$C$103,tblCharacterCapture[[Character Name]:[Clan]],4,0),"")=$A1) * IFERROR(VLOOKUP($C$14:$C$103,tblCharacterCapture[[Character Name]:[City Status]],79,0),0) )} -> 0 | AN1: {=SUMPRODUCT( (ISNUMBER(AN$14:AN$103))*(AN$14:AN$103>0) * (IFERROR(VLOOKUP($C$14:$C$103,tblCharacterCapture[[Character Name]:[Clan]],4,0),"")=$A1) * IFERROR(VLOOKUP($C$14:$C$103,tblCharacterCapture[[Character Name]:[City Status]],79,0),0) )} -> 0 | AS1: {=SUMPRODUCT( (ISNUMBER(AS$14:AS$103))*(AS$14:AS$103>0) * (IFERROR(VLOOKUP($C$14:$C$103,tblCharacterCapture[[Character Name]:[Clan]],4,0),"")=$A1) * IFERROR(VLOOKUP($C$14:$C$103,tblCharacterCapture[[Character Name]:[City Status]],79,0),0) )} -> 0 | AX1: {=SUMPRODUCT( (ISNUMBER(AX$14:AX$103))*(AX$14:AX$103>0) * (IFERROR(VLOOKUP($C$14:$C$103,tblCharacterCapture[[Character Name]:[Clan]],4,0),"")=$A1) * IFERROR(VLOOKUP($C$14:$C$103,tblCharacterCapture[[Character Name]:[City Status]],79,0),0) )} -> 0 | BC1: {=SUMPRODUCT( (ISNUMBER(BC$14:BC$103))*(BC$14:BC$103>0) * (IFERROR(VLOOKUP($C$14:$C$103,tblCharacterCapture[[Character Name]:[Clan]],4,0),"")=$A1) * IFERROR(VLOOKUP($C$14:$C$103,tblCharacterCapture[[Character Name]:[City Status]],79,0),0) )} -> 0 | BH1: {=SUMPRODUCT( (ISNUMBER(BH$14:BH$103))*(BH$14:BH$103>0) * (IFERROR(VLOOKUP($C$14:$C$103,tblCharacterCapture[[Character Name]:[Clan]],4,0),"")=$A1) * IFERROR(VLOOKUP($C$14:$C$103,tblCharacterCapture[[Character Name]:[City Status]],79,0),0) )} -> 0 | BM1: {=SUMPRODUCT( (ISNUMBER(BM$14:BM$103))*(BM$14:BM$103>0) * (IFERROR(VLOOKUP($C$14:$C$103,tblCharacterCapture[[Character Name]:[Clan]],4,0),"")=$A1) * IFERROR(VLOOKUP($C$14:$C$103,tblCharacterCapture[[Character Name]:[City Status]],79,0),0) )} -> 0 | BR1: {=SUMPRODUCT( (ISNUMBER(BR$14:BR$103))*(BR$14:BR$103>0) * (IFERROR(VLOOKUP($C$14:$C$103,tblCharacterCapture[[Character Name]:[Clan]],4,0),"")=$A1) * IFERROR(VLOOKUP($C$14:$C$103,tblCharacterCapture[[Character Name]:[City Status]],79,0),0) )} -> 0 | BW1: {=SUMPRODUCT( (ISNUMBER(BW$14:BW$103))*(BW$14:BW$103>0) * (IFERROR(VLOOKUP($C$14:$C$103,tblCharacterCapture[[Character Name]:[Clan]],4,0),"")=$A1) * IFERROR(VLOOKUP($C$14:$C$103,tblCharacterCapture[[Character Name]:[City Status]],79,0),0) )} -> 0 | CB1: {=SUMPRODUCT( (ISNUMBER(CB$14:CB$103))*(CB$14:CB$103>0) * (IFERROR(VLOOKUP($C$14:$C$103,tblCharacterCapture[[Character Name]:[Clan]],4,0),"")=$A1) * IFERROR(VLOOKUP($C$14:$C$103,tblCharacterCapture[[Character Name]:[City Status]],79,0),0) )} -> 0 | CG1: {=SUMPRODUCT( (ISNUMBER(CG$14:CG$103))*(CG$14:CG$103>0) * (IFERROR(VLOOKUP($C$14:$C$103,tblCharacterCapture[[Character Name]:[Clan]],4,0),"")=$A1) * IFERROR(VLOOKUP($C$14:$C$103,tblCharacterCapture[[Character Name]:[City Status]],79,0),0) )} -> 0 | CL1: {=SUMPRODUCT( (ISNUMBER(CL$14:CL$103))*(CL$14:CL$103>0) * (IFERROR(VLOOKUP($C$14:$C$103,tblCharacterCapture[[Character Name]:[Clan]],4,0),"")=$A1) * IFERROR(VLOOKUP($C$14:$C$103,tblCharacterCapture[[Character Name]:[City Status]],79,0),0) )} -> 0 | CQ1: {=SUMPRODUCT( (ISNUMBER(CQ$14:CQ$103))*(CQ$14:CQ$103>0) * (IFERROR(VLOOKUP($C$14:$C$103,tblCharacterCapture[[Character Name]:[Clan]],4,0),"")=$A1) * IFERROR(VLOOKUP($C$14:$C$103,tblCharacterCapture[[Character Name]:[City Status]],79,0),0) )} -> 0 | CV1: {=SUMPRODUCT( (ISNUMBER(CV$14:CV$103))*(CV$14:CV$103>0) * (IFERROR(VLOOKUP($C$14:$C$103,tblCharacterCapture[[Character Name]:[Clan]],4,0),"")=$A1) * IFERROR(VLOOKUP($C$14:$C$103,tblCharacterCapture[[Character Name]:[City Status]],79,0),0) )} -> 0 | DA1: {=SUMPRODUCT( (ISNUMBER(DA$14:DA$103))*(DA$14:DA$103>0) * (IFERROR(VLOOKUP($C$14:$C$103,tblCharacterCapture[[Character Name]:[Clan]],4,0),"")=$A1) * IFERROR(VLOOKUP($C$14:$C$103,tblCharacterCapture[[Character Name]:[City Status]],79,0),0) )} -> 0 | DF1: {=SUMPRODUCT( (ISNUMBER(DF$14:DF$103))*(DF$14:DF$103>0) * (IFERROR(VLOOKUP($C$14:$C$103,tblCharacterCapture[[Character Name]:[Clan]],4,0),"")=$A1) * IFERROR(VLOOKUP($C$14:$C$103,tblCharacterCapture[[Character Name]:[City Status]],79,0),0) )} -> 0 | DK1: {=SUMPRODUCT( (ISNUMBER(DK$14:DK$103))*(DK$14:DK$103>0) * (IFERROR(VLOOKUP($C$14:$C$103,tblCharacterCapture[[Character Name]:[Clan]],4,0),"")=$A1) * IFERROR(VLOOKUP($C$14:$C$103,tblCharacterCapture[[Character Name]:[City Status]],79,0),0) )} -> 0 | DP1: {=SUMPRODUCT( (ISNUMBER(DP$14:DP$103))*(DP$14:DP$103>0) * (IFERROR(VLOOKUP($C$14:$C$103,tblCharacterCapture[[Character Name]:[Clan]],4,0),"")=$A1) * IFERROR(VLOOKUP($C$14:$C$103,tblCharacterCapture[[Character Name]:[City Status]],79,0),0) )} -> 0 | DU1: {=SUMPRODUCT( (ISNUMBER(DU$14:DU$103))*(DU$14:DU$103>0) * (IFERROR(VLOOKUP($C$14:$C$103,tblCharacterCapture[[Character Name]:[Clan]],4,0),"")=$A1) * IFERROR(VLOOKUP($C$14:$C$103,tblCharacterCapture[[Character Name]:[City Status]],79,0),0) )} -> 0 | DZ1: {=SUMPRODUCT( (ISNUMBER(DZ$14:DZ$103))*(DZ$14:DZ$103>0) * (IFERROR(VLOOKUP($C$14:$C$103,tblCharacterCapture[[Character Name]:[Clan]],4,0),"")=$A1) * IFERROR(VLOOKUP($C$14:$C$103,tblCharacterCapture[[Character Name]:[City Status]],79,0),0) )} -> 0 | EE1: {=SUMPRODUCT( (ISNUMBER(EE$14:EE$103))*(EE$14:EE$103>0) * (IFERROR(VLOOKUP($C$14:$C$103,tblCharacterCapture[[Character Name]:[Clan]],4,0),"")=$A1) * IFERROR(VLOOKUP($C$14:$C$103,tblCharacterCapture[[Character Name]:[City Status]],79,0),0) )} -> 0 | EJ1: {=SUMPRODUCT( (ISNUMBER(EJ$14:EJ$103))*(EJ$14:EJ$103>0) * (IFERROR(VLOOKUP($C$14:$C$103,tblCharacterCapture[[Character Name]:[Clan]],4,0),"")=$A1) * IFERROR(VLOOKUP($C$14:$C$103,tblCharacterCapture[[Character Name]:[City Status]],79,0),0) )} -> 0 | EO1: {=SUMPRODUCT( (ISNUMBER(EO$14:EO$103))*(EO$14:EO$103>0) * (IFERROR(VLOOKUP($C$14:$C$103,tblCharacterCapture[[Character Name]:[Clan]],4,0),"")=$A1) * IFERROR(VLOOKUP($C$14:$C$103,tblCharacterCapture[[Character Name]:[City Status]],79,0),0) )} -> 0 | ET1: {=SUMPRODUCT( (ISNUMBER(ET$14:ET$103))*(ET$14:ET$103>0) * (IFERROR(VLOOKUP($C$14:$C$103,tblCharacterCapture[[Character Name]:[Clan]],4,0),"")=$A1) * IFERROR(VLOOKUP($C$14:$C$103,tblCharacterCapture[[Character Name]:[City Status]],79,0),0) )} -> 0 | EY1: {=SUMPRODUCT( (ISNUMBER(EY$14:EY$103))*(EY$14:EY$103>0) * (IFERROR(VLOOKUP($C$14:$C$103,tblCharacterCapture[[Character Name]:[Clan]],4,0),"")=$A1) * IFERROR(VLOOKUP($C$14:$C$103,tblCharacterCapture[[Character Name]:[City Status]],79,0),0) )} -> 0 | FD1: {=SUMPRODUCT( (ISNUMBER(FD$14:FD$103))*(FD$14:FD$103>0) * (IFERROR(VLOOKUP($C$14:$C$103,tblCharacterCapture[[Character Name]:[Clan]],4,0),"")=$A1) * IFERROR(VLOOKUP($C$14:$C$103,tblCharacterCapture[[Character Name]:[City Status]],79,0),0) )} -> 0 | FI1: {=SUMPRODUCT( (ISNUMBER(FI$14:FI$103))*(FI$14:FI$103>0) * (IFERROR(VLOOKUP($C$14:$C$103,tblCharacterCapture[[Character Name]:[Clan]],4,0),"")=$A1) * IFERROR(VLOOKUP($C$14:$C$103,tblCharacterCapture[[Character Name]:[City Status]],79,0),0) )} -> 0 | FN1: {=SUMPRODUCT( (ISNUMBER(FN$14:FN$103))*(FN$14:FN$103>0) * (IFERROR(VLOOKUP($C$14:$C$103,tblCharacterCapture[[Character Name]:[Clan]],4,0),"")=$A1) * IFERROR(VLOOKUP($C$14:$C$103,tblCharacterCapture[[Character Name]:[City Status]],79,0),0) )} -> 0 | FS1: {=SUMPRODUCT( (ISNUMBER(FS$14:FS$103))*(FS$14:FS$103>0) * (IFERROR(VLOOKUP($C$14:$C$103,tblCharacterCapture[[Character Name]:[Clan]],4,0),"")=$A1) * IFERROR(VLOOKUP($C$14:$C$103,tblCharacterCapture[[Character Name]:[City Status]],79,0),0) )} -> 0 | FX1: {=SUMPRODUCT( (ISNUMBER(FX$14:FX$103))*(FX$14:FX$103>0) * (IFERROR(VLOOKUP($C$14:$C$103,tblCharacterCapture[[Character Name]:[Clan]],4,0),"")=$A1) * IFERROR(VLOOKUP($C$14:$C$103,tblCharacterCapture[[Character Name]:[City Status]],79,0),0) )} -> 0 | GC1: {=SUMPRODUCT( (ISNUMBER(GC$14:GC$103))*(GC$14:GC$103>0) * (IFERROR(VLOOKUP($C$14:$C$103,tblCharacterCapture[[Character Name]:[Clan]],4,0),"")=$A1) * IFERROR(VLOOKUP($C$14:$C$103,tblCharacterCapture[[Character Name]:[City Status]],79,0),0) )} -> 0
